Workbook
Name diet_items: AOM_diets!$M:$Q

Sheet bibliography

Sheet era_fields_v1
A1: Field.Name | B1: Data.Type | C1: Description | D1: Example
A2: Index | B2: Numeric | C2: A unique number identifiying an single observation (i.e. row) in ERA.
A3: Code | B3: Character | C3: Each paper is assigned a unique code that can be used to identify the source of the data in the database. The code consists of your initials (first and last name) and a sequential four-digit number that begins with 0000 and goes up 1 with each paper entered. | D3: TR0343
D4: NN1002
A5: Author | B5: Character | C5: The name of the first author, last name comes first with no punctuation. Use all initials given and do not include spaces between initials. | D5: Bucagu C
D6: Yamoah CF
A7: Date | B7: Positive Integer | C7: The year of publication.
A8: Journal | B8: Character | C8: Abbreviation of the journal name. We use WoS abbreviations that can be found here: https://images.webofknowledge.com/images/help/WOS/A_abrvjt.html | D8: Soil & Tillage Research = STR
C9: This field will autofill using the data in the Levels tab matching to the user selected journal name. | D9: Journal of Plant Nutrition = JPN
A10: DOI | B10: Character | C10: DOI (or url if no DOI available) of article. DOI = Digital Object Identifier.
A11: Elevation | B11: Integer | C11: The elevation in meters (m). Provide the mid-point if a range is given. | D11: 875
A12: Country | B12: Character | C12: Country Name | D12: Kenya
D13: Ivory Coast
A14: ISO.3166-1.alpha-3 | B14: Character | C14: Standardized country name using ISO.3166-1.alpha-3. This field should be auto filled using the country selected and data in the Levels Tab, | D14: KEN
D15: CIV
A16: Site.Type | B16: Character | C16: One of the following: Farm, Station, Greenhouse, Survey, or Lab. Farm research is conducted in a farmer’s field and can be managed by the farmer or researcher. Station research is conducted in a controlled setting of research station, university or school. Survey research is conducted via interviews that yields quantitative data based on testimonial. Greenhouse is conducted in a greenhouse and is only relevant for studies of greenhouse gas emissions data. Lab studies can include fisheries feeding trials conducted at a small scale in university research labs. | D16: Farm
A17: Site.ID | B17: Character | C17: Free text name to identify the site. Include institution/station name and location or village/town in county/district, but not the country. | D17: Chitedze ARS, Lilongwe
D18: IITA, Ibadan
A19: MAT | B19: Numeric | C19: Reported mean annual temperature in degrees C. If a range is given, average the values and enter the average. If mean highs and lows are given, they can be averaged to estimate the mean annual temperature.
A20: MAP | B20: Numeric | C20: Mean annual precipitation (mm) for the location. This should be a long-term average for more than 10 years of data.
A21: TAP | B21: Numeric | C21: Total annual precipitation (mm) for the location in the year corresponding to the outcome data
A22: MSP | B22: Numeric | C22: Mean seasonal precipitation (mm) for the location in the season corresponding to the outcome data. This should be a long-term average from more than 10 years of data.
A23: TSP | B23: Numeric | C23: Total seasonal precipitation (mm) for the location in the season corresponding to the outcome data
A24: Soil.Type | B24: Character | C24: List the given soil classification/name in lowercase letters. If more than one soil type is given (within the same taxonomic system) enter both separated by a period ‘.’ | D24: ferric lixisol
D25: lixisol.plinthisol
A26: Soil.Classification | B26: Character | C26: List the taxonomic system used to classify the soil. Choose from {FAO, USDA, other}. | D26: FAO
A27: Soil.Texture | B27: Character | C27: List the soil texture provided in the text or in tables in lowercase letters. If no texture is named, but % of sand, silt and clay are given, use the soil texture triangle to estimate soil texture (https://www.nrcs.usda.gov/wps/portal/nrcs/detail/soils/survey/?cid=nrcs142p2_054167). | D27: sandy loam
D28: clay
A29: SOC | B29: Numeric | C29: Soil organic carbon. If multiple soil depths are reported, use 0-20 cm, or the closest reported value. Do NOT use soil organic matter (SOM) or total carbon (TSC) measurements here. | D29: 3.4
D30: 0.54
A31: SOC.Unit | B31: Character | C31: Units provided for soil organic carbon. Usually either g/kg or % (also can be density kg/m3 or stocks t/ha) | D31: %
A32: SOC.Depth | B32: Character | C32: Concatenate min (top) and max (bottom) depths user entered with a ""-"", e.g. 0-10. | D32: 10
D33: 20
A34: Soil.pH | B34: Positive Integer | C34: Soil pH value derived during site characterization. If multiple methods for pH are given, report the water (H2O) method. | D34: 5.9
A35: Soil.pH.Method | B35: Character | C35: Method used to calculate soil pH. | D35: CaCl2
A36: Plant.Start | B36: Date | C36: Starting of planting period (dd.mm.yyyy) | D36: 01.12.2015
A37: Plant.End | B37: Date | C37: End of planting period (dd.mm.yyyy) | D37: 10.12.2015
A38: Harvest.Start | B38: Date | C38: Starting of harvest period (dd.mm.yyyy) | D38: 04.04.2016
A39: Harvest.End | B39: Date | C39: End of harvest period (dd.mm.yyyy) | D39: 05.04.2016
A40: Rep | B40: Positive Integer | C40: The number of replicates for the treatments. If the number varies between treatments, use the lowest number. If no number is given, leave blank. | D40: 4
A41: Plot.Size | B41: Positive Integer | C41: The size of the smallest treatment plot unit in m2. If plot dimensions are given, calculate the area in m2. For example, if the size of the subplots is 6m x 4m, the Plot.Size is 24 (m2). | D41: 10
A42: CID | B42: Character | C42: A unique identifier (within study) describing a set of management practices that occurred in the control which is used to identify the treatment combinations tested, to allow comparison across outcomes in a paper. A default system of T1, T2, T3, etc. can be used. CID should describe the treatment used as the control for this observation. | D42: C0
D43: C1
A44: C.Descrip | B44: Character | C44: [Superceded by C.Descrip.Clean column] Free text description of the control treatment. Use sufficient detail to easily identify the practices. | D44: Conventional tillage with 20 kg N/ha
A45: C.NI | B45: Character | C45: Amount of inorganic (chemical) nitrogen applied to control plots in kg/ha | D45: 20
A46: C.NO | B46: Character | C46: Amount of nitrogen in organic materials (manures or compost, but not residues) applied to control plots, preferably in kg/ha. If no nitrogen content is provided, please list amount of organic manure applied with a ‘t’ to symbolize tonnes. | D46: 40
D47: 5t
A48: TID | B48: Character | C48: A unique identifier (within study) describing a set of management practices that occurred in treatment which is used to identify the treatment combinations tested, to allow comparison across outcomes in a paper. A default system of T1, T2, T3, etc. can be used. TID should describe the treatment used as the control for this observation. | D48: T1
D49: T2
A50: T.Descrip | B50: Character | C50: [Superceded by T.Descrip.Clean column] Free text description of the CSA treatment. Use sufficient detail to easily identify all the component practices. | D50: Reduced tillage with mulch
A51: T.NI | B51: Numeric | C51: Amount of inorganic (chemical) nitrogen (N) applied to CSA treatment in kg/ha | D51: 80
A52: T.NO | B52: Numeric | C52: Amount of nitrogen (N) in organic materials (manures or compost) applied to CSA treatment, preferably in kg/ha. If no nitrogen content is provided, please list amount of organic manure applied with a ‘t’ to symbolize tonnes. | D52: 40
D53: 5t
A54: Diversity | B54: Character | C54: Name of species in intercrop or rotations including the crop, first letter of name capitilized and the rest lowercase. Use a dash (-) for intercrops and forward slash (/) for rotation. Use common names of species, unless agroforestry species, then use scientific name. This should be used for both crop and agroforestry intercroppings. | D54: Maize/Cotton/Bean
D55: Maize-Albizia gummifera
A56: Variety | B56: Character | C56: Commercial name of the crop or animal variety. Do not include the type of crop or animal in field (e.g. Maasai Red Goats should be Maasai Red). | D56: G2333
D57: Katumani
A58: Tree | B58: Character | C58: Name of tree species used in agroforestry experiments, can be both as an intercrop or as an agroforestry mulch. Please use scientific name and be careful of your spelling. Use full scientific name, do not abbreviate genus (e.g., Mangifera indica should not be abbreviated to M.indica). | D58: Gliricidia sepium
D59: Acacia abyssinica
A60: Duration | B60: Numeric | C60: Length of time the experiment has been ongoing up to the date the data are being reported for in years. In bimodal rainfall systems with multiple growing seasons, seasons are identified by fractions of the year, 0.5, etc. If outcomes are reported in a unimodal rainfall system with one growing season per year, the duration can be equivalent to one year. | D60: 0.5
D61: 1
D62: 5
A63: M.Year | B63: Character | C63: The calendar year the measurement was taken. Seasons in multi-season systems are identified by decimals ‘.1’ or ‘.2’ for the first and second season respectively. When the measurements are average values for more than one year create a decimal for the years covered. | D63: 1999
D64: 2002.2
D65: 1999.2004
A66: M.Year.Start | B66: Postive Integer | C66: First year the measurement was taken (YYYY). For yield or similar outcomes this should relate to the harvest year (rather than the planting year). Where data are aggregated across years also complete the Measurement End Year Field.
A67: M.Year.End | B67: Postive Integer | C67: This only required for temporally aggregated observations (e.g. a result that has been averaged from crop yields reported from 2000,2001 and 2002). Here report the last year of the period over for which observations were aggregated (in the previous example this would be 2002).
A68: Season.Start | B68: Postive Integer | C68: This only required in areas where there are mutiple growing seasons in a year (e.g., areas with bimodal rainfall or irrigated cropping in dry seasons of a unimodal system).
C69: Leave blank where there is only one growing season per year or no seasonal information is presented with the data.
C70: Code the season in order 1,2,etc. Determine the season sequence by harvest year. If there are two cropping seasons, with crops harvested in Feb and Sept, Feb = season 1 and Sept = season 2.
A71: Season.End | B71: Postive Integer | C71: This only required for temporally aggregated observations in areas with more than one growing season (e.g. a result that has been averaged from crop yields reported from 2000 season 1,2001 season 1 and 2002 season 1). Here report the last season of the period over for which observations were aggregated (in the previous example this would be 1).
A72: EU | B72: Character | C72: The experimental unit (EU) for which experiment outcomes are reported. This usually a crop or animal product. For cookstove papers it may be a cookstove. The EU for soil outcomes should be the crop(s) grown on the soil unless no crops are grown at all. Letters in the code should be lowercase. If the outcome refers to multiple experimental units (e.g. soil outcomes during an intercropping experiment) select all experimental units separated by a period (see EU2 tab).
A73: Outcode | B73: Character | C73: The productivity, resilience, or mitigation outcome indicator that data are being reported on (see OUTCOMES2 tab). | D73: 101
D74: 267
A75: Units | B75: Character | C75: Free text description of the units of the data being reported without special characters or formatting. | D75: kg/ha
A76: MeanC | B76: Numeric | C76: The value that corresponds to the control treatment and outcome. Please standard yields to t/ha where appropropriate, keeping as many decimal places as there is data for. | D76: 1.5
A77: MeanT | B77: Numeric | C77: The value that corresponds to the CSA treatment and outcome. Please standard yields to kg/ha where appropropriate, keeping as many decimal places as there is data for. | D77: 3.7
A78: Upper | B78: Numeric | C78: The depth for which the MeanC and MeanT correspond for soil properties in cm (lowest depth value = upper, so if you have a depth of 0-20 cm the lowest value = 20). | D78: 0
A79: Lower | B79: Numeric | C79: The depth for which the MeanC and MeanT correspond for soil properties in cm (highest depth value = lower, so if you have a depth of 0-20 cm the highest value = 0). | D79: 10
A80: DataLoc | B80: Character | C80: The location in the paper where the data can be found. This should be three letters (fig, tab, or txt) in lowercase and a number (for figures and tables) to signify figure, table or text, respectively. | D80: Fig. 1
D81: Table 2
A82: USD2010.C | B82: Numeric | C82: Monetary outcomes converted to International USD 2010 using World Bank CPI, PPP and exchange rates. There are no reliable data for Zimbabwe. | D82: 100
A83: USD2010.T | B83: Numeric | C83: Monetary outcomes converted to International USD 2010 using World Bank CPI, PPP and exchange rates. There are no reliable data for Zimbabwe. | D83: 100
A84: MeanFlip | B84: Character | C84: Is a negative result considered better than a positive result (i.e. MeanT/MeanC <1 = good)? This is indexed in using the Outcode field in the compednium and the ""Negative Values"" field in the OUTCOMES tab | D84: logical (T/F)
A85: T.Feed.Source | B85: Character | C85: Where were livestock diets in the treatment practice(s) sourced from? | D85: Purchased
D86: Produced On-farm
D87: Purchased & Produced On-farm
A88: C.Feed.Source | B88: Character | C88: Where were livestock diets in the control practice(s) sourced from? | D88: Purchased
D89: Produced On-farm
D90: Purchased & Produced On-farm
A91: Species | B91: Character | C91: The tree species for which the experiment outcome are reported
A92: Partial.Outcome.Name | B92: Character | C92: Free text to describe the partial outcome
A93: Analysis.Function | B93: Character | C93: Describes the logical process used to compare control to treatment (for developers)
A94: Version | B94: Numeric | C94: Year in which the ERA data entry took place. Either 2018 or 2020
A95: Irrigation.C | B95: Logical | C95: Indicates the presence of irrigation in the control treatment
A96: Irrigation.T | B96: Logical | C96: Indicates the presence of irrigation in the experimental treatment
A97: Irrig.Meth.C | B97: Character | C97: Method of irrigation used in the control treatment. Cell will be blank if Irrigation.C is FALSE
A98: Irrig.Meth.T | B98: Character | C98: Method of irrigation used in the experimental treatment. Cell will be blank if Irrigation.T is FALSE
A99: C1:Cn | B99: Character | C99: Codes corresponding to all practices used on the control treatment described in C.Descrip. Only one code is placed in each column (see subpractices column of PRACTICES2 tab). | D99: h10
A100: T1:Tn | B100: Character | C100: Codes corresponding to all practices used on the CSA treatment described in T.Descrip. Only one code is placed in each column (see subpractices column of PRACTICES2 tab). | D100: b38
...

Sheet era_fields_v2
A1: Table | B1: Table_Description | C1: Field | D1: majestic_hippo_2020 | E1: skinny_cow_2022 | F1: industrious_elephant_2023 | G1: courageous_camel_2024 | H1: key_type | I1: source_table | J1: lookup_table | K1: Calculated | L1: Display_Name | M1: Data_Type | N1: Field_Description | O1: Notes | P1: Values | Q1: Validation | R1: Required | S1: Ref_Source | T1: Ref_Name | U1: Ref_Link | V1: Ref_Match | W1: Ref_Notes | X1: Translation source | Y1: Spanish Translation | Z1: Ref2_DataScribe | AA1: Ref2_Source | AB1: Ref2_Name | AC1: Ref2_Link | AD1: Ref2_Match | AE1: Ref2_Notes | AF1: Other_Links
A2: Pub.Out | B2: This table captures bibliographic information. Each publication is assigned a unique code in the B.Code field that acts a key field in all other extraction template tables. | C2: B.Code | D2: TRUE | E2: TRUE | F2: TRUE | G2: TRUE | H2: p | K2: Yes | L2: ERA Publication Code | M2: Character | N2: A unique code that identifies an extracted publication in the ERA dataset. This code is present in all the tables of era extraction data models. | P2: concatenation of unique userID and a number | Q2: NA | R2: NA | S2: NA | T2: NA | U2: NA | V2: NA | W2: NA | Z2: NA | AA2: NA | AB2: NA | AC2: NA | AD2: NA | AE2: NA | AF2: NA
A3: Pub.Out | B3: =B2 -> This table captures bibliographic information. Each publication is assigned a unique code in the B.Code field that acts a key field in all other extraction template tables. | C3: B.Author.Last | D3: TRUE | E3: TRUE | F3: TRUE | G3: TRUE | K3: No | L3: Author Last Name | M3: Character | N3: Publication first author's surname. | P3: Free Text | Q3: NA | R3: NA
A4: Pub.Out | B4: =B3 -> This table captures bibliographic information. Each publication is assigned a unique code in the B.Code field that acts a key field in all other extraction template tables. | C4: B.Date | D4: TRUE | E4: TRUE | F4: TRUE | G4: TRUE | K4: No | L4: Year Published | M4: Integer (YYYY) | N4: The year of publication. | P4: NA | Q4: Integer >1950 & <=Present Year | R4: Yes
A5: Pub.Out | B5: =B4 -> This table captures bibliographic information. Each publication is assigned a unique code in the B.Code field that acts a key field in all other extraction template tables. | C5: B.Journal | D5: TRUE | E5: TRUE | F5: TRUE | G5: TRUE | K5: No | L5: Journal | M5: Character | N5: Name of journal this research is published in. | P5: SCiO should have some ideas how to populate this field | Q5: NA | R5: Yes
A6: Pub.Out | B6: =B5 -> This table captures bibliographic information. Each publication is assigned a unique code in the B.Code field that acts a key field in all other extraction template tables. | C6: B.DOI | D6: TRUE | E6: TRUE | F6: TRUE | G6: TRUE | K6: No | L6: DOI | M6: Character | N6: Digital object identifier (DOI) for the publication (e.g. 10.1080/03650340.2017.1411589). Do not include https://doi.org/ when entering this. Please strip the “https://doi.org/” when entering a doi . Correct = “10.1002/jrsm.1563”, Incorrect = “https://doi.org/10.1002/jrsm.1563”. If there is no DOI for a publication then report the https address of the article. | P6: Free Text | Q6: Strip out https:// | R6: One of B.Doi or B.Url required
A7: Pub.Out | B7: =B6 -> This table captures bibliographic information. Each publication is assigned a unique code in the B.Code field that acts a key field in all other extraction template tables. | C7: B.Url | D7: TRUE | E7: TRUE | F7: TRUE | G7: TRUE | K7: No | L7: Website | M7: Character | N7: For a publication with no DOI, please enter the full website address where it can be found. | O7: Has this field been merged with doi in the new data model | P7: Free Text | Q7: Should be a web address | R7: One of B.Doi or B.Url required
A8: Pub.Out | B8: =B7 -> This table captures bibliographic information. Each publication is assigned a unique code in the B.Code field that acts a key field in all other extraction template tables. | C8: B.Project | D8: TRUE | E8: TRUE | F8: TRUE | G8: TRUE | K8: No | L8: Project | M8: Character | N8: Name the project of the current extraction round | P8: Data extractions will relate to specific projects/budgets/modules this field will link to a table of projects that the user can define, or a user is assigned to a specific project and it autofills. | Q8: NA | R8: Yes
A9: Pub.Out | B9: =B8 -> This table captures bibliographic information. Each publication is assigned a unique code in the B.Code field that acts a key field in all other extraction template tables. | C9: B.Link1 | D9: TRUE | E9: TRUE | F9: TRUE | G9: TRUE | K9: No | L9: Linked Publication DOI/Website 1 | M9: Character | N9: Publications that are referenced in this publication that may present results from the same experiment. | P9: Free Text | Q9: Should be a web address or DOI | R9: No
A10: Pub.Out | B10: =B9 -> This table captures bibliographic information. Each publication is assigned a unique code in the B.Code field that acts a key field in all other extraction template tables. | C10: B.Link2 | D10: TRUE | E10: TRUE | F10: TRUE | G10: TRUE | K10: No | L10: Linked Publication DOI/Website 2 | M10: Character | N10: Publications that are referenced in this publication that may present results from the same experiment. | P10: Free Text | Q10: Should be a web address or DOI | R10: No
A11: Pub.Out | B11: =B10 -> This table captures bibliographic information. Each publication is assigned a unique code in the B.Code field that acts a key field in all other extraction template tables. | C11: B.Link3 | D11: TRUE | E11: TRUE | F11: TRUE | G11: TRUE | K11: No | L11: Linked Publication DOI/Website 3 | M11: Character | N11: Publications that are referenced in this publication that may present results from the same experiment. | P11: Free Text | Q11: Should be a web address or DOI | R11: No
A12: Pub.Out | B12: =B11 -> This table captures bibliographic information. Each publication is assigned a unique code in the B.Code field that acts a key field in all other extraction template tables. | C12: B.Link4 | D12: TRUE | E12: TRUE | F12: TRUE | G12: TRUE | K12: No | L12: Linked Publication DOI/Website 4 | M12: Character | N12: Publications that are referenced in this publication that may present results from the same experiment. | P12: Free Text | Q12: Should be a web address or DOI | R12: No
A13: Site.Out | B13: Here we record the geographic co-ordinates of where an experiment has taken place and the uncertainty associated with this. You can record multiple locations. For each site you can also capture general biophysical information about the site and the starting conditions that describe the soils of the site. | C13: Site.Type | D13: TRUE | E13: TRUE | F13: TRUE | G13: TRUE | K13: No | L13: What is the context of the experiment? | M13: Character | N13: This describes the nature of the field and who is managing it | P13: lookup_levels$Site.Type | Q13: NA | R13: Yes
A14: Site.Out | B14: Here we record the geographic co-ordinates of where an experiment has taken place and the uncertainty associated with this. You can record multiple locations. For each site you can also capture general biophysical information about the site and the starting conditions that describe the soils of the site. | C14: Country | D14: TRUE | E14: TRUE | F14: TRUE | G14: TRUE | K14: No | L14: Country | M14: Character | N14: Country where the study is performed | P14: Country$Countries | Q14: NA | R14: Yes
A15: Site.Out | B15: Here we record the geographic co-ordinates of where an experiment has taken place and the uncertainty associated with this. You can record multiple locations. For each site you can also capture general biophysical information about the site and the starting conditions that describe the soils of the site. | C15: Site.ID | D15: TRUE | E15: TRUE | F15: TRUE | G15: TRUE | H15: p | K15: No | L15: Site Name | M15: Character | N15: If you select a site name that already exists in ERA, the latitude and longitude fields will auto-populate. Please check the auto-generated co-ordinates against the ones reported in the publication and in GoogleMaps/Earth. If there is a mismatch you can overwrite the autogenerated values. | P15: Free Text/Can choose exisiting Site.ID for specified Country within the database or add a new one, perhaps the list should also be subset by Site experimental type. If co-ordinates are changed for the site we need to Flag this to check. | Q15: None | R15: Yes
A16: Site.Out | B16: Here we record the geographic co-ordinates of where an experiment has taken place and the uncertainty associated with this. You can record multiple locations. For each site you can also capture general biophysical information about the site and the starting conditions that describe the soils of the site. | C16: Site.Admin | D16: TRUE | E16: TRUE | F16: TRUE | G16: TRUE | K16: No | L16: How is the location reported? | M16: Character | N16: A qualitative measure of how accurate you think the location reporting is. If the study is at a research station, but we only know the location of the city where the station is, we record "City". If we know the exact location of the station record "Facility". | P16: lookup_levels$Site.Admin | Q16: NA | R16: Yes
A17: Site.Out | B17: Here we record the geographic co-ordinates of where an experiment has taken place and the uncertainty associated with this. You can record multiple locations. For each site you can also capture general biophysical information about the site and the starting conditions that describe the soils of the site. | C17: Site.Agg | D17: TRUE | E17: TRUE | F17: TRUE | G17: TRUE | K17: No | L17: Does the location contain sub-locations? | M17: Character | N17: State yes if a paper reports a general location which contains sub-locations that you do not know the co-ordinates of. For example a paper might state "we repeated the experiment on 10 farms in 5 villages in Busia county, Kenya" so we have a county location and know there are 5 village sub-locations in this county, we don't know where these villages are and results are reported averaged across all the farms and villages. If we know the location or names of the villages (e.g. results are reported per village) then we create one site per village and state "no" in this field. | P17: Yes, No | Q17: NA | R17: Yes
A18: Site.Out | B18: Here we record the geographic co-ordinates of where an experiment has taken place and the uncertainty associated with this. You can record multiple locations. For each site you can also capture general biophysical information about the site and the starting conditions that describe the soils of the site. | C18: ISO.3166.1.alpha.3 | D18: FALSE | E18: TRUE | F18: TRUE | G18: TRUE | K18: No | L18: Enter the Iso Code of the Country | M18: Character | N18: Three letters code for countries | O18: this is not in the excel but in the dataset in R | Q18: NA | R18: No
A19: Site.Out | B19: Here we record the geographic co-ordinates of where an experiment has taken place and the uncertainty associated with this. You can record multiple locations. For each site you can also capture general biophysical information about the site and the starting conditions that describe the soils of the site. | C19: Site.LatD | D19: TRUE | E19: TRUE | F19: TRUE | G19: TRUE | K19: No | L19: Latitude (Decimal Degrees) | M19: Numeric | N19: Longitude and latitude are geographic coordinates that specify the position of a point on the Earth's surface, with longitude measuring east-west position and latitude measuring north-south position | P19: NA | Q19: Should be within the country selected. | R19: Yes
A20: Site.Out | B20: Here we record the geographic co-ordinates of where an experiment has taken place and the uncertainty associated with this. You can record multiple locations. For each site you can also capture general biophysical information about the site and the starting conditions that describe the soils of the site. | C20: Site.Lat.Unc | D20: TRUE | E20: TRUE | F20: TRUE | G20: TRUE | K20: No | L20: Latitude Uncertainty (m) | M20: Numeric | N20: An important field used where a location is a region (e.g. a county or district polygon) which has a bounding box that is more rectangular than square (if square then just used the Uncertainty (Radius in m) field). Give the height of the region NAMITA IS THIS THE TOTAL HEIGHT OR HALF THE HEIGHT in meters? | P20: NA | Q20: Values <=10m are suspicious (this would be very tiny region or experiment) | R20: Yes if Site.Buffer.Manual is blank or Site.Lon.Unc is not blank
A21: Site.Out | B21: Here we record the geographic co-ordinates of where an experiment has taken place and the uncertainty associated with this. You can record multiple locations. For each site you can also capture general biophysical information about the site and the starting conditions that describe the soils of the site. | C21: Site.LonD | D21: TRUE | E21: TRUE | F21: TRUE | G21: TRUE | K21: No | L21: Longitude (Decimal Degrees) | M21: Numeric | N21: Longitude and latitude are geographic coordinates that specify the position of a point on the Earth's surface, with longitude measuring east-west position and latitude measuring north-south position | P21: NA | Q21: Should be within the country selected. | R21: Yes
A22: Site.Out | B22: Here we record the geographic co-ordinates of where an experiment has taken place and the uncertainty associated with this. You can record multiple locations. For each site you can also capture general biophysical information about the site and the starting conditions that describe the soils of the site. | C22: Site.Lon.Unc | D22: TRUE | E22: TRUE | F22: TRUE | G22: TRUE | K22: No | L22: Longitude Uncertainty (m) | M22: Numeric | N22: An important field used where a location is a region (e.g. a county or district polygon) which has a bounding box that is more rectangular than square (if square then just used the Uncertainty (Radius in m) field). Give the width of the region NAMITA IS THIS THE TOTAL HEIGHT OR HALF THE HEIGHT in meters? | Q22: Values <=10m are suspicious (this would be very tiny region or experiment) | R22: Yes if Site.Buffer.Manual is blank or Site.Lat.Unc is not blank
A23: Site.Out | B23: Here we record the geographic co-ordinates of where an experiment has taken place and the uncertainty associated with this. You can record multiple locations. For each site you can also capture general biophysical information about the site and the starting conditions that describe the soils of the site. | C23: Site.Buffer.Manual | D23: TRUE | E23: TRUE | F23: TRUE | G23: TRUE | K23: No | L23: Uncertainty (Radius in m) | M23: Numeric | N23: An important field used to indicate spatial uncertainty where a location is a point or a region (e.g. a county or district polygon) with a square bounding box. Give the radius of uncertainty in meter for the point or region (so the distance from the centre of the region or study plot to the edge). If the study site is a research station you take the centre of the research station to the edge of the station. | Q23: Values <=10m are suspicious (this would be very tiny region or experiment) | R23: Yes if Site.Lat.Unc & Site.Lon.Unc are not blank, not allowed to be filled if Site.Lat.Unc|Site.Lon.Unc are not blank.
A24: Site.Out | B24: Here we record the geographic co-ordinates of where an experiment has taken place and the uncertainty associated with this. You can record multiple locations. For each site you can also capture general biophysical information about the site and the starting conditions that describe the soils of the site. | C24: Site.Rain.Seasons | D24: TRUE | E24: TRUE | F24: TRUE | G24: TRUE | K24: No | L24: Number of Rainy Seasons | M24: Integer | N24: Number of rainy seasons | P24: 1,2,Year Round,Unspecified,NA | Q24: NA | R24: Yes
A25: Site.Out | B25: Here we record the geographic co-ordinates of where an experiment has taken place and the uncertainty associated with this. You can record multiple locations. For each site you can also capture general biophysical information about the site and the starting conditions that describe the soils of the site. | C25: Site.Start.S1 | D25: TRUE | E25: TRUE | F25: TRUE | G25: TRUE | K25: No | L25: Season1 Start | M25: Character | N25: start date of the first season | P25: lookup_levels$Site.Seasons | Q25: NA | R25: No
A26: Site.Out | B26: Here we record the geographic co-ordinates of where an experiment has taken place and the uncertainty associated with this. You can record multiple locations. For each site you can also capture general biophysical information about the site and the starting conditions that describe the soils of the site. | C26: Site.End.S1 | D26: TRUE | E26: TRUE | F26: TRUE | G26: TRUE | K26: No | L26: Season1 End | M26: Character | N26: end date of the first season | P26: lookup_levels$Site.Seasons | Q26: NA | R26: No
A27: Site.Out | B27: Here we record the geographic co-ordinates of where an experiment has taken place and the uncertainty associated with this. You can record multiple locations. For each site you can also capture general biophysical information about the site and the starting conditions that describe the soils of the site. | C27: Site.Length.S1 | D27: TRUE | E27: TRUE | F27: TRUE | G27: TRUE | K27: No | L27: Rainy Season 1 Length (days) | M27: Integer | N27: Length of the first season | P27: NA | Q27: <=365, warning if >=200 and not in RCongo or DRCongo | R27: No
A28: Site.Out | B28: Here we record the geographic co-ordinates of where an experiment has taken place and the uncertainty associated with this. You can record multiple locations. For each site you can also capture general biophysical information about the site and the starting conditions that describe the soils of the site. | C28: Site.Start.S2 | D28: TRUE | E28: TRUE | F28: TRUE | G28: TRUE | K28: No | L28: Season2 Start | M28: Character | N28: start date of the second season | P28: lookup_levels$Site.Seasons | Q28: NA | R28: No
A29: Site.Out | B29: Here we record the geographic co-ordinates of where an experiment has taken place and the uncertainty associated with this. You can record multiple locations. For each site you can also capture general biophysical information about the site and the starting conditions that describe the soils of the site. | C29: Site.End.S2 | D29: TRUE | E29: TRUE | F29: TRUE | G29: TRUE | K29: No | L29: Season2 End | M29: Character | N29: end date of the second season | P29: lookup_levels$Site.Seasons | Q29: NA | R29: No
A30: Site.Out | B30: Here we record the geographic co-ordinates of where an experiment has taken place and the uncertainty associated with this. You can record multiple locations. For each site you can also capture general biophysical information about the site and the starting conditions that describe the soils of the site. | C30: Site.Length.S2 | D30: TRUE | E30: TRUE | F30: TRUE | G30: TRUE | K30: No | L30: Rainy Season 2 Length (days) | M30: Integer | N30: length of the second season | P30: NA | Q30: Value<(365-Site.Length.S1) | R30: No
A31: Site.Out | B31: Here we record the geographic co-ordinates of where an experiment has taken place and the uncertainty associated with this. You can record multiple locations. For each site you can also capture general biophysical information about the site and the starting conditions that describe the soils of the site. | C31: Site.MSP.S1 | D31: TRUE | E31: TRUE | F31: TRUE | G31: TRUE | K31: No | L31: Mean Seasonal Precipitation (mm) - S1 | M31: Integer | N31: Mean Precipitation for the first season | P31: NA | Q31: Range 0 to 9000. Warning on values not in range 200 to 4000. This could be linked to a country table. | R31: No
A32: Site.Out | B32: Here we record the geographic co-ordinates of where an experiment has taken place and the uncertainty associated with this. You can record multiple locations. For each site you can also capture general biophysical information about the site and the starting conditions that describe the soils of the site. | C32: Site.MSP.S2 | D32: TRUE | E32: TRUE | F32: TRUE | G32: TRUE | K32: No | L32: Mean Seasonal Precipitation (mm) - S2 | M32: Integer | N32: Mean Precipitation fot the second season | P32: NA | Q32: Range 0 to 9000. Warning on values not in range 200 to 4000. This could be linked to a country table. | R32: No
A33: Site.Out | B33: Here we record the geographic co-ordinates of where an experiment has taken place and the uncertainty associated with this. You can record multiple locations. For each site you can also capture general biophysical information about the site and the starting conditions that describe the soils of the site. | C33: Site.MAP | D33: TRUE | E33: TRUE | F33: TRUE | G33: TRUE | K33: No | L33: Mean Annual Rainfall (mm) | M33: Integer | N33: This field is used to report the long-term avergae mean annual rainfall of the location. Rainall that is reported for a specific season or year during the experiment should be recorded in the times tab | P33: NA | Q33: Range 0 to 9000. Warning on values not in range 200 to 4000. This could be linked to a country table. | R33: No
A34: Site.Out | B34: Here we record the geographic co-ordinates of where an experiment has taken place and the uncertainty associated with this. You can record multiple locations. For each site you can also capture general biophysical information about the site and the starting conditions that describe the soils of the site. | C34: Site.MAT | D34: TRUE | E34: TRUE | F34: TRUE | G34: TRUE | K34: No | L34: Mean Annual Temperature (°C) | M34: Integer | N34: This field is used to report the long-term avergae mean annual temperature of the location. Temperature that is reported for a specific season or year during the experiment should be recorded in the times tab | P34: NA | Q34: Range 5 to 45. Warning on values not in range 10 to 35. | R34: No
A35: Site.Out | B35: Here we record the geographic co-ordinates of where an experiment has taken place and the uncertainty associated with this. You can record multiple locations. For each site you can also capture general biophysical information about the site and the starting conditions that describe the soils of the site. | C35: Site.Elevation | D35: TRUE | E35: TRUE | F35: TRUE | G35: TRUE | K35: No | L35: Elevation (masl) | M35: Integer | N35: Elevation in meters above sea level | P35: NA | Q35: Range -200 to 5000. Warning on values not in range to 5 to 3500. | R35: No
... A38: Site.Out | B38: Here we record the geographic co-ordinates of where an experiment has taken place and the uncertainty associated with this. You can record multiple locations. For each site you can also capture general biophysical information about the site and the starting conditions that describe the soils of the site. | C38: Site.Soil.Texture | D38: TRUE | E38: TRUE | F38: TRUE | G38: TRUE | K38: No | L38: Soil Texture | M38: Character | N38: Texture of the soil site | P38: lookup_levels$Soil.Texture | Q38: NA | R38: No
A39: Site.Out | B39: Here we record the geographic co-ordinates of where an experiment has taken place and the uncertainty associated with this. You can record multiple locations. For each site you can also capture general biophysical information about the site and the starting conditions that describe the soils of the site. | C39: Site.Notes | D39: TRUE | E39: TRUE | F39: TRUE | G39: TRUE | K39: No | L39: Site.Notes | M39: Character | P39: Free Text | Q39: NA | R39: No
A40: Site.Out | B40: Here we record the geographic co-ordinates of where an experiment has taken place and the uncertainty associated with this. You can record multiple locations. For each site you can also capture general biophysical information about the site and the starting conditions that describe the soils of the site. | C40: B.Code | D40: TRUE | E40: TRUE | F40: TRUE | G40: TRUE | H40: f | I40: Pub.Out | K40: Yes | L40: NA | M40: Character | N40: =N$2 -> A unique code that identifies an extracted publication in the ERA dataset. This code is present in all the tables of era extraction data models. | P40: Pub.Out$B.Code | Q40: NA | R40: NA | S40: NA | T40: NA | U40: NA | V40: NA | W40: NA | Z40: NA | AA40: NA | AB40: NA | AC40: NA | AD40: NA | AE40: NA | AF40: NA
A41: Soil.Out | B41: This section is used to record detailed soil properties at the beginning of an experiment, including texture, pH, nutrient content, and other relevant information. You can add several lines to the table where soil properties are reported for multiple depths. Don't record soil properties measured after an experiment has begun here. | C41: Site.ID | D41: TRUE | E41: TRUE | F41: TRUE | G41: TRUE | H41: f | I41: Site.Out | K41: No | L41: Site Name | M41: Character | N41: If you select a site name that already exists in ERA, the latitude and longitude fields will auto-populate. Please check the auto-generated co-ordinates against the ones reported in the publication and in GoogleMaps/Earth. If there is a mismatch you can overwrite the autogenerated values. | P41: Free Text/Can choose exisiting Site.ID for specified Country within the database or add a new one, perhaps the list should also be subset by Site experimental type. If co-ordinates are changed for the site we need to Flag this to check. | Q41: None | R41: Yes | S41: NA | T41: NA | U41: NA | V41: NA | W41: NA | X41: Camila | Y41: Nombre del sitio
A43: Soil.Out | B43: This section is used to record detailed soil properties at the beginning of an experiment, including texture, pH, nutrient content, and other relevant information. You can add several lines to the table where soil properties are reported for multiple depths. Don't record soil properties measured after an experiment has begun here. | C43: Soil.Upper | D43: TRUE | E43: TRUE | F43: TRUE | G43: TRUE | K43: No | L43: Depth (cm) Upper | M43: Numeric | N43: The upper limit of depth at which soil samples are collected for analysis of soil properties such as texture, pH, and nutrient content. | P43: NA | Q43: Range 0 to 500, Soil.Upper>=Soil.Lower | R43: Yes | S43: AGROVOC | T43: depth | U43: http://aims.fao.org/aos/agrovoc/c_2190 | V43: Partial | W43: measure > dimensions > depth | X43: Camila | Y43: Profundidad
A44: Soil.Out | B44: This section is used to record detailed soil properties at the beginning of an experiment, including texture, pH, nutrient content, and other relevant information. You can add several lines to the table where soil properties are reported for multiple depths. Don't record soil properties measured after an experiment has begun here. | C44: Soil.Lower | D44: TRUE | E44: TRUE | F44: TRUE | G44: TRUE | K44: No | L44: Depth (cm) Lower | M44: Numeric | N44: The lower limit of depth at which soil samples are collected for analysis of soil properties such as texture, pH, and nutrient content. The lower depth will be greater than the upper depth | P44: NA | Q44: Range 0 to 500, Soil.Lower>=Soil.Upper | R44: Yes | S44: AGROVOC | T44: depth | U44: http://aims.fao.org/aos/agrovoc/c_2190 | V44: Partial | W44: measure > dimensions > depth | X44: Camila | Y44: Profundidad
A45: Soil.Out | B45: This section is used to record detailed soil properties at the beginning of an experiment, including texture, pH, nutrient content, and other relevant information. You can add several lines to the table where soil properties are reported for multiple depths. Don't record soil properties measured after an experiment has begun here. | C45: variable | D45: FALSE | E45: TRUE | F45: TRUE | G45: FALSE | K45: No | L45: Soil variable measured | M45: Character | N45: Select the variable measured on soil | P45: Free Text
A46: Soil.Out | B46: This section is used to record detailed soil properties at the beginning of an experiment, including texture, pH, nutrient content, and other relevant information. You can add several lines to the table where soil properties are reported for multiple depths. Don't record soil properties measured after an experiment has begun here. | C46: value | D46: FALSE | E46: TRUE | F46: TRUE | G46: FALSE | K46: No | L46: Value of the measured variable | M46: Numeric | N46: Enter the measure of the soil variable | P46: Free_Text
A47: Soil.Out | B47: This section is used to record detailed soil properties at the beginning of an experiment, including texture, pH, nutrient content, and other relevant information. You can add several lines to the table where soil properties are reported for multiple depths. Don't record soil properties measured after an experiment has begun here. | C47: Unit | D47: FALSE | E47: TRUE | F47: TRUE | G47: FALSE | K47: No | L47: Unit of the value of the measured variable | M47: Character | N47: Unit of the soil variable | P47: lookup?
A48: Soil.Out | B48: This section is used to record detailed soil properties at the beginning of an experiment, including texture, pH, nutrient content, and other relevant information. You can add several lines to the table where soil properties are reported for multiple depths. Don't record soil properties measured after an experiment has begun here. | C48: Method | D48: FALSE | E48: TRUE | F48: TRUE | G48: FALSE | K48: No | L48: Method for the measured variable | M48: Character | N48: Method to measure the soil variable | P48: lookup?
A49: Soil.Out | B49: This section is used to record detailed soil properties at the beginning of an experiment, including texture, pH, nutrient content, and other relevant information. You can add several lines to the table where soil properties are reported for multiple depths. Don't record soil properties measured after an experiment has begun here. | C49: SND | D49: TRUE | E49: TRUE | F49: FALSE | G49: TRUE | K49: No | L49: Sand (%) | M49: Numeric | N49: Content of mineral particles with sizes between 63µm-2mm in soil. Note: According to different national and international particle-size classification systems, size classes may differ slightly. Source: AGROVOC | P49: NA | Q49: Range 0 to 100, SND<=(100-SLT-CLY) | R49: No | S49: AGROVOC | T49: soil separates sand | U49: http://aims.fao.org/aos/agrovoc/c_7190 | V49: Partial | W49: properties > soil properties > soil chemicophysical properties > soil texture > soil separates substances > rock > sand | X49: Camila | Y49: Arena
A50: Soil.Out | B50: This section is used to record detailed soil properties at the beginning of an experiment, including texture, pH, nutrient content, and other relevant information. You can add several lines to the table where soil properties are reported for multiple depths. Don't record soil properties measured after an experiment has begun here. | C50: SLT | D50: TRUE | E50: TRUE | F50: FALSE | G50: TRUE | K50: No | L50: Silt (%) | M50: Numeric | N50: Content of mineral particles with sizes between 2-63µm in soil. Note: According to different national and international particle-size classification systems, size classes may differ slightly. Source: AGROVOC | P50: NA | Q50: Range 0 to 100, SLT<=(100-SND-CLY) | R50: No | S50: AGROVOC | T50: soil separates silt | U50: http://aims.fao.org/aos/agrovoc/c_7190 http://aims.fao.org/aos/agrovoc/c_331558 | V50: Partial | W50: properties > soil properties > soil chemicophysical properties > soil texture > soil separates substances > sediment > silt | X50: Camila | Y50: Limo
A51: Soil.Out | B51: This section is used to record detailed soil properties at the beginning of an experiment, including texture, pH, nutrient content, and other relevant information. You can add several lines to the table where soil properties are reported for multiple depths. Don't record soil properties measured after an experiment has begun here. | C51: CLY | D51: TRUE | E51: TRUE | F51: FALSE | G51: TRUE | K51: No | L51: Clay (%) | M51: Numeric | N51: Very fine mineral particles smaller than 2 µm. Source: AGROVOC | P51: NA | Q51: Range 0 to 100, CLY<=(100-SND-SLT) | R51: No | S51: AGROVOC | T51: clay | U51: http://aims.fao.org/aos/agrovoc/c_15619 | V51: Yes | W51: ... > soil properties > soil chemicophysical properties > soil texture > soil separates > clay substances > rock > clay | X51: Camila | Y51: Arcilla
A52: Soil.Out | B52: This section is used to record detailed soil properties at the beginning of an experiment, including texture, pH, nutrient content, and other relevant information. You can add several lines to the table where soil properties are reported for multiple depths. Don't record soil properties measured after an experiment has begun here. | C52: Soil.BD | D52: TRUE | E52: TRUE | F52: FALSE | G52: FALSE | K52: No | L52: Bulk Density (BD) | M52: Numeric | N52: Also called Soil Density. Soil bulk density is the weight of soil per unit volume, expressed in g/cm3 or Mg/m3, and is an indicator of soil compaction or looseness, which affects root growth, water infiltration, and nutrient availability. | P52: NA | Q52: Depends on Unit | R52: No | S52: AGROVOC | T52: soil density | U52: http://aims.fao.org/aos/agrovoc/c_7167 | V52: Yes | W52: properties > soil properties > soil chemicophysical properties > soil density | X52: Camila | Y52: Densidad aparente
A53: Soil.Out | B53: This section is used to record detailed soil properties at the beginning of an experiment, including texture, pH, nutrient content, and other relevant information. You can add several lines to the table where soil properties are reported for multiple depths. Don't record soil properties measured after an experiment has begun here. | C53: Soil.TC | D53: TRUE | E53: TRUE | F53: FALSE | G53: FALSE | K53: No | L53: Total Carbon (TC) | M53: Numeric | N53: Content or amount of total carbon in soil, including organic carbon and carbon from lime. Source: AGROVOC | P53: NA | Q53: Depends on Unit | R53: No | S53: AGROVOC | T53: total carbon | U53: http://aims.fao.org/aos/agrovoc/c_24fb4269 | V53: Yes | W53: properties > soil properties > soil chemicophysical properties > total carbon | X53: Camila | Y53: Carbono total
A54: Soil.Out | B54: This section is used to record detailed soil properties at the beginning of an experiment, including texture, pH, nutrient content, and other relevant information. You can add several lines to the table where soil properties are reported for multiple depths. Don't record soil properties measured after an experiment has begun here. | C54: Soil.SOC | D54: TRUE | E54: TRUE | F54: FALSE | G54: FALSE | K54: No | L54: Soil Organic Carbon Content (SOC) | M54: Numeric | N54: Soil organic carbon (SOC) content is a measure of the amount of carbon present in the soil in the form of organic matter, such as dead plant and animal material, that has not yet decomposed into inorganic carbon dioxide. SOC content is expressed as a percentage or weight of carbon per unit of soil mass and is a critical indicator of soil health and fertility. Soil organic carbon (SOC) is a component of soil organic matter (SOM) and represents the carbon-containing fraction of SOM. | P54: NA | Q54: Depends on Unit | R54: No | S54: AGROVOC | T54: soil organic carbon | U54: http://aims.fao.org/aos/agrovoc/c_389fe908 | V54: Yes | W54: substances > organic matter > soil organic matter > soil organic carbon | X54: Camila | Y54: Contenido de carbono organico
A55: Soil.Out | B55: This section is used to record detailed soil properties at the beginning of an experiment, including texture, pH, nutrient content, and other relevant information. You can add several lines to the table where soil properties are reported for multiple depths. Don't record soil properties measured after an experiment has begun here. | C55: Soil.SOM | D55: TRUE | E55: TRUE | F55: FALSE | G55: FALSE | K55: No | L55: Soil Organic Matter Content (SOM) | M55: Numeric | N55: Soil organic matter (SOM) content, includes both living and dead organic matter in the soil, such as plant roots, microorganisms, and decomposing organic materials. SOM is a more comprehensive measure of the total organic matter in the soil (than SOC), including both the stable and labile fractions, and is a key indicator of soil quality and productivity. While SOC is a subset of SOM, SOM takes into account the complex interactions among different organic matter components and soil properties, making it a more comprehensive indicator of soil health. | P55: NA | Q55: Depends on Unit | R55: No | S55: AGROVOC | T55: soil organic matter | U55: http://aims.fao.org/aos/agrovoc/c_35657 | V55: Yes | W55: substances > organic matter > soil organic matter | X55: Camila | Y55: Contenido de materia organica
A56: Soil.Out | B56: This section is used to record detailed soil properties at the beginning of an experiment, including texture, pH, nutrient content, and other relevant information. You can add several lines to the table where soil properties are reported for multiple depths. Don't record soil properties measured after an experiment has begun here. | C56: Soil.pH | D56: TRUE | E56: TRUE | F56: FALSE | G56: TRUE | K56: No | L56: Soil pH | M56: Numeric | N56: Soil pH is a measure of the acidity or alkalinity of the soil, expressed as the negative logarithm of the hydrogen ion concentration (pH scale ranges from 0 to 14). The pH scale is logarithmic, so each whole number represents a tenfold difference in acidity or alkalinity. Soil pH is a critical parameter for soil fertility and plant growth, as it influences nutrient availability, microbial activity, and soil structure. | P56: NA | Q56: Range 3 to 11, warning if <4 or >10 | R56: No | S56: AGROVOC | T56: soil pH | U56: http://aims.fao.org/aos/agrovoc/c_34901 | V56: Yes | W56: properties > chemicophysical properties > pH > soil pH measure > pH > soil pH properties > soil properties > soil chemicophysical properties > soil pH | X56: Camila | Y56: pH del suelo
A57: Soil.Out | B57: This section is used to record detailed soil properties at the beginning of an experiment, including texture, pH, nutrient content, and other relevant information. You can add several lines to the table where soil properties are reported for multiple depths. Don't record soil properties measured after an experiment has begun here. | C57: Soil.CEC | D57: TRUE | E57: TRUE | F57: FALSE | G57: FALSE | K57: No | L57: Cation Exchange Capacity (CEC) | M57: Numeric | N57: Cation Exchange Capacity (CEC) is a measure of the soil's ability to hold positively charged ions, known as cations, and is expressed as the number of milliequivalents of cations per 100 grams of soil. CEC is a critical parameter for soil fertility, as it influences the soil's ability to retain and supply essential plant nutrients such as calcium, magnesium, and potassium. While CEC and EC are both indicators of soil health and fertility, CEC relates to the soil's nutrient-holding capacity, while EC reflects the level of soil salinity. | P57: NA | Q57: Depends on Unit | R57: No | S57: AGROVOC | T57: cation exchange capacity | U57: http://aims.fao.org/aos/agrovoc/c_24981 | V57: Yes | W57: properties > chemicophysical properties > ion exchange capacity > cation exchange capacity measure > ion exchange capacity > cation exchange capacity | X57: Camila | Y57: Capacidad de intercambio cationico
A58: Soil.Out | B58: This section is used to record detailed soil properties at the beginning of an experiment, including texture, pH, nutrient content, and other relevant information. You can add several lines to the table where soil properties are reported for multiple depths. Don't record soil properties measured after an experiment has begun here. | C58: Soil.EC | D58: TRUE | E58: TRUE | F58: FALSE | G58: FALSE | K58: No | L58: Electrical Conductivity (EC) | M58: Numeric | N58: Electrical Conductivity (EC), is a measure of the soil's ability to conduct electrical charges and is expressed as the amount of electrical current that passes through a soil sample. EC is related to the concentration of soluble salts in the soil, and high EC values can indicate soil salinity, which can be detrimental to crop growth and yield. While CEC and EC are both indicators of soil health and fertility, CEC relates to the soil's nutrient-holding capacity, while EC reflects the level of soil salinity. | P58: NA | Q58: Depends on Unit | R58: No | S58: AGROVOC | T58: electrical conductivity | U58: http://aims.fao.org/aos/agrovoc/c_24022 | V58: Yes | W58: properties > chemicophysical properties > electrical properties > electrical conductivity | X58: Camila | Y58: Conductividad electrica
A59: Soil.Out | B59: This section is used to record detailed soil properties at the beginning of an experiment, including texture, pH, nutrient content, and other relevant information. You can add several lines to the table where soil properties are reported for multiple depths. Don't record soil properties measured after an experiment has begun here. | C59: Soil.FC | D59: TRUE | E59: TRUE | F59: FALSE | G59: FALSE | K59: No | L59: Water Holding Capacity (WHC) | M59: Numeric | N59: Soil water holding capacity (WHC) is the maximum amount of water that a given volume of soil can hold against the force of gravity, usually expressed as the amount of water retained per unit of soil depth or volume. The water holding capacity of a soil depends on its texture, structure, organic matter content, and compaction, and is a critical factor for plant growth and productivity, particularly in areas with limited or erratic rainfall. | P59: NA | Q59: Depends on Unit | R59: No | S59: AGROVOC | T59: water holding capacity | U59: http://aims.fao.org/aos/agrovoc/c_25304 | V59: Yes | W59: properties > chemicophysical properties > water holding capacity | X59: Camila | Y59: Capacidad de retencio de agua (o Capacidad de campo=Field capacity)
A60: Soil.Out | B60: This section is used to record detailed soil properties at the beginning of an experiment, including texture, pH, nutrient content, and other relevant information. You can add several lines to the table where soil properties are reported for multiple depths. Don't record soil properties measured after an experiment has begun here. | C60: Soil.TN | D60: TRUE | E60: TRUE | F60: FALSE | G60: FALSE | K60: No | L60: Total Nitrogen (TN) | M60: Numeric | N60: Content or amount of total nitrogen in soil. Source: AGROVOC | P60: NA | Q60: Depends on Unit | R60: No | S60: AGROVOC | T60: total nitrogen | U60: http://aims.fao.org/aos/agrovoc/c_bdc779f4 | V60: Yes | W60: properties > soil properties > soil chemicophysical properties > nitrogen content > total nitrogen properties > composition > proximate composition > nitrogen content > total nitrogen | X60: Camila | Y60: Nitrogeno total
... A63: Soil.Out | B63: This section is used to record detailed soil properties at the beginning of an experiment, including texture, pH, nutrient content, and other relevant information. You can add several lines to the table where soil properties are reported for multiple depths. Don't record soil properties measured after an experiment has begun here. | C63: Soil.AN | D63: TRUE | E63: TRUE | F63: FALSE | G63: FALSE | K63: No | L63: Available Nitrogen (AN) | M63: Numeric | N63: Content of plant available nitrogen in soil. Source: AGROVOC | P63: NA | Q63: Depends on Unit | R63: No | S63: AGROVOC | T63: plant available nitrogen | U63: http://aims.fao.org/aos/agrovoc/c_05f1777f | V63: Yes | W63: properties > soil properties > soil chemicophysical properties > nitrogen content > plant available nitrogen properties > composition > proximate composition > nitrogen content > plant available nitrogen | X63: Camila | Y63: Nitrogeno disponible
A64: Soil.Out | B64: This section is used to record detailed soil properties at the beginning of an experiment, including texture, pH, nutrient content, and other relevant information. You can add several lines to the table where soil properties are reported for multiple depths. Don't record soil properties measured after an experiment has begun here. | C64: Soil.AP | D64: TRUE | E64: TRUE | F64: FALSE | G64: FALSE | K64: No | L64: Available Phosphorus (AP) | M64: Numeric | N64: Content of plant available phosphorous in soil. Source: AGROVOC | P64: NA | Q64: Depends on Unit | R64: No | S64: AGROVOC | T64: plant available phosphorus | U64: http://aims.fao.org/aos/agrovoc/c_eb7b4957 | V64: Yes | W64: properties > soil properties > soil chemicophysical properties > phosphorus content > plant available phosphorus
A65: Soil.Out | B65: This section is used to record detailed soil properties at the beginning of an experiment, including texture, pH, nutrient content, and other relevant information. You can add several lines to the table where soil properties are reported for multiple depths. Don't record soil properties measured after an experiment has begun here. | C65: Soil.TP | D65: TRUE | E65: TRUE | F65: FALSE | G65: FALSE | K65: No | L65: Total Phosphorus (TP) | M65: Numeric | N65: Total P content, e.g. in a soil sample. Source: AGROVOC | P65: NA | Q65: Depends on Unit | R65: No | S65: AGROVOC | T65: total phosphorus | U65: http://aims.fao.org/aos/agrovoc/c_ac4b3c22 | V65: Yes | W65: properties > soil properties > soil chemicophysical properties > phosphorus content > total phosphorus
A66: Soil.Out | B66: This section is used to record detailed soil properties at the beginning of an experiment, including texture, pH, nutrient content, and other relevant information. You can add several lines to the table where soil properties are reported for multiple depths. Don't record soil properties measured after an experiment has begun here. | C66: Soil.CaCO3 | D66: TRUE | E66: TRUE | F66: FALSE | G66: FALSE | K66: No | L66: Calcium Carbonate | M66: Numeric | N66: Content or amount of calcium carbonate (CaCO3) in soil. | P66: NA | Q66: Depends on Unit | R66: No | S66: AGROVOC | T66: calcium carbonate | U66: http://aims.fao.org/aos/agrovoc/c_1197 | V66: Partial | W66: substances > chemical compounds > salts > inorganic acid salts > carbonates > calcium carbonate substances > chemical compounds > inorganic compounds > inorganic acid salts > carbonates > calcium carbonate
A67: Soil.Out | B67: This section is used to record detailed soil properties at the beginning of an experiment, including texture, pH, nutrient content, and other relevant information. You can add several lines to the table where soil properties are reported for multiple depths. Don't record soil properties measured after an experiment has begun here. | C67: SND.Unit | D67: TRUE | E67: TRUE | F67: FALSE | G67: TRUE | K67: Yes | L67: Sand Unit | M67: Character | N67: The reporting unit of sand, silt or clay is set to percent %. The total of sand, silt and clay should total 100. | P67: % | Q67: If !is.na(SND) then this field == % | R67: NA | S67: AGROVOC | V67: No | X67: Camila | Y67: Arena | Z67: No | AA67: OM | AB67: percent | AC67: http://www.ontology-of-units-of-measure.org/resource/om-2/percent | AD67: Yes
A68: Soil.Out | B68: This section is used to record detailed soil properties at the beginning of an experiment, including texture, pH, nutrient content, and other relevant information. You can add several lines to the table where soil properties are reported for multiple depths. Don't record soil properties measured after an experiment has begun here. | C68: SLT.Unit | D68: TRUE | E68: TRUE | F68: FALSE | G68: TRUE | K68: Yes | L68: Silt Unit | M68: Character | N68: The reporting unit of sand, silt or clay is set to percent %. The total of sand, silt and clay should total 100. | P68: % | Q68: If !is.na(SLT) then this field == % | R68: NA | S68: AGROVOC | V68: No | X68: Camila | Y68: Limo | Z68: No | AA68: OM | AB68: percent | AC68: http://www.ontology-of-units-of-measure.org/resource/om-2/percent | AD68: Yes
A69: Soil.Out | B69: This section is used to record detailed soil properties at the beginning of an experiment, including texture, pH, nutrient content, and other relevant information. You can add several lines to the table where soil properties are reported for multiple depths. Don't record soil properties measured after an experiment has begun here. | C69: CLY.Unit | D69: TRUE | E69: TRUE | F69: FALSE | G69: TRUE | K69: Yes | L69: Clay Unit | M69: Character | N69: The reporting unit of sand, silt or clay is set to percent %. The total of sand, silt and clay should total 100. | P69: % | Q69: If !is.na(CLY) then this field == % | R69: NA | S69: AGROVOC | V69: No | X69: Camila | Y69: Arcilla | Z69: No | AA69: OM | AB69: percent | AC69: http://www.ontology-of-units-of-measure.org/resource/om-2/percent | AD69: Yes
A70: Soil.Out | B70: This section is used to record detailed soil properties at the beginning of an experiment, including texture, pH, nutrient content, and other relevant information. You can add several lines to the table where soil properties are reported for multiple depths. Don't record soil properties measured after an experiment has begun here. | C70: Soil.BD.Unit | D70: TRUE | E70: TRUE | F70: FALSE | G70: FALSE | K70: No | L70: Bulk Density (BD) Unit | M70: Character | N70: Unit of measurement for bulk density. | P70: lookup_levels$Soil.BD.Unit | Q70: NA | R70: Needs to be filled if a corresponding value exists for this soil parameter. | S70: NA | T70: NA | U70: NA | V70: NA | W70: NA | X70: Camila | Y70: Densidad aparente | Z70: Yes | AA70: IAO | AB70: measurement unit label | AC70: http://purl.obolibrary.org/obo/IAO_0000003 | AD70: (Yes) | AE70: A measurement unit label is as a label that is part of a scalar measurement datum and denotes a unit of measure.
A71: Soil.Out | B71: This section is used to record detailed soil properties at the beginning of an experiment, including texture, pH, nutrient content, and other relevant information. You can add several lines to the table where soil properties are reported for multiple depths. Don't record soil properties measured after an experiment has begun here. | C71: Soil.TC.Unit | D71: TRUE | E71: TRUE | F71: FALSE | G71: FALSE | K71: No | L71: Total Carbon (TC) Unit | M71: Character | N71: Unit of measurement for total carbon. | P71: lookup_levels$Soil.SOM.Unit | Q71: NA | R71: Needs to be filled if a corresponding value exists for this soil parameter. | S71: NA | T71: NA | U71: NA | V71: NA | W71: NA | X71: Camila | Y71: Carbono total | Z71: Yes | AA71: IAO | AB71: measurement unit label | AC71: http://purl.obolibrary.org/obo/IAO_0000003 | AD71: (Yes) | AE71: A measurement unit label is as a label that is part of a scalar measurement datum and denotes a unit of measure.
A72: Soil.Out | B72: This section is used to record detailed soil properties at the beginning of an experiment, including texture, pH, nutrient content, and other relevant information. You can add several lines to the table where soil properties are reported for multiple depths. Don't record soil properties measured after an experiment has begun here. | C72: Soil.SOC.Unit | D72: TRUE | E72: TRUE | F72: FALSE | G72: FALSE | K72: No | L72: Soil Organic Carbon Content (SOC) Unit | M72: Character | N72: Unit of measurement for soil organic carbon. | P72: lookup_levels$Soil.SOM.Unit | Q72: NA | R72: Needs to be filled if a corresponding value exists for this soil parameter. | S72: NA | T72: NA | U72: NA | V72: NA | W72: NA | X72: Camila | Y72: Contenido organico del suelo | Z72: Yes | AA72: IAO | AB72: measurement unit label | AC72: http://purl.obolibrary.org/obo/IAO_0000003 | AD72: (Yes) | AE72: A measurement unit label is as a label that is part of a scalar measurement datum and denotes a unit of measure.
A73: Soil.Out | B73: This section is used to record detailed soil properties at the beginning of an experiment, including texture, pH, nutrient content, and other relevant information. You can add several lines to the table where soil properties are reported for multiple depths. Don't record soil properties measured after an experiment has begun here. | C73: Soil.SOM.Unit | D73: TRUE | E73: TRUE | F73: FALSE | G73: FALSE | K73: No | L73: Soil Organic Matter Content (SOM) Unit | M73: Character | N73: Unit of measurement for soil organic matter. | P73: lookup_levels$Soil.SOM.Unit | Q73: NA | R73: Needs to be filled if a corresponding value exists for this soil parameter. | S73: NA | T73: NA | U73: NA | V73: NA | W73: NA | X73: Camila | Y73: Contenido de materia organica del suelo | Z73: Yes | AA73: IAO | AB73: measurement unit label | AC73: http://purl.obolibrary.org/obo/IAO_0000003 | AD73: (Yes) | AE73: A measurement unit label is as a label that is part of a scalar measurement datum and denotes a unit of measure.
A74: Soil.Out | B74: This section is used to record detailed soil properties at the beginning of an experiment, including texture, pH, nutrient content, and other relevant information. You can add several lines to the table where soil properties are reported for multiple depths. Don't record soil properties measured after an experiment has begun here. | C74: Soil.CEC.Unit | D74: TRUE | E74: TRUE | F74: FALSE | G74: FALSE | K74: No | L74: Cation Exchange Capacity (CEC) Unit | M74: Character | N74: Unit of measurement for Cation Exchange Capacity. | P74: lookup_levels$Soil.CEC.Unit | Q74: NA | R74: Needs to be filled if a corresponding value exists for this soil parameter. | S74: NA | T74: NA | U74: NA | V74: NA | W74: NA | X74: Camila | Y74: Capacidad de intercambio cationico | Z74: Yes | AA74: IAO | AB74: measurement unit label | AC74: http://purl.obolibrary.org/obo/IAO_0000003 | AD74: (Yes) | AE74: A measurement unit label is as a label that is part of a scalar measurement datum and denotes a unit of measure.
A75: Soil.Out | B75: This section is used to record detailed soil properties at the beginning of an experiment, including texture, pH, nutrient content, and other relevant information. You can add several lines to the table where soil properties are reported for multiple depths. Don't record soil properties measured after an experiment has begun here. | C75: Soil.EC.Unit | D75: TRUE | E75: TRUE | F75: FALSE | G75: FALSE | K75: No | L75: Electrical Conductivity (EC) Unit | M75: Character | N75: Unit of measurement for Electrical Conductivity. | P75: lookup_levels$Soil.CEC.Unit | Q75: NA | R75: Needs to be filled if a corresponding value exists for this soil parameter. | S75: NA | T75: NA | U75: NA | V75: NA | W75: NA | X75: Camila | Y75: Conductividad electrica | Z75: Yes | AA75: IAO | AB75: measurement unit label | AC75: http://purl.obolibrary.org/obo/IAO_0000003 | AD75: (Yes) | AE75: A measurement unit label is as a label that is part of a scalar measurement datum and denotes a unit of measure.
A76: Soil.Out | B76: This section is used to record detailed soil properties at the beginning of an experiment, including texture, pH, nutrient content, and other relevant information. You can add several lines to the table where soil properties are reported for multiple depths. Don't record soil properties measured after an experiment has begun here. | C76: Soil.FC.Unit | D76: TRUE | E76: TRUE | F76: FALSE | G76: FALSE | K76: No | L76: Water Holding Capacity (WHC) Unit | M76: Character | N76: Unit of measurement for soil water holding capacity. | P76: lookup_levels$Soil.FC.Unit | Q76: NA | R76: Needs to be filled if a corresponding value exists for this soil parameter. | S76: NA | T76: NA | U76: NA | V76: NA | W76: NA | X76: Camila | Y76: Capacidad de retencion de agua | Z76: Yes | AA76: IAO | AB76: measurement unit label | AC76: http://purl.obolibrary.org/obo/IAO_0000003 | AD76: (Yes) | AE76: A measurement unit label is as a label that is part of a scalar measurement datum and denotes a unit of measure.
A77: Soil.Out | B77: This section is used to record detailed soil properties at the beginning of an experiment, including texture, pH, nutrient content, and other relevant information. You can add several lines to the table where soil properties are reported for multiple depths. Don't record soil properties measured after an experiment has begun here. | C77: Soil.TN.Unit | D77: TRUE | E77: TRUE | F77: FALSE | G77: FALSE | K77: No | L77: Total Nitrogen (TN) Unit | M77: Character | N77: Unit of measurement for soil total nitrogen. | P77: lookup_levels$Soil.N.Unit | Q77: NA | R77: Needs to be filled if a corresponding value exists for this soil parameter. | S77: NA | T77: NA | U77: NA | V77: NA | W77: NA | X77: Camila | Y77: Nitrogeno total | Z77: Yes | AA77: IAO | AB77: measurement unit label | AC77: http://purl.obolibrary.org/obo/IAO_0000003 | AD77: (Yes) | AE77: A measurement unit label is as a label that is part of a scalar measurement datum and denotes a unit of measure.
A78: Soil.Out | B78: This section is used to record detailed soil properties at the beginning of an experiment, including texture, pH, nutrient content, and other relevant information. You can add several lines to the table where soil properties are reported for multiple depths. Don't record soil properties measured after an experiment has begun here. | C78: Soil.NH4.Unit | D78: TRUE | E78: TRUE | F78: FALSE | G78: FALSE | K78: No | L78: Ammonium (NH4+) Unit | M78: Character | N78: Unit of measurement for soil ammonium. | P78: lookup_levels$Soil.N.Unit | Q78: NA | R78: Needs to be filled if a corresponding value exists for this soil parameter. | S78: NA | T78: NA | U78: NA | V78: NA | W78: NA | X78: Camila | Y78: Amonio | Z78: Yes | AA78: IAO | AB78: measurement unit label | AC78: http://purl.obolibrary.org/obo/IAO_0000003 | AD78: (Yes) | AE78: A measurement unit label is as a label that is part of a scalar measurement datum and denotes a unit of measure.
A79: Soil.Out | B79: This section is used to record detailed soil properties at the beginning of an experiment, including texture, pH, nutrient content, and other relevant information. You can add several lines to the table where soil properties are reported for multiple depths. Don't record soil properties measured after an experiment has begun here. | C79: Soil.NO3.Unit | D79: TRUE | E79: TRUE | F79: FALSE | G79: FALSE | K79: No | L79: Nitrate (NO3-) Unit | M79: Character | N79: Unit of measurement for soil nitrate. | P79: lookup_levels$Soil.N.Unit | Q79: NA | R79: Needs to be filled if a corresponding value exists for this soil parameter. | S79: NA | T79: NA | U79: NA | V79: NA | W79: NA | X79: Camila | Y79: Nitrato | Z79: Yes | AA79: IAO | AB79: measurement unit label | AC79: http://purl.obolibrary.org/obo/IAO_0000003 | AD79: (Yes) | AE79: A measurement unit label is as a label that is part of a scalar measurement datum and denotes a unit of measure.
A80: Soil.Out | B80: This section is used to record detailed soil properties at the beginning of an experiment, including texture, pH, nutrient content, and other relevant information. You can add several lines to the table where soil properties are reported for multiple depths. Don't record soil properties measured after an experiment has begun here. | C80: Soil.AN.Unit | D80: TRUE | E80: TRUE | F80: FALSE | G80: FALSE | K80: No | L80: Available Nitrogen (AN) Unit | M80: Character | N80: Unit of measurement for soil available nitrogen. | P80: lookup_levels$Soil.N.Unit | Q80: NA | R80: Needs to be filled if a corresponding value exists for this soil parameter. | S80: NA | T80: NA | U80: NA | V80: NA | W80: NA | X80: Camila | Y80: Nitrogeno disponible | Z80: Yes | AA80: IAO | AB80: measurement unit label | AC80: http://purl.obolibrary.org/obo/IAO_0000003 | AD80: (Yes) | AE80: A measurement unit label is as a label that is part of a scalar measurement datum and denotes a unit of measure.
A81: Soil.Out | B81: This section is used to record detailed soil properties at the beginning of an experiment, including texture, pH, nutrient content, and other relevant information. You can add several lines to the table where soil properties are reported for multiple depths. Don't record soil properties measured after an experiment has begun here. | C81: Soil.pH.Unit | G81: TRUE | K81: No | L81: Available Phosphorus (AP) Unit | M81: Character | N81: Unit of measurement for soil available phosphorus. | P81: lookup_levels$Soil.N.Unit | Q81: NA | R81: Needs to be filled if a corresponding value exists for this soil parameter. | S81: NA | T81: NA | U81: NA | V81: NA | W81: NA | Z81: Yes | AA81: IAO | AB81: measurement unit label | AC81: http://purl.obolibrary.org/obo/IAO_0000003 | AD81: (Yes) | AE81: A measurement unit label is as a label that is part of a scalar measurement datum and denotes a unit of measure.
A82: Soil.Out | B82: This section is used to record detailed soil properties at the beginning of an experiment, including texture, pH, nutrient content, and other relevant information. You can add several lines to the table where soil properties are reported for multiple depths. Don't record soil properties measured after an experiment has begun here. | C82: Soil.AP.Unit | D82: TRUE | E82: TRUE | F82: FALSE | G82: FALSE | K82: No | L82: Available Phosphorus (AP) Unit | M82: Character | N82: Unit of measurement for soil available phosphorus. | P82: lookup_levels$Soil.N.Unit | Q82: NA | R82: Needs to be filled if a corresponding value exists for this soil parameter. | S82: NA | T82: NA | U82: NA | V82: NA | W82: NA | Z82: Yes | AA82: IAO | AB82: measurement unit label | AC82: http://purl.obolibrary.org/obo/IAO_0000003 | AD82: (Yes) | AE82: A measurement unit label is as a label that is part of a scalar measurement datum and denotes a unit of measure.
A83: Soil.Out | B83: This section is used to record detailed soil properties at the beginning of an experiment, including texture, pH, nutrient content, and other relevant information. You can add several lines to the table where soil properties are reported for multiple depths. Don't record soil properties measured after an experiment has begun here. | C83: Soil.TP.Unit | D83: TRUE | E83: TRUE | F83: FALSE | G83: FALSE | K83: No | L83: Total Phosphorus (TP) Unit | M83: Character | N83: Unit of measurement for soil total phosphorus. | P83: lookup_levels$Soil.N.Unit | Q83: NA | R83: Needs to be filled if a corresponding value exists for this soil parameter. | S83: NA | T83: NA | U83: NA | V83: NA | W83: NA | Z83: Yes | AA83: IAO | AB83: measurement unit label | AC83: http://purl.obolibrary.org/obo/IAO_0000003 | AD83: (Yes) | AE83: A measurement unit label is as a label that is part of a scalar measurement datum and denotes a unit of measure.
A84: Soil.Out | B84: This section is used to record detailed soil properties at the beginning of an experiment, including texture, pH, nutrient content, and other relevant information. You can add several lines to the table where soil properties are reported for multiple depths. Don't record soil properties measured after an experiment has begun here. | C84: Soil.CaCO3.Unit | D84: TRUE | E84: TRUE | F84: FALSE | G84: FALSE | K84: No | L84: Calcium Carbonate Unit | M84: Character | N84: Unit of measurement for soil calcium carbonate. | P84: lookup_levels$Soil.SOM.Unit | Q84: NA | R84: Needs to be filled if a corresponding value exists for this soil parameter. | S84: NA | T84: NA | U84: NA | V84: NA | W84: NA | Z84: Yes | AA84: IAO | AB84: measurement unit label | AC84: http://purl.obolibrary.org/obo/IAO_0000003 | AD84: (Yes) | AE84: A measurement unit label is as a label that is part of a scalar measurement datum and denotes a unit of measure.
A85: Soil.Out | B85: This section is used to record detailed soil properties at the beginning of an experiment, including texture, pH, nutrient content, and other relevant information. You can add several lines to the table where soil properties are reported for multiple depths. Don't record soil properties measured after an experiment has begun here. | C85: Soil.P.Method | D85: TRUE | E85: TRUE | F85: FALSE | G85: FALSE | K85: No | L85: Phosphorus Measurement Method | M85: Character | N85: Method of measurement for soil phosphorus. | P85: lookup_levels$Soil.P.Method | Q85: NA | R85: Needs to be filled if a corresponding value exists for this soil parameter. | S85: NA | T85: NA | U85: NA | V85: NA | W85: NA
A86: Soil.Out | B86: This section is used to record detailed soil properties at the beginning of an experiment, including texture, pH, nutrient content, and other relevant information. You can add several lines to the table where soil properties are reported for multiple depths. Don't record soil properties measured after an experiment has begun here. | C86: Soil.N.Method | D86: TRUE | E86: TRUE | F86: FALSE | G86: FALSE | K86: No | L86: Nitrogen Measurement Method | M86: Character | N86: Method of measurement for soil nitrogen. | P86: lookup_levels$Soil.N.Method | Q86: NA | R86: Needs to be filled if a corresponding value exists for this soil parameter. | S86: NA | T86: NA | U86: NA | V86: NA | W86: NA
A87: Soil.Out | B87: This section is used to record detailed soil properties at the beginning of an experiment, including texture, pH, nutrient content, and other relevant information. You can add several lines to the table where soil properties are reported for multiple depths. Don't record soil properties measured after an experiment has begun here. | C87: Soil.SOC.Method | D87: TRUE | E87: TRUE | F87: FALSE | G87: FALSE | K87: No | L87: SOC Measurement Method | M87: Character | N87: Method of measurement for soil organic carbon. | P87: lookup_levels$SOC.Method | Q87: NA | R87: Needs to be filled if a corresponding value exists for this soil parameter. | S87: NA | T87: NA | U87: NA | V87: NA | W87: NA | X87: Camila | Y87: Metodo de medicion de contenido de carbono organico del suelo
A88: Soil.Out | B88: This section is used to record detailed soil properties at the beginning of an experiment, including texture, pH, nutrient content, and other relevant information. You can add several lines to the table where soil properties are reported for multiple depths. Don't record soil properties measured after an experiment has begun here. | C88: Soil.SOM.Method | D88: TRUE | E88: TRUE | F88: FALSE | G88: FALSE | K88: No | L88: SOM Measurement Method | M88: Character | N88: Method of measurement for soil organic matter. | P88: lookup_levels$SOM.Method | Q88: NA | R88: Needs to be filled if a corresponding value exists for this soil parameter. | S88: NA | T88: NA | U88: NA | V88: NA | W88: NA | X88: Camila | Y88: Metodo de medicion de contenido de materia organica del suelo
A89: Soil.Out | B89: This section is used to record detailed soil properties at the beginning of an experiment, including texture, pH, nutrient content, and other relevant information. You can add several lines to the table where soil properties are reported for multiple depths. Don't record soil properties measured after an experiment has begun here. | C89: Soil.pH.Method | D89: TRUE | E89: TRUE | F89: FALSE | G89: FALSE | K89: No | L89: pH Measurement Method | M89: Character | N89: Method of measurement for soil pH. | P89: lookup_levels$Soil.pH.Method | Q89: NA | R89: Needs to be filled if a corresponding value exists for this soil parameter. | S89: NA | T89: NA | U89: NA | V89: NA | W89: NA | X89: Camila | Y89: Metodo de medicion de pH del suelo
A90: Soil.Out | B90: This section is used to record detailed soil properties at the beginning of an experiment, including texture, pH, nutrient content, and other relevant information. You can add several lines to the table where soil properties are reported for multiple depths. Don't record soil properties measured after an experiment has begun here. | C90: B.Code | D90: TRUE | E90: TRUE | F90: FALSE | G90: TRUE | H90: f | I90: Pub.Out | K90: Yes | L90: NA | M90: Character | N90: =N$2 -> A unique code that identifies an extracted publication in the ERA dataset. This code is present in all the tables of era extraction data models. | P90: Pub.Out$B.Code | Q90: NA | R90: NA | S90: NA | T90: NA | U90: NA | V90: NA | W90: NA | Z90: NA | AA90: NA | AB90: NA | AC90: NA | AD90: NA | AE90: NA | AF90: NA
A91: Soil.Out | C91: USDA.Texture | D91: TRUE | E91: TRUE | F91: FALSE | G91: FALSE | K91: Yes | L91: Soil Texture Class (USDA) | M91: Character | N91: Soil texture classified according to the USDA soil texture triangle. | O91: To convert % sand, silt and clay values into a class we use the Soiltexture::TT.points.in.classes R function https://www.rdocumentation.org/packages/soiltexture/versions/1.5.1/topics/TT.points.in.classes. This is done automatically and not by the data extractor. | P91: Output by Soiltexture::TT.points.in.classes | Q91: NA | R91: NA | S91: AGROVOC | T91: soil texture | U91: http://aims.fao.org/aos/agrovoc/c_7199 | V91: Partial | W91: properties > soil properties > soil chemicophysical properties > soil texture | X91: Camila | Y91: Textura del suelo
A92: Soil.Out | C92: Site.Soil.Texture | G92: TRUE | I92: Site.Out | K92: Yes | L92: Soil Texture Class (USDA) | M92: Character | N92: Soil texture classified according to the USDA soil texture triangle. | O92: To convert % sand, silt and clay values into a class we use the Soiltexture::TT.points.in.classes R function https://www.rdocumentation.org/packages/soiltexture/versions/1.5.1/topics/TT.points.in.classes. This is done automatically and not by the data extractor. | P92: Output by Soiltexture::TT.points.in.classes | Q92: NA | R92: NA | S92: AGROVOC | T92: soil texture | U92: http://aims.fao.org/aos/agrovoc/c_7199 | V92: Partial | W92: properties > soil properties > soil chemicophysical properties > soil texture | X92: Camila | Y92: Textura del suelo
A93: ExpD.Out | B93: Experimental design information, such as plot size, layout and notes on historical management. | C93: EX.Design | D93: TRUE | E93: TRUE | F93: TRUE | G93: TRUE | K93: No | L93: Experimental Design | M93: Character | N93: A plan specification that states how treatments are allocated to the experimental units during an agronomic trial. It refers to the conceptual framework within which the experiment is conducted. Source: AGRO | P93: Free Text | Q93: None, but a lookup table could be implemented | S93: AGROVOC | T93: experimental design | U93: http://aims.fao.org/aos/agrovoc/c_29466 | V93: Yes | W93: activities > design > experimental design | X93: Camila | Y93: Diseño experimental | Z93: Yes | AA93: AGRO | AB93: agronomic experimental design | AC93: http://purl.obolibrary.org/obo/AGRO_00000343 | AD93: Yes
A94: ExpD.Out | C94: EX.Plot.Size | D94: TRUE | E94: TRUE | F94: TRUE | G94: FALSE | K94: No | L94: Size of Experimental Plot (m2) | M94: Numeric | N94: The size of a treatment plot in the experiment, if variable use the mean value or mid-point of the size range. | P94: NA | Q94: EX.Plot.Size>=EX.HPlot.Size
A95: ExpD.Out | C95: EX.HPlot.Size | D95: TRUE | E95: TRUE | F95: TRUE | G95: FALSE | K95: No | L95: Size of Harvested Plot (m2) | M95: Numeric | N95: The area of an treatment plot harvested to estimate crop yields (or other outcomes if crop yield was not the primary focus of the experiment). | P95: NA | Q95: EX.HPlot.Size<=EX.Plot.Size
A96: ExpD.Out | C96: EX.Notes | D96: TRUE | E96: TRUE | F96: TRUE | G96: TRUE | K96: No | L96: Design & Previous Management Notes | M96: Character | N96: Copy details about experimental design and previous management here. Previous management describes the study site before the experiment began. | P96: Free Text | Q96: NA | S96: NA | T96: NA | U96: NA | V96: NA | W96: NA
A97: ExpD.Out | C97: Ex.Acclim | D97: FALSE | E97: FALSE | F97: FALSE | G97: TRUE | K97: No | L97: Acclimatization (days) | M97: Numeric
A98: ExpD.Out | C98: B.Code | D98: TRUE | E98: TRUE | F98: TRUE | G98: TRUE | H98: f | I98: Pub.Out | K98: Yes | L98: NA | M98: Character | N98: =N$2 -> A unique code that identifies an extracted publication in the ERA dataset. This code is present in all the tables of era extraction data models. | P98: Pub.Out$B.Code | Q98: NA | R98: NA | S98: NA | T98: NA | U98: NA | V98: NA | W98: NA | Z98: NA | AA98: NA | AB98: NA | AC98: NA | AD98: NA | AE98: NA | AF98: NA
A99: Times.Out | C99: B.Code | D99: FALSE | E99: FALSE | F99: TRUE | G99: TRUE | H99: f | I99: Pub.Out | K99: Yes | L99: NA | M99: Character | N99: =N$2 -> A unique code that identifies an extracted publication in the ERA dataset. This code is present in all the tables of era extraction data models. | P99: Pub.Out$B.Code | R99: NA | S99: NA | T99: NA | U99: NA | V99: NA | W99: NA | Z99: NA | AA99: NA | AB99: NA | AC99: NA | AD99: NA | AE99: NA | AF99: NA
A100: Times.Out | C100: Time | D100: FALSE | E100: FALSE | F100: TRUE | G100: TRUE | H100: p | K100: No | L100: Time Period Name | M100: Character
A101: Times.Out | C101: Time.Start.Day | D101: FALSE | E101: FALSE | F101: FALSE | G101: TRUE
A102: Times.Out | C102: Time.Start.Month | D102: FALSE | E102: FALSE | F102: FALSE | G102: TRUE
A103: Times.Out | C103: Time.Start.Year | D103: FALSE | E103: FALSE | F103: TRUE | G103: TRUE | L103: Year Start as stated by the author | M103: Numeric | N103: year when the experiment started
A104: Times.Out | C104: Time.End.Day | D104: FALSE | E104: FALSE | F104: FALSE | G104: TRUE
A105: Times.Out | C105: Time.End.Month | D105: FALSE | E105: FALSE | F105: FALSE | G105: TRUE
...

Sheet prac
A1: Code | B1: Theme | C1: Theme.Code | D1: Practice | E1: Practice.Code | F1: Subpractice | G1: Subpractice.Code | H1: Subpractice.S | I1: Subpractice.Suffix | J1: Definition | K1: Notes | L1: Linked.Tab | M1: Linked.Col | N1: Depreciated
A2: a1 | B2: Agroforestry | C2: Agroforestry | D2: FMNR | E2: FMNR | F2: Farmer Managed Natural Regeneration | G2: FMNR | H2: FMNR | I2: NA | J2: Systematic regrowth of trees or shrubs on agricultural, forest or pasture land. FMNR is used in areas where there are stumps that can coppice or seeds that can germinate. Sometimes called farmer assisted regeneration. | K2: Typically defined as FMNR or farmer assisted regeneration by author in text. | L2: Int.Out | M2: ED.Int | N2: FALSE
A3: a3 | B3: Agroforestry | C3: Agroforestry | D3: Alleycropping | E3: Al | F3: Alleycropping (N fixing) | G3: Al+N | H3: AgFor Alley (Nfix) | I3: Nfix | J3: Intercropping with rows or alleys of nitrogen fixing trees or woody shrubs. | L3: Int.Out | M3: ED.Int | N3: FALSE
A4: a4 | B4: Agroforestry | C4: Agroforestry | D4: Alleycropping | E4: Al | F4: Alleycropping (Non N fixing) | G4: Al-N | H4: AgFor Alley (nonNfix) | I4: nonNfix | J4: Intercropping with rows or alleys of trees or woody shrubs that do not fix nitrogen. | L4: Int.Out | M4: ED.Int | N4: FALSE
A5: a4.1 | B5: Agroforestry | C5: Agroforestry | D5: Alleycropping | E5: Al | F5: Alleycropping (Mixed) | G5: Al±N | H5: AgFor Alley (Mixed) | I5: Mixed | J5: Intercropping with rows or alleys of a mixture of trees or woody shrubs of which some but not all fix nitrogen. | L5: Int.Out | M5: ED.Int | N5: FALSE
A6: a14 | B6: Agroforestry | C6: Agroforestry | D6: Alleycropping | E6: Al | F6: Alleycropping (Unspecified) | G6: Al | H6: AgFor Alley (noID) | I6: NoID | J6: Intercropping with rows or alleys of trees or woody shrubs where no information about the type of plant is given. | L6: Int.Out | M6: ED.Int | N6: FALSE
A7: a8 | B7: Agroforestry | C7: Agroforestry | D7: Parklands | E7: Pa | F7: Parklands | G7: Pa | H7: Parklands | I7: NA | J7: Intercropping under scattered or regularly planted trees. | K7: Typically named parklands in the document text. Difference with scattered trees is unclear. | L7: Int.Out | M7: ED.Int | N7: FALSE
A8: a8.1 | B8: Agroforestry | C8: Agroforestry | D8: Parklands | E8: Pa | F8: Scattered Trees | G8: ST | H8: Scattered Trees | I8: NA | J8: Unspecified sparse or scattered trees incorporated into croplands, pastures or rangelands. | K8: Difference with Parklands is unclear, other than parklands is not mentioned in the definition. | L8: Int.Out | M8: ED.Int | N8: FALSE
A9: a9 | B9: Agroforestry | C9: Agroforestry | D9: Boundary Planting | E9: BP | F9: Tree Windbreak | G9: TW | H9: Windbreak | I9: NA | J9: Barriers of trees or shrubs planted along field boundaries to protect plants against wind. | L9: AF.Out | M9: AF.Level.Name | N9: FALSE
A10: a10 | B10: Agroforestry | C10: Agroforestry | D10: Boundary Planting | E10: BP | F10: Living Fences or Hedgerows | G10: LF | H10: Hedge | I10: NA | J10: Living fence and hedges are planted in rows around the edge of the field to reduce the effect of wind or runoff on crops. | K10: Note some early agroforestry papers named alleycropping 'hedgerows', but any form of hedge intercropped within a field should be categorized as alleycropping. | L10: AF.Out | M10: AF.Level.Name | N10: FALSE
A11: a11 | B11: Agroforestry | C11: Agroforestry | D11: Silvopasture | E11: Si | F11: Silvopasture | G11: Si | H11: Silvopastoral | I11: NA | J11: Combination of trees or shrubs with pasture (forage grasses) and livestock | L11: AF.Out | M11: AF.Level.Name | N11: FALSE
A12: a22 | B12: Agroforestry | C12: Agroforestry | D12: Silvopasture | E12: Si | F12: Agrosilvopastoral System | G12: AgSi | H12: Agrosilvopastoral | I12: NA | J12: Combination of livestock production systems (pastures) with trees or shrubs and crops. | L12: AF.Out | M12: AF.Level.Name | N12: FALSE
A13: a12 | B13: Agroforestry | C13: Agroforestry | D13: Multistrata Agroforestry | E13: MA | F13: Multistrata Agroforestry | G13: MA | H13: AgFor Multistrata | I13: NA | J13: Multistorey systems agroforestry systems have several spatial strata occupied by different tree (i.e. woody) crops (coffee, tea, cacao, banana etc). | K13: Typically identified as multistrata in the document text. - include two or more vegetation layers and more than one tree species - multiple tree crop species and crops (N-fixing legume cover crops) | L13: Int.Out | M13: ED.Int | N13: FALSE
A14: a15 | B14: Agroforestry | C14: Agroforestry | D14: Agroforestry Pruning | E14: AP | F14: Tree Prunings Applied (Unspecified) | G14: TPA | H14: AgFor Prune (noID) | I14: NoID | J14: Prunings (leaves, branches, etc.) of an unidentified woody plant were retained/returned to the cropping area, but it is unknown if they were mulched or incorporated. | K14: This could be from alleycropping, biomass transfer models or cut-and-carry where prunings come from off the field. It does not include situations where crop processing byproducts such as a oil palm bunch residues or walnut shells are applied to a field, these should be recorded using a regular mulch code. | L14: Res.Out | M14: M.Level.Name | N14: FALSE
A15: a15.1 | B15: Agroforestry | C15: Agroforestry | D15: Agroforestry Pruning | E15: AP | F15: Tree Prunings Mulched (Unspecified) | G15: TPM | H15: AgFor Prune Mulch (noID) | I15: NoID | J15: Prunings (leaves, branches, etc.) of an unidentified woody plant were applied to the cropping area as mulch (prunings on the surface). | K15: This could be from alleycropping, biomass transfer models or cut-and-carry where prunings come from off the field. | L15: Res.Out | M15: M.Level.Name | N15: FALSE
A16: a15.2 | B16: Agroforestry | C16: Agroforestry | D16: Agroforestry Pruning | E16: AP | F16: Tree Prunings Incorporated (Unspecified) | G16: TPI | H16: AgFor Prune Incorp (noID) | I16: NoID | J16: Prunings (leaves, branches, etc.) of an unidentified woody plant were applied to the cropping area and incorporated into the soil (e.g., by ploughing). | K16: This could be from alleycropping, biomass transfer models or cut-and-carry where prunings come from off the field. | L16: Res.Out | M16: M.Level.Name | N16: FALSE
A17: a16 | B17: Agroforestry | C17: Agroforestry | D17: Agroforestry Pruning | E17: AP | F17: Tree Prunings Applied (N fixing) | G17: TAP+N | H17: AgFor Prune (Nfix) | I17: Nfix | J17: Prunings (leaves, branches, etc.) of a nitrogen fixing (leguminous) woody plant residues were retained/returned to the cropping area, but it is unknown if they were mulched or incorporated. | K17: This could be from alleycropping, biomass transfer models or cut-and-carry where prunings come from off the field. | L17: Res.Out | M17: M.Level.Name | N17: FALSE
A18: a16.1 | B18: Agroforestry | C18: Agroforestry | D18: Agroforestry Pruning | E18: AP | F18: Tree Prunings Mulched (N fixing) | G18: TPM+N | H18: AgFor Prune Mulch (Nfix) | I18: Nfix | J18: Prunings (leaves, branches, etc.) of a nitrogen fixing (leguminous) woody plant applied were applied to the cropping area as mulch (prunings on the surface). | K18: This could be from alleycropping, biomass transfer models or cut-and-carry where prunings come from off the field. | L18: Res.Out | M18: M.Level.Name | N18: FALSE
A19: a16.2 | B19: Agroforestry | C19: Agroforestry | D19: Agroforestry Pruning | E19: AP | F19: Tree Prunings Incorporated (N fixing) | G19: TPI+N | H19: AgrFor Prune Incorp (Nfix) | I19: Nfix | J19: Prunings (leaves, branches, etc.) of a nitrogen fixing (leguminous) woody plant applied were applied to the cropping area and incorporated into the soil (e.g., by ploughing). | K19: This could be from alleycropping, biomass transfer models or cut-and-carry where prunings come from off the field. | L19: Res.Out | M19: M.Level.Name | N19: FALSE
A20: a17 | B20: Agroforestry | C20: Agroforestry | D20: Agroforestry Pruning | E20: AP | F20: Tree Prunings Applied (Non N fixing) | G20: TPA-N | H20: AgrFor Prune (nonNfix) | I20: nonNfix | J20: Prunings (leaves, branches, etc.) of a non-nitrogen fixing (not leguminous) woody plant were retained/returned to the cropping area, but it is unknown if they were mulched or incorporated. | K20: This could be from alleycropping, biomass transfer models or cut-and-carry where prunings come from off the field. | L20: Res.Out | M20: M.Level.Name | N20: FALSE
A21: a17.1 | B21: Agroforestry | C21: Agroforestry | D21: Agroforestry Pruning | E21: AP | F21: Tree Prunings Mulched (Non N fixing) | G21: TPM-N | H21: AgFor Prune Mulch (nonNfix) | I21: nonNfix | J21: Prunings (leaves, branches, etc.) of a non-nitrogen fixing (not leguminous) woody plant applied were applied to the cropping area as mulch (prunings on the surface). | K21: This could be from alleycropping, biomass transfer models or cut-and-carry where prunings come from off the field. | L21: Res.Out | M21: M.Level.Name | N21: FALSE
A22: a17.2 | B22: Agroforestry | C22: Agroforestry | D22: Agroforestry Pruning | E22: AP | F22: Tree Prunings Incorporated (Non N fixing) | G22: TPI-N | H22: AgFor Prune Incorp (nonNfix) | I22: nonNfix | J22: Prunings (leaves, branches, etc.) of a non-nitrogen fixing (not leguminous) woody plant applied were applied to the cropping area and incorporated into the soil (e.g., by ploughing). | K22: This could be from alleycropping, biomass transfer models or cut-and-carry where prunings come from off the field. | L22: Res.Out | M22: M.Level.Name | N22: FALSE
A23: a18 | B23: Agroforestry | C23: Agroforestry | D23: Agroforestry Pruning | E23: AP | F23: Tree Pruning (Fate Unknown) | G23: TP | H23: AgFor Prune (Unknown) | I23: Unknown | J23: The cutting or coppicing of woody agroforestry species, generally to reduce competition or shading with intercrops, but the fate of the residues is unknown (it is unclear if was applied or removed). | K23: This could be from alleycropping, biomass transfer models or cut-and-carry where prunings come from off the field. | L23: Res.Out | M23: M.Level.Name | N23: FALSE
A24: a19.1 | B24: Agroforestry | C24: Agroforestry | D24: Agroforestry Fallow | E24: AF | F24: Agroforestry Fallow (N fixing) | G24: AF+N | H24: AgFor Fallow (Nfix) | I24: Nfix | J24: Planting fallows with short-rotation woody or perennial species that fix nitrogen. | L24: Rot.Out | M24: ED.Rot | N24: FALSE
A25: a19.2 | B25: Agroforestry | C25: Agroforestry | D25: Agroforestry Fallow | E25: AF | F25: Agroforestry Fallow (Non N fixing) | G25: AF-N | H25: AgFor Fallow (nonNfix) | I25: nonNfix | J25: Planting fallows with short-rotation woody or perennial species that do not fix nitrogen. | L25: Rot.Out | M25: ED.Rot | N25: FALSE
A26: a19.3 | B26: Agroforestry | C26: Agroforestry | D26: Agroforestry Fallow | E26: AF | F26: Agroforestry Fallow (Unspecified) | G26: AF | H26: AgFor Fallow (NoID) | I26: NoID | J26: Planting fallows with short-rotation woody or perennial species of an unknown type. | L26: Rot.Out | M26: ED.Rot | N26: FALSE
A27: a99 | B27: Agroforestry | C27: Agroforestry | D27: Other Agroforestry | E27: OA | F27: Other Agroforestry | G27: OA | H27: AgFor Other | J27: Agroforestry practice that does not meet definitions in Agroforestry practice theme. | K27: Please notify ERA team if you use this code. | L27: AF.Out | M27: AF.Level.Name | N27: FALSE
A28: d17.1 | B28: Animals | C28: Animals | D28: Feed Addition | E28: FA | F28: Crop Fodders (Added) | G28: FA+CF | H28: Feed Crop (Add) | I28: Add | J28: Feeds added to animal diets that come from non-woody crops not usually grown for fodder, but for another purpose (e.g. consumption). These can be crop grain. field residues (for example maize stalks left over once the grain component has been harvested) and or processing residues (for example the maize bran produced as a byproduct of milling flour). Soyabeans fit in this category as they are grown for human consumption and livestock feed. | K28: Feeds are added compared to a control practice (basal diet) that does not contain items which would gain the same ERA classfication. Control diets are often hay ad libitum or hay ad libitum + maize stover. | L28: Animals.Out | M28: A.Level.Name | N28: FALSE
A29: d17.2 | B29: Animals | C29: Animals | D29: Feed Addition | E29: FA | F29: Non Crop Fodders (Added) | G29: FA+NC | H29: Feed NonCrop (Add) | I29: Add | J29: Feeds added to animal diets that are non-woody crops grown primarily for fodder (e.g., alfafa or clover grown to feed to cattle) or non-woody plants harvested from non-cropped areas (e.g., forage grasses such as napier grass grown to stabilize terraces, cactus harvested from boundary fences, wild growing plants in wayside or fallows, algae, etc.). | K29: Feeds are added compared to a control practice (basal diet) that does not contain items which would gain the same ERA classfication. Control diets are often hay ad libitum or hay ad libitum + maize stover. | L29: Animals.Out | M29: A.Level.Name | N29: FALSE
A30: d17.3 | B30: Animals | C30: Animals | D30: Feed Addition | E30: FA | F30: Agroforestry Fodders (Added) | G30: FA+AF | H30: Feed AgFor (Add) | I30: Add | J30: Feeds added to animal diets that are from agroforestry shrub or tree fodders or other woody plants. | K30: Feeds are added compared to a control practice (basal diet) that does not contain items which would gain the same ERA classfication. Control diets are often hay ad libitum or hay ad libitum + maize stover. | L30: Animals.Out | M30: A.Level.Name | N30: FALSE
A31: d17.4 | B31: Animals | C31: Animals | D31: Feed Addition | E31: FA | F31: Animal Manures (Added) | G31: FA+AM | H31: Feed Manure (Add) | I31: Add | J31: Feeds added to animal diets that are animal manures. | K31: Feeds are added compared to a control practice (basal diet) that does not contain items which would gain the same ERA classfication. Control diets are often hay ad libitum or hay ad libitum + maize stover. | L31: Animals.Out | M31: A.Level.Name | N31: FALSE
A32: d17.5 | B32: Animals | C32: Animals | D32: Feed Addition | E32: FA | F32: Other Feed (Added) | G32: FA+O | H32: Feed Other (Add) | I32: Add | J32: Feeds added to animal diets that are non-plant or non-manure based materials. These typically include materials that are the by-product of animal processing (e.g., bone meal or fish meal). | K32: Feeds are added compared to a control practice (basal diet) that does not contain items which would gain the same ERA classfication. Control diets are often hay ad libitum or hay ad libitum + maize stover. | L32: Animals.Out | M32: A.Level.Name | N32: FALSE
A33: d18.1 | B33: Animals | C33: Animals | D33: Feed Substitution | E33: FS | F33: Crop Fodders (Substituted) | G33: FS+CF | H33: Feed Crop (Sub) | I33: Sub | J33: Components of a basal diet fully or partially substituted for residues from crops not primarily grown for fodder, but for another purpose (e.g. consumption). These can be field residues (for example maize stalks left over once the grain component has been harvested) and or processing residues (for example the maize bran produced as a byproduct of milling flour). | K33: Substitutions are typically defined by the author. Usually they are looking to substitute a conventional (e.g. purchased diet) with cheaper or more sustainable alternatives. | L33: Animals.Out | M33: A.Level.Name | N33: FALSE
A34: d18.2 | B34: Animals | C34: Animals | D34: Feed Substitution | E34: FS | F34: Non Crop Fodders (Substituted) | G34: FS+NC | H34: Feed NonCrop (Sub) | I34: Sub | J34: Components of a basal diet fully or partially substituted for non-woody crops grown primarily for fodder (e.g., alfafa or clover grown to feed to cattle) or non-woody plants harvested from non-cropped areas (e.g., forage grasses such as napier grass grown to stabilize terraces, cactus harvested from boundary fences, wild growing plants in wayside or fallows, algae, etc.). Feeds are added compared to a base practice control such as hay ad libitum only. | K34: Substitutions are typically defined by the author. Usually they are looking to substitute a conventional (e.g. purchased diet) with cheaper or more sustainable alternatives. | L34: Animals.Out | M34: A.Level.Name | N34: FALSE
A35: d18.3 | B35: Animals | C35: Animals | D35: Feed Substitution | E35: FS | F35: Agroforestry Fodders (Substituted) | G35: FS+AF | H35: Feed AgFor (Sub) | I35: Sub | J35: Components of a basal diet fully or partially substituted for agroforestry shrub or tree fodders (woody plants). | K35: Substitutions are typically defined by the author. Usually they are looking to substitute a conventional (e.g. purchased diet) with cheaper or more sustainable alternatives. | L35: Animals.Out | M35: A.Level.Name | N35: FALSE
A36: d18.4 | B36: Animals | C36: Animals | D36: Feed Substitution | E36: FS | F36: Animal Manures (Substituted) | G36: FS+AM | H36: Feed Manure (Sub) | I36: Sub | J36: Components of a basal diet fully or partially substituted for animal manures. | K36: Substitutions are typically defined by the author. Usually they are looking to substitute a conventional (e.g. purchased diet) with cheaper or more sustainable alternatives. | L36: Animals.Out | M36: A.Level.Name | N36: FALSE
A37: d18.5 | B37: Animals | C37: Animals | D37: Feed Substitution | E37: FS | F37: Other Feed (Substituted) | G37: FS+O | H37: Feed Byproducts (Sub) | I37: Sub | J37: Components of a basal diet fully or partially substituted with non-plant and non-manure based materials. These typically include materials for the by-product of animal processing (e.g., bone meal or fish meal). | K37: Substitutions are typically defined by the author. Usually they are looking to substitute a conventional (e.g. purchased diet) with cheaper or more sustainable alternatives. | L37: Animals.Out | M37: A.Level.Name | N37: FALSE
A38: d22.1 | B38: Animals | C38: Animals | D38: Feed Processing | E38: FP | F38: Chemically Processed Feed | G38: FP+Ch | H38: Feed Chem Process | I38: NA | J38: Fodders that have been chemically processed, for example urea-treated stover or fermented fodders. Silage is a type of fodder made from green foliage crops which have been preserved by acidification, achieved through fermentation. | L38: Animals.Out | M38: A.Level.Name | N38: FALSE
A39: d22.2 | B39: Animals | C39: Animals | D39: Feed Processing | E39: FP | F39: Mechanically Processed Feed | G39: FP+Me | H39: Feed Mech Process | I39: NA | J39: Fodders or plant wastes that have been mechanically processed, for example chopped or pelletted grasses or ground orange peel. | L39: Animals.Out | M39: A.Level.Name | N39: FALSE
A40: d22.3 | B40: Animals | C40: Animals | D40: Feed Processing | E40: FP | F40: Concentrated Feed | G40: FP+Co | H40: Feed Concentrates | I40: NA | J40: Non-forage feeds rich in energy and protein. Concentrates include feeds such as maize bran, cotton seed cake, molasses, fish meal and bean cake. Non-forage feeds may use energy or protein rich part plants such as seeds, whereas forage feeds are mainly plant leaves and stems. | L40: Animals.Out | M40: A.Level.Name | N40: FALSE
A41: d9 | B41: Animals | C41: Animals | D41: Genetic Improvement | E41: GI | F41: Improved Breeds | G41: GI-Im | H41: Breed Impr | I41: NA | J41: The use of improved animal breeds, these are animals bred for specific traits usually productivity (typically breeds exotic to Africa like Friesen, Holstein or Jersey cows). | L41: Var.Out | M41: V.Level.Name | N41: FALSE
A42: d10 | B42: Animals | C42: Animals | D42: Genetic Improvement | E42: GI | F42: Hybridization or Cross Breeding | G42: GI-Hy | H42: Breed Hybrid | I42: NA | J42: The use of animal cross breeds produced by the mating (hybridization) of individuals of different breeds, varieties, or species. | L42: Var.Out | M42: V.Level.Name | N42: FALSE
A43: d13 | B43: Animals | C43: Animals | D43: Manure Management | E43: MM | F43: Manure Collection | G43: MM-Co | H43: Manure Collection | I43: NA | J43: Techniques to collect manure, e.g, increased frequency of collection and removal from the kraal. | L43: Animals.Out | M43: A.Level.Name | N43: FALSE
A44: d14 | B44: Animals | C44: Animals | D44: Manure Management | E44: MM | F44: Manure Storage | G44: MM-St | H44: Manure Storage | I44: NA | J44: Manure storage techniques such as heaps, pits or dry lots. | L44: Animals.Out | M44: A.Level.Name | N44: FALSE
A45: d15 | B45: Animals | C45: Animals | D45: Manure Management | E45: MM | F45: Manure Treatment | G45: MM-Tr | H45: Manure Treat | I45: NA | J45: Techniques for treatment of manure. | L45: Animals.Out | M45: A.Level.Name | N45: FALSE
A46: d16 | B46: Animals | C46: Animals | D46: Pasture Management | E46: PM | F46: Rotational Grazing | G46: PM+RG | H46: Grazing Rotation | I46: NA | J46: The movement of animals between different paddocks at intervals. | L46: Animals.Out | M46: A.Level.Name | N46: FALSE
A47: d11 | B47: Animals | C47: Animals | D47: Pasture Management | E47: PM | F47: Improved Pasture (N fixing) | G47: PM+IP+N | H47: Pasture Impr (Nfix) | I47: Nfix | J47: The planting of pastures with leguminous forages. | L47: Animals.Out | M47: A.Level.Name | N47: FALSE
A48: d12 | B48: Animals | C48: Animals | D48: Pasture Management | E48: PM | F48: Improved Pasture (Non N fixing) | G48: PM+IP-N | H48: Pasture Impr (nonNfix) | I48: nonNfix | J48: The planting of pastures with non-leguminous forages. | L48: Animals.Out | M48: A.Level.Name | N48: FALSE
A49: d19 | B49: Animals | C49: Animals | D49: Pasture Management | E49: PM | F49: Controlled Grazing | G49: PM+CG | H49: Grazing Controlled | I49: NA | J49: The restriction of animal movement within pastures. Controlled grazing is known by many names, such as rotational grazing, rotational stocking, intensive grazing and strip grazing. Typically a large pasture is subdivided into several smaller pastures (paddocks) by cross fencing and animals stocked in one of the paddocks. When the forage has been removed, cattle are rotated to the next paddock. | L49: Animals.Out | M49: A.Level.Name | N49: FALSE
... A51: d1 | B51: Animals | C51: Animals | D51: Aquasilviculture | E51: AqS | F51: Aquasilviculture | G51: AqS | H51: Aquasilviculture | I51: NA | J51: An aquaculture practice in combination with a sylviculture practice in close spatial proximity. The classic example of this practice is fish or crustacean farming in mangroves, to conserve or restore mangrove trees and produce food. | L51: Animals.Out | M51: A.Level.Name | N51: FALSE
A52: h60 | B52: Animals | C52: Animals | D52: Feed Addition; Feed Substitution | F52: Basal or Conventional Diet | H52: Diet Control | J52: A diet fed to animals without additional of anything. | K52: A control for addition (supplementation) of feeds. | N52: FALSE
A53: h61 | B53: Animals | C53: Animals | D53: Feed Addition; Feed Substitution | F53: Conventional Supplement Use | H53: Diet Control | J53: Supplement given to animals by the farmer or deemed control by author and is | K53: A control for addition (supplementation) or substitution of feeds. | N53: FALSE
A54: h10.3 | B54: Animals | C54: Animals | D54: Manure Management | F54: Conventional Manure Handling | H54: Manure Hand Conv | J54: Conventional Manure handling (farmer practice). | N54: FALSE
A55: h11 | B55: Animals | C55: Animals | D55: Pasture Management | F55: Conventional Pasture Management | H55: Pasture Man Conv | J55: Conventional pasture management. This could be the traditional or farmer practice or a practice the authors state as an unimproved control practice. | N55: FALSE
A56: h55.2 | B56: Animals | C56: Animals | D56: Genetic Improvement | F56: Unspecified | H56: Unspecified | J56: The breed breed practice is not specified as being improved or unimproved | N56: FALSE
A57: h55.1 | B57: Animals | C57: Animals | D57: Genetic Improvement | F57: Unimproved Breed | H57: Breed Unimpr | J57: A local or otherwise unimproved animal breed. | K57: A control for improved breeds/hybrid and cross breeds. | N57: FALSE
A58: b34 | B58: Blue Water Management | C58: Blue Water Management | D58: Irrigation | E58: Ir | F58: Drip Irrigation | G58: Ir+Dr | H58: Irrigation Drip | I58: NA | J58: The use of plastic pipes to drip water into the soil at low pressure. | L58: Irrig.Out | M58: I.Level.Name | N58: FALSE
A59: b37 | B59: Blue Water Management | C59: Blue Water Management | D59: Deficit Irrigation | E59: DIr | F59: Deficit Irrigation | G59: Ir+De | H59: Irrigation Deficit | I59: NA | J59: Application of water below full crop requirements compared to a control of conventional irrigation. | L59: Irrig.Out | M59: I.Level.Name | N59: FALSE
A60: b72 | B60: Blue Water Management | C60: Blue Water Management | D60: Irrigation | E60: Ir | F60: Sprinkler Irrigation | G60: Ir+S | H60: Irrigation Sprinkers | I60: NA | J60: Application of irrigation through sprinkler technology. | L60: Irrig.Out | M60: I.Level.Name | N60: FALSE
A61: b36 | B61: Blue Water Management | C61: Blue Water Management | D61: Irrigation | E61: Ir | F61: Alternate Partial Rootzone Irrigation | G61: Ir+APR | H61: Irrigation APRI | I61: NA | J61: Part of the root is exposed to drying soil and the remaining is irrigated in accordance with crop requirements and soil drying rate. This practice is also called partial root zone drying (PRD). | L61: Irrig.Out | M61: I.Level.Name | N61: FALSE
A62: b54 | B62: Blue Water Management | C62: Blue Water Management | D62: Supplemental Irrigation | E62: SIr | F62: Supplemental Irrigation | G62: Ir+Su | H62: Irrigation Supp | I62: NA | J62: The addition of irrigation to typically rainfed crops. | L62: Irrig.Out | M62: I.Level.Name | N62: FALSE
A63: b53 | B63: Blue Water Management | C63: Blue Water Management | D63: Irrigation | E63: Ir | F63: Irrigation (Other) | G63: IrO | H63: Irrigation Other | I63: NA | J63: The use of improved irrigation that isn't more specifically defined. | L63: Irrig.Out | M63: I.Level.Name | N63: FALSE
A64: b13 | B64: Blue Water Management | C64: Blue Water Management | D64: Improved Rice Management | E64: IRM | F64: Alternate Wetting & Drying (AWD) | G64: IRM+AWD | H64: AWD | I64: NA | J64: Repeated flooding and draining of paddy rice fields, managed responsively in relation to soil moisture levels. | L64: NA | M64: NA | N64: FALSE
A65: b14.1 | B65: Blue Water Management | C65: Blue Water Management | D65: Improved Rice Management | E65: IRM | F65: Midseason Drainage | G65: IRM+MD | H65: Midseason Drainage | I65: NA | J65: The paddy rice field is drained during the season, but usually only once. | L65: NA | M65: NA | N65: FALSE
A66: b14.2 | B66: Blue Water Management | C66: Blue Water Management | D66: Improved Rice Management | E66: IRM | F66: Reduced Water Use in Rice | G66: IRM+RWU | H66: Reduced Water Use | I66: NA | J66: Practices that reduce water use in rice that are not alternate wetting & drying (AWD) or midseason drainage. Consider creating a new practice rather than using this code. | L66: NA | M66: NA | N66: FALSE
A67: b15 | B67: Blue Water Management | C67: Blue Water Management | D67: Improved Rice Management | E67: IRM | F67: System of Rice Intensification (SRI) | G67: SRI | H67: SRI | I67: NA | J67: If possible it is best to unpack SRI into its component practices rather than using this practice code. If impossible to disaggregate the SRI practice then use this code. SRI is a system package which can include early transplanting (8-12 days), 25cm spacing and alternate wet and dry. Identified by authors. | L67: NA | M67: NA | N67: TRUE
A68: b3.1 | B68: Crop Management | C68: Crop Management | D68: Crop Rotation | E68: CRo | F68: Rotation (N fixing) | G68: CRo+N | H68: Rotation (Nfix) | I68: Nfix | J68: A crop rotation sequence of two or more legumes. A general definition of rotation is that more than one crop is grown in the same location, but across different growing season (diversification in time). Different varieties of the same crop do not count as rotation. A crop is not counted in a rotation sequence when it is obviously a minor intercrop to a main crop which is invariant over time (typically there is standard planting of the main crop from year to year and the intercrop is squeezed in-between the rows of the main crop, for example cowpea planted at a low density inbetween maize rows). | K68: Crops should be grown for harvest and not as cover crop or green manure. | L68: Rot.Out | M68: ED.Rot | N68: FALSE
A69: b3.2 | B69: Crop Management | C69: Crop Management | D69: Crop Rotation | E69: CRo | F69: Rotation (Non N fixing) | G69: CRo-N | H69: Rotation (nonNfix) | I69: nonNfix | J69: A crop rotation sequence with two or more non-legumes. A general definition of rotation is that more than one crop is grown in the same location, but across different growing season (diversification in time). Different varieties of the same crop do not count as rotation. | K69: Crops should be grown for harvest and not as cover crop or green manure. | L69: Rot.Out | M69: ED.Rot | N69: FALSE
A70: b43 | B70: Crop Management | C70: Crop Management | D70: Crop Rotation | E70: CRo | F70: Rotation (N fixing & Non N fixing) | G70: CRo±N | H70: Rotation (Mixed) | I70: Mixed | J70: A crop rotation sequence containing non-leguminous and leguminous crops (e.g. a maize/bean rotation a maize-bean intercrop followed by cassava). A general definition of rotation is that more than one crop is grown in the same location, but across different growing season (diversification in time). Different varieties of the same crop do not count as rotation. A crop is not counted in a rotation sequence when it is obviously a minor intercrop to a main crop which is invariant over time (typically there is standard planting of the main crop from year to year and the intercrop is squeezed in-between the rows of the main crop, for example cowpea planted at a low density inbetween maize rows). | K70: Crops should be grown for harvest and not as cover crop or green manure. | L70: Rot.Out | M70: ED.Rot | N70: FALSE
A71: b44 | B71: Crop Management | C71: Crop Management | D71: Crop Rotation | F71: Complex Rotation | H71: Rotation (Complex) | I71: Complex | J71: A crop rotation sequence with three or more species or rotations with different annual cycles. If intercropping is present in a complex rotation then this should also be captured with an intercropping code. A species is not counted towards a rotation sequence species count when it is obviously a minor intercrop to a main crop which remains invariant (typically there is standard planting of the main crop from year to year and the intercrop is squeezed in-between the rows of the main crop, for example cowpea planted at a low density inbetween maize rows). If it is not clear which crops are main or minor or not then count them all towards a complex rotation total (so an experiement might have maize one year, then the next year some maize rows are replaced with beans, in this case the beans are counted as a rotation crop and the number of species is two). A general definition of rotation is that more than one crop is grown in the same location, but across different growing season (diversification in time). Different varieties of the same crop do not count as rotation. Crops should be grown for harvest and not as cover crop or green manure. | L71: Rot.Out | M71: ED.Rot | N71: TRUE
A72: b31 | B72: Crop Management | C72: Crop Management | D72: Crop Rotation | F72: Intercrop Rotation | H72: Rotation (Int Only) | I72: Int Only | J72: Rotation where a main crop remains the same between seasons (no change in spatial location or crop identity), but the minor intercrop is not always present. If the same crop is intercropped throughout the sequence (e.g. Maize-Beans/Maize/Maize-Beans) then this requires a Partial Intercropping code (b50.1, b50.2 or b50.3) or if the intercrop changes throughout the sequence (e.g. Maize-Beans/Maize-Millet/Maize-Beans) this requires a Complex Intercrop Rotation code (b57). If the intercrop is mostly one crop for a long sequence, but rarely something else is planted, we still consider this to be relevant to the Partial Intercropping code. A general definition of rotation is that more than one crop is grown in the same location, but across different growing season (diversification in time). Different varieties of the same crop do not count as rotation. A crop is not counted in a rotation sequence when it is obviously a minor intercrop to a main crop which is invariant over time (typically there is standard planting of the main crop from year to year and the intercrop is squeezed in-between the rows of the main crop, for example cowpea planted at a low density inbetween maize rows). Crops should be grown for harvest and not as cover crop or green manure (if the latter see the green manure practices). | L72: Rot.Out | M72: ED.Rot | N72: TRUE
A73: b48.1 | B73: Crop Management | C73: Crop Management | D73: Double Cropping | F73: Double Cropping (N fixing & Non N fixing) | J73: A double cropping system where two different crops are planting sequentially within the same growing season. Some crops fix nitrogen others do not. | M73: ED.Int | N73: FALSE
A74: b48.2 | B74: Crop Management | C74: Crop Management | D74: Double Cropping | F74: Double Cropping (Non N fixing) | J74: A double cropping system where two different crops are planting sequentially within the same growing season. No crops fix nitrogen. | M74: ED.Int | N74: FALSE
A75: b48.3 | B75: Crop Management | C75: Crop Management | D75: Double Cropping | F75: Double Cropping (N fixing) | J75: A double cropping system where two different crops are planting sequentially within the same growing season. All crops fix nitrogen. | M75: ED.Int | N75: FALSE
A76: b48.4 | B76: Crop Management | C76: Crop Management | D76: Double Cropping | F76: Double Cropping (Monocrop) | J76: A double cropping system where the same crop is planted more than once and sequentially within the same growing season. | M76: ED.Int | N76: FALSE
A77: b49.1 | B77: Crop Management | C77: Crop Management | D77: Intercropping | F77: Sequential Intercropping (N fixing & Non N fixing) | J77: An intercropping and double cropping system where two crops are planted together at the start of the season, then one is harvested and another crop planted whilst the non-harvested crop is growing (all within the same season). Some crops fix nitrogen others does not. | M77: ED.Int | N77: FALSE
A78: b49.2 | B78: Crop Management | C78: Crop Management | D78: Intercropping | F78: Sequential Intercropping (Non N fixing) | J78: An intercropping and double cropping intercropping system where two crops are planted together at the start of the season, then one is harvested and another crop planted whilst the non-harvested crop is growing (all within the same season). No crops fix nitrogen. | M78: ED.Int | N78: FALSE
A79: b49.3 | B79: Crop Management | C79: Crop Management | D79: Intercropping | F79: Sequential Intercropping (N fixing) | J79: An intercropping and double cropping system where two crops are planted together at the start of the season, then one is harvested and another crop planted whilst the non-harvested crop is growing (all within the same season). All crops fix nitrogen. | M79: ED.Int | N79: FALSE
A80: b61.1 | B80: Crop Management | C80: Crop Management | D80: Intercropping | F80: Relay Intercropping (N fixing & Non N fixing) | J80: A crop is planted and then another is planted with that crop, but at a later date within the same season. Some crops fixes nitrogen the others does not. | M80: ED.Int | N80: FALSE
A81: b61.2 | B81: Crop Management | C81: Crop Management | D81: Intercropping | F81: Relay Intercropping (Non N fixing) | J81: A crop is planted and then another is planted with that crop, but at a later date within the same season. No crops fixes nitrogen. | M81: ED.Int | N81: FALSE
A82: b61.3 | B82: Crop Management | C82: Crop Management | D82: Intercropping | F82: Relay Intercropping (N fixing) | J82: A crop is planted and then another is planted with that crop, but at a later date within the same season. All crop fix nitrogen. | M82: ED.Int | N82: FALSE
A83: b13.3 | B83: Crop Management | C83: Crop Management | D83: Green Manure | F83: Relay Green Manure (N fixing & Non N fixing) | J83: A crop is planted and then a green manure is planted with that crop, but at a later date within the same season. Some crops fixes nitrogen the others does not. A green manure is usually planted to improve soil quality and it should not be harvested crop. | M83: ED.Int | N83: FALSE
A84: b12.3 | B84: Crop Management | C84: Crop Management | D84: Green Manure | F84: Relay Green Manure (Non N fixing) | J84: A crop is planted and then a green manure is planted with that crop, but at a later date within the same season. No crops fixes nitrogen. | M84: ED.Int | N84: FALSE
A85: b11.3 | B85: Crop Management | C85: Crop Management | D85: Green Manure | F85: Relay Green Manure (N fixing) | J85: A crop is planted and then a green manure is planted with that crop, but at a later date within the same season. All crop fix nitrogen. | M85: ED.Int | N85: FALSE
A86: b25 | B86: Crop Management | C86: Crop Management | D86: Intercropping | E86: In | F86: Intercrop (N fixing & Non N fixing) | G86: In±N | H86: Intercrop (Mixed) | I86: Mixed | J86: An intercropping system with a legume and non-legume. Intercropping is where more than one crop is grown at the same time in the same area of management (typically a single field), this is diversification in space rather than diversification in time. Crops should be grown for harvest and not as cover crop or green manure (if the latter see the green manure practices). | L86: Int.Out | M86: ED.Int | N86: FALSE
A87: b50.1 | B87: Crop Management | C87: Crop Management | D87: Intercropping | E87: In | F87: Intercrop (Non N fixing) | G87: In-N | H87: Intercrop (nonNfix) | I87: nonNfix | J87: An intercropping system with two non-legumes. Intercropping is where more than one crop is grown at the same time in the same area of management (typically a single field), this is diversification in space rather than diversification in time. Crops should be grown for harvest and not as cover crop or green manure (if the latter see the green manure practices). | L87: Int.Out | M87: ED.Int | N87: FALSE
A88: b50.2 | B88: Crop Management | C88: Crop Management | D88: Intercropping | E88: In | F88: Intercrop (N fixing) | G88: In+N | H88: Intercrop (Nfix) | I88: Nfix | J88: An intercropping system with two or more legumes (edible or marketable). Intercropping is where more than one crop is grown at the same time in the same area of management (typically a single field), this is diversification in space rather than diversification in time. Crops should be grown for harvest and not as cover crop or green manure (if the latter see the green manure practices). | L88: Int.Out | M88: ED.Int | N88: FALSE
A89: b50.3 | B89: Crop Management | C89: Crop Management | D89: Intercropping | F89: Complex Intercrop | H89: Intercrop (Complex) | I89: Complex | J89: An intercropping system that is too complex to descirbe using existing ERA definitions. Typically involving multiple intercropping practices at the same time. Please use the notes to descirbe this practice. | L89: Int.Out | M89: ED.Int
A90: b50.4 | B90: Crop Management | C90: Crop Management | D90: Intercropping | E90: In | F90: Intercrop (Unspecified) | G90: In | H90: Intercrop (Unsp.) | I90: Unsp. | J90: An intercropping system is present, but no details on composition are available. Intercropping is where more than one crop is grown at the same time in the same area of management (typically a single field), this is diversification in space rather than diversification in time. Crops should be grown for harvest and not as cover crop or green manure (if the latter see the green manure practices). | K90: Only use this practice where there are no details presented about an intercropping paper. All we know is that intercropping was present. | L90: Int.Out | M90: ED.Int | N90: FALSE
A91: b55.1 | B91: Crop Management | C91: Crop Management | D91: Intercropping | F91: Partial Intercrop (N fixing & Non N fixing) | H91: Intercrop (Part; Mixed) | I91: Part;Mixed | J91: An intercropping system with a legume and non-legume where intercropping is not present every season (spatial diversification that is variable over time). For example a repeating sequence of Maize followed by a Maize-Cowpea intercrop, this would also get an intercrop rotation code. Intercropping is where more than one crop is grown at the same time in the same area of management (typically a single field), this is diversification in space rather than diversification in time. Crops should be grown for harvest and not as cover crop or green manure (if the latter see the green manure practices). | L91: Int.Out | M91: ED.Int | N91: TRUE
A92: b55.2 | B92: Crop Management | C92: Crop Management | D92: Intercropping | F92: Partial Intercrop (Non N fixing) | H92: Intercrop (Part; nonNfix) | I92: Part;nonNfix | J92: An intercropping system with two non-legume crops where intercropping is not present every season (spatial diversification that is variable over time). For example a repeating sequence of Maize followed by a Maize-Cowpea intercrop, this would also get an intercrop rotation code. Intercropping is where more than one crop is grown at the same time in the same area of management (typically a single field), this is diversification in space rather than diversification in time. Crops should be grown for harvest and not as cover crop or green manure (if the latter see the green manure practices). | L92: Int.Out | M92: ED.Int | N92: TRUE
A93: b55.3 | B93: Crop Management | C93: Crop Management | D93: Intercropping | F93: Partial Intercrop (N fixing) | H93: Intercrop (Part; Nfix) | I93: Part;Nfix | J93: An intercropping system with two legume crops where intercropping is not present every season (spatial diversification that is variable over time). For example a repeating sequence of Maize followed by a Maize-Cowpea intercrop, this would also get an intercrop rotation code. Intercropping is where more than one crop is grown at the same time in the same area of management (typically a single field), this is diversification in space rather than diversification in time. Crops should be grown for harvest and not as cover crop or green manure (if the latter see the green manure practices). | L93: Int.Out | M93: ED.Int | N93: TRUE
A94: b57 | B94: Crop Management | C94: Crop Management | D94: Intercropping | F94: Complex Intercrop Rotation | H94: Intercrop (Rot; Complex) | I94: Rot Complex | J94: There is a main crop (there is no change in spatial location or crop identity) and intercrop (minor) crop sequence , but the nature of the main-intercrop pairing changes between seasons (e.g. Maize-Beans/Maize-Millet/Maize-Beans) , this can be thought of as rotation in the intercrop (minor crop). If the intercrop is mostly one crop for a long sequence, but rarely something else is planted, we still consider this to be relevant to the Partial Intercropping code. Intercropping is where more than one crop is grown at the same time in the same area of management (typically a single field), this is diversification in space rather than diversification in time. Crops should be grown for harvest and not as cover crop or green manure (if the latter see the green manure practices). | L94: Rot.Out | M94: ED.Rot | N94: TRUE
A95: b59 | B95: Crop Management | C95: Crop Management | D95: Intercropping or Rotation | E95: In/CRo | F95: Intercropping or Rotation (N fixing & Non N fixing) | G95: In/CRo±N | H95: Int or Rot (Mixed) | I95: Mixed | J95: Only use this practices where a paper states that legume intercropping or rotation was used, but the outcomes do not distinguish between the two. | K95: This outcome will typically relate to farmer trials or surveys. | L95: Rot.Out | M95: ED.Rot | N95: FALSE
A96: c1 | B96: Energy | C96: Energy | D96: Biogas | E96: BG | F96: Biogas | G96: BG | H96: Biogas Prod | I96: NA | J96: Biogas production from from anaerobic biodigesters. | K96: The comparison for this practice can be wood fuel or charcoal production as traditional energy sources (the outcomes would be cost, labor, fuel use, cooking time, etc.). | L96: E.Out | M96: E.Level.Name | N96: FALSE
A97: c4 | B97: Energy | C97: Energy | D97: Biogas | F97: Biofertilizer | H97: Biofertilizer | I97: NA | J97: Fertilizer (biofertilizer) produced using a biodigestor slurry. | K97: USE COMPOST CODE b29 | L97: E.Out | M97: E.Level.Name | N97: TRUE
A98: c3 | B98: Energy | C98: Energy | D98: Biogas | E98: BG | F98: Biogas Switching | G98: BG+Sw | H98: Biogas Switch | I98: NA | J98: Switching of biodigestors biomass feedstocks. | K98: Biodigestor papers only. | L98: E.Out | M98: E.Level.Name | N98: FALSE
A99: c2 | B99: Energy | C99: Energy | D99: Cookstove | E99: CS | F99: Improved Cookstoves | G99: CS | H99: Cookstove Improv | I99: NA | J99: Improved cookstove designed to burn biomass fuels in a cleaner and more efficient manner than conventional practice (e.g., traditional three-stone fires). | L99: E.Out | M99: E.Level.Name | N99: FALSE
A100: c5 | B100: Energy | C100: Energy | D100: Cookstove | E100: CS | F100: Cookstove Switching | G100: CS+Sw | H100: Cookstove Switch | I100: NA | J100: Switching cookstove biomass feedstocks. | K100: Cooking fuel studies only. Changing the source of fuel doesn't count (e.g. unsustainable wood from source A vs sustianable fuel from source B). | L100: E.Out | M100: E.Level.Name | N100: FALSE
A101: h14 | B101: Energy | C101: Energy | D101: Cookstove | F101: Unimproved Stove Technology | H101: Cookstove Unimpr | J101: Use of traditional stoves for burning biomass fuels lile traditional three-stone; a control for improved cookstoves | K101: A control for an improved cookstove. | N101: FALSE
...

Sheet prod
A1: EU | B1: Product.Type | C1: Product.Type.Code | D1: Product.Subtype | E1: Product.Subtype.Code | F1: Product | G1: Product.Simple | H1: Product.Simple.Code | I1: Component | J1: Latin.Name | K1: Notes | L1: Nfix | M1: Tree | N1: Mulched | O1: Incorp | P1: Unknown.Fate | Q1: ECOCROP.Name | R1: ECOCROP.Notes | S1: ICC_Code_1.1 | T1: ICC_CropName | U1: Livestock_Group | V1: Livestock_Class | W1: Livestock_Descriptor | X1: CPC_Code_2.1 | Y1: WFO_Code | Z1: UN_Comtrade_Code_1 | AA1: UN_Comtrade_Description_1 | AB1: UN_Comtrade_Code_2 | AC1: UN_Comtrade_Description_2 | AD1: MapSPAM
A2: a5 | B2: Animal | C2: Animal | D2: Bovine | E2: Bo | F2: Buffalo | G2: Buffalo | H2: Buf | I2: Meat | J2: Bubalus bubalis | L2: NA | M2: NA | N2: NA | O2: NA | P2: NA | Q2: NA | R2: NA | S2: NA | T2: NA | U2: 1 | V2: 12 | W2: buffaloes | X2: 2112 | Y2: NA | Z2: 201 | AA2: meat of bovine animals; fresh or chilled
A3: a8 | B3: Animal | C3: Animal | D3: Bovine | E3: Bo | F3: Cattle (Meat) | G3: Cattle | H3: Cat | I3: Meat | L3: NA | M3: NA | N3: NA | O3: NA | P3: NA | Q3: NA | R3: NA | S3: NA | T3: NA | U3: 1 | V3: 11 | W3: cattle | X3: 2111 | Y3: NA | Z3: 201 | AA3: meat of bovine animals; fresh or chilled
A4: a8.1 | B4: Animal | C4: Animal | D4: Bovine | E4: Bo | F4: Cattle (Milk) | G4: Cattle | H4: Cat | I4: Milk | L4: NA | M4: NA | N4: NA | O4: NA | P4: NA | Q4: NA | R4: NA | S4: NA | T4: NA | U4: 1 | V4: 11 | W4: cattle | X4: 2111 | Y4: NA | Z4: 401 | AA4: milk and cream; not concentrated, not containing added sugar or other sweetening matter
A5: a6 | B5: Animal | C5: Animal | D5: Camelid | E5: Cam | F5: Camel (Meat) | G5: Camel | H5: Cam | I5: Meat | J5: Camelus dromedarius | L5: NA | M5: NA | N5: NA | O5: NA | P5: NA | Q5: NA | R5: NA | S5: NA | T5: NA | U5: 5 | V5: 51 | W5: camels | X5: 2121 | Y5: NA | Z5: 20860 | AA5: meat and edible meat offal; of camels and other camelids (Camelidae), fresh, chilled or frozen
A6: a6.1 | B6: Animal | C6: Animal | D6: Camelid | E6: Cam | F6: Camel (Milk) | G6: Camel | H6: Cam | I6: Milk | J6: Camelus dromedarius | L6: NA | M6: NA | N6: NA | O6: NA | P6: NA | Q6: NA | R6: NA | S6: NA | T6: NA | U6: 5 | V6: 51 | W6: camels | X6: 2121 | Y6: NA | Z6: 10613 | AA6: mammals; live, camels and other camelids (Camelidae) | AB6: 401 | AC6: milk and cream; not concentrated, not containing added sugar or other sweetening matter
A7: a13 | B7: Animal | C7: Animal | D7: Caprine | E7: Cap | F7: Goat (Meat) | G7: Goat | H7: Goa | I7: Meat | J7: Capra aegagrus hircus | L7: NA | M7: NA | N7: NA | O7: NA | P7: NA | Q7: NA | R7: NA | S7: NA | T7: NA | U7: 2 | V7: 22 | W7: goats | X7: 2123 | Y7: NA | Z7: 20450 | AA7: meat; of goats, fresh, chilled or frozen
A8: a13.1 | B8: Animal | C8: Animal | D8: Caprine | E8: Cap | F8: Goat (Milk) | G8: Goat | H8: Goa | I8: Milk | J8: Capra aegagrus hircus | L8: NA | M8: NA | N8: NA | O8: NA | P8: NA | Q8: NA | R8: NA | S8: NA | T8: NA | U8: 2 | V8: 22 | W8: goats | X8: 2123 | Y8: NA | Z8: 10420 | AA8: Goats; live | AB8: 401 | AC8: milk and cream; not concentrated, not containing added sugar or other sweetening matter
A9: a20 | B9: Animal | C9: Animal | D9: Caprine | E9: Cap | F9: Sheep (Meat) | G9: Sheep | H9: Shee | I9: Meat | J9: Ovis aries | L9: NA | M9: NA | N9: NA | O9: NA | P9: NA | Q9: NA | R9: NA | S9: NA | T9: NA | U9: 2 | V9: 21 | W9: sheep | X9: 2122 | Y9: NA | Z9: 204 | AA9: meat of sheep or goats; fresh, chilled or frozen
A10: a20.1 | B10: Animal | C10: Animal | D10: Caprine | E10: Cap | F10: Sheep (Milk) | G10: Sheep | H10: Shee | I10: Milk | J10: Ovis aries | L10: NA | M10: NA | N10: NA | O10: NA | P10: NA | Q10: NA | R10: NA | S10: NA | T10: NA | U10: 2 | V10: 21 | W10: sheep | X10: 2122 | Y10: NA | Z10: 10410 | AA10: sheep; live | AB10: 401 | AC10: milk and cream; not concentrated, not containing added sugar or other sweetening matter
A11: a20.2 | B11: Animal | C11: Animal | D11: Caprine | E11: Cap | F11: Sheep (Wool) | G11: Sheep | H11: Shee | I11: Wool | J11: Ovis aries | L11: NA | M11: NA | N11: NA | O11: NA | P11: NA | Q11: NA | R11: NA | S11: NA | T11: NA | U11: 2 | V11: 21 | W11: sheep | X11: 2122 | Y11: NA | Z11: 10410 | AA11: sheep; live
A12: n8 | B12: Plant | C12: Plant | D12: Cash Crops | E12: CaCr | F12: Aloe | G12: Aloe | H12: Alo | I12: Leaf | J12: Aloe vera;Aloe sp | L12: No | M12: No | N12: b27.2 | O12: b41.2 | P12: b40.2 | Q12: Aloe sp. | R12: Aloe arborescens + Aloe barbadensis + Aloe ferox + Aloe perryi | S12: no match | T12: no match | U12: NA | V12: NA | W12: NA | X12: NA | Y12: wfo-0000758976-wfo-4000001341 | Z12: no match
A13: l4.1 | B13: Plant | C13: Plant | D13: Cash Crops | E13: CaCr | F13: Coffee Arabica | G13: Arabica | H13: Ara | I13: Seed | J13: Coffea arabica | L13: No | M13: Yes | N13: a17.1 | O13: a17.2 | P13: a17 | Q13: Coffea arabica | S13: 6.01.01 | T13: coffee | U13: NA | V13: NA | W13: NA | X13: NA | Y13: wfo-0000910097 | Z13: 90111 | AA13: coffee; not roasted or decaffeinated | AD13: arabica coffee
A14: l4.2 | B14: Plant | C14: Plant | D14: Cash Crops | E14: CaCr | F14: Coffee Arabica (Pods) | G14: Arabica | H14: Ara | I14: Pods | J14: Coffea arabica | L14: No | M14: Yes | N14: a17.1 | O14: a17.2 | P14: a17 | Q14: Coffea arabica | S14: 6.01.01 | T14: coffee | U14: NA | V14: NA | W14: NA | X14: NA | Y14: wfo-0000910097 | Z14: 90111 | AA14: coffee; not roasted or decaffeinated | AD14: arabica coffee
A15: l18 | B15: Plant | C15: Plant | D15: Cash Crops | E15: CaCr | F15: Chamomile | G15: Chamomile | H15: Camo | I15: Flower | J15: Matricaria chamomilla | L15: No | M15: No | N15: b27.2 | O15: b41.2 | P15: b40.2 | Q15: NA | S15: no match | U15: NA | V15: NA | W15: NA | X15: NA | Y15: NA | Z15: no match
A16: l2 | B16: Plant | C16: Plant | D16: Cash Crops | E16: CaCr | F16: Cocoa or Cacao | G16: Cocoa | H16: Cocoa | I16: Unspecified | J16: Theobroma cacao | K16: Seeds or beans | L16: No | M16: Yes | N16: a17.1 | O16: a17.2 | P16: a17 | Q16: Theobroma cacao | S16: 6.01.04 | T16: cocoa (cacao) | U16: NA | V16: NA | W16: NA | X16: NA | Y16: wfo-0000458440 | Z16: 180100 | AA16: cocoa beans; whole or broken, raw or roasted | AD16: cocoa
A17: l2.1 | B17: Plant | C17: Plant | D17: Cash Crops | E17: CaCr | F17: Cocoa or Cacao (Beans) | G17: Cocoa | H17: Cocoa | I17: Seed | J17: Theobroma cacao | K17: Seeds or beans | L17: No | M17: Yes | N17: a17.1 | O17: a17.2 | P17: a17 | Q17: Theobroma cacao | S17: 6.01.04 | T17: cocoa (cacao) | U17: NA | V17: NA | W17: NA | X17: NA | Y17: wfo-0000458440 | Z17: 180100 | AA17: cocoa beans; whole or broken, raw or roasted | AD17: cocoa
A18: l2.2 | B18: Plant | C18: Plant | D18: Cash Crops | E18: CaCr | F18: Cocoa or Cacao (Butter) | G18: Cocoa | H18: Cocoa | I18: Oil | J18: Theobroma cacao | K18: Cocoa liquor, cocoa butter or chocolate | L18: No | M18: Yes | N18: a17.1 | O18: a17.2 | P18: a17 | Q18: Theobroma cacao | S18: 6.01.04 | T18: cocoa (cacao) | U18: NA | V18: NA | W18: NA | X18: NA | Y18: wfo-0000458440 | Z18: 180400 | AA18: cocoa; butter, fat and oil | AD18: cocoa
A19: l2.3 | B19: Plant | C19: Plant | D19: Cash Crops | E19: CaCr | F19: Cocoa or Cacao (Pods) | G19: Cocoa | H19: Cocoa | I19: Pods | J19: Theobroma cacao | K19: Pods | L19: No | M19: Yes | N19: a17.1 | O19: a17.2 | P19: a17 | Q19: Theobroma cacao | S19: 6.01.04 | T19: cocoa (cacao) | U19: NA | V19: NA | W19: NA | X19: NA | Y19: wfo-0000458440 | Z19: no match | AD19: cocoa
A20: l4 | B20: Plant | C20: Plant | D20: Cash Crops | E20: CaCr | F20: Coffee | G20: Coffee | H20: Cof | I20: Seed | J20: Coffea sp | L20: No | M20: Yes | N20: a17.1 | O20: a17.2 | P20: a17 | Q20: Coffea sp. | S20: 6.01.01 | T20: coffee | U20: NA | V20: NA | W20: NA | X20: NA | Y20: wfo-4000008851 | Z20: 90111 | AA20: coffee; not roasted or decaffeinated
A21: l14 | B21: Plant | C21: Plant | D21: Cash Crops | E21: CaCr | F21: Cupuaçu | G21: Cupuaçu | H21: Cup | I21: Fruit | J21: Theobroma grandiflorum | L21: No | M21: Yes | N21: a17.1 | O21: a17.2 | P21: a17 | Q21: Theobroma grandiflorum | R21: Amazonia species used to make a cocoa like butter | S21: no match | T21: no match | U21: NA | V21: NA | W21: NA | X21: NA | Y21: wfo-0000458603 | Z21: no match
A22: h16 | B22: Plant | C22: Plant | D22: Cash Crops | E22: CaCr | F22: Guar Gum or Cluster Bean | G22: Guar Gum | H22: GuGu | I22: Seeds | J22: Cyamopsis tetragonoloba | L22: No | M22: Yes | N22: a17.1 | O22: a17.2 | P22: a17 | Q22: Cyamopsis tetragonoloba | S22: no match | T22: no match | U22: NA | V22: NA | W22: NA | X22: NA | Y22: wfo-0000189996 | Z22: 130232 | AA22: mucilages and thickeners; whether or not modified, derived from locust beans, locust bean seeds or guar seeds
A23: l17 | B23: Plant | C23: Plant | D23: Cash Crops | E23: CaCr | F23: Gum Arabic | G23: Gum Arabic | H23: Gum | I23: Sap | J23: Acacia senegal (for example) | L23: No | M23: Yes | N23: a17.1 | O23: a17.2 | P23: a17 | Q23: Acacia senegal | S23: no match | T23: no match | U23: NA | V23: NA | W23: NA | X23: NA | Y23: wfo-0000210855 | Z23: 130120 | AA23: gum arabic
A24: l15 | B24: Plant | C24: Plant | D24: Cash Crops | E24: CaCr | F24: Hibiscus or Roselle (Flowers) | G24: Hibiscus | H24: Hibi | I24: Flower | J24: Hibiscus sabdariffa | K24: Flowers for making beverages | L24: No | M24: Yes | N24: a17.1 | O24: a17.2 | P24: a17 | Q24: Hibiscus sabdariffa | S24: 9.02.01.02 | T24: kenaf | U24: NA | V24: NA | W24: NA | X24: NA | Y24: wfo-4000017873 | Z24: no match
A25: l6 | B25: Plant | C25: Plant | D25: Cash Crops | E25: CaCr | F25: Hops | G25: Hops | H25: Hop | I25: Flower | J25: Humulus lupulus | L25: No | M25: No | N25: b27.2 | O25: b41.2 | P25: b40.2 | Q25: Humulus lupulus | S25: 6.02.02.07 | T25: hops | U25: NA | V25: NA | W25: NA | X25: NA | Y25: wfo-0000725866 | Z25: 121010 | AA25: hop cones; neither ground nor powdered nor in the form of pellets
A26: I23 | B26: Plant | C26: Plant | D26: Cash Crops | E26: CaCr | F26: Khat | G26: Khat | H26: Khat | I26: Leaf | J26: Catha edulis | L26: No | M26: Yes | N26: a17.1 | O26: a17.2 | P26: a17 | U26: NA | V26: NA | W26: NA | X26: NA | Y26: wfo-0001031800
A27: l22 | B27: Plant | C27: Plant | D27: Cash Crops | E27: CaCr | F27: Moringa | G27: Moringa | H27: Mor | I27: Leaf | J27: Moringa oleifera | L27: No | M27: Yes | N27: a17.1 | O27: a17.2 | P27: a17 | Q27: Moringa oleifera | S27: 6229 | T27: Drumstick tree | U27: NA | V27: NA | W27: NA | X27: NA | Y27: wfo-0001085051 | Z27: no match
A28: l21 | B28: Plant | C28: Plant | D28: Cash Crops | E28: CaCr | F28: Pelargonium sidoides | G28: Pelargonium sidoides | H28: PeSi | I28: Tuber/Root/Bulb | J28: Pelargonium sidoides | L28: No | M28: No | N28: b27.2 | O28: b41.2 | P28: b40.2 | Q28: NA | R28: No Match | S28: no match | T28: no match | U28: NA | V28: NA | W28: NA | X28: NA | Y28: wfo-0001221559 | Z28: no match
A29: l4.2 | B29: Plant | C29: Plant | D29: Cash Crops | E29: CaCr | F29: Coffee Robusta | G29: Robusta | H29: Rob | I29: Seed | J29: Coffea canephora | L29: No | M29: Yes | N29: a17.1 | O29: a17.2 | P29: a17 | Q29: Coffea canephora | S29: 6.01.01 | T29: coffee | U29: NA | V29: NA | W29: NA | X29: NA | Y29: wfo-0000910571 | Z29: 90111 | AA29: coffee; not roasted or decaffeinated | AD29: robusta coffee
A30: l4.3 | B30: Plant | C30: Plant | D30: Cash Crops | E30: CaCr | F30: Coffee Robusta (Pods) | G30: Robusta | H30: Rob | I30: Pods | J30: Coffea canephora | L30: No | M30: Yes | N30: a17.1 | O30: a17.2 | P30: a17 | Q30: Coffea canephora | S30: 6.01.01 | T30: coffee | U30: NA | V30: NA | W30: NA | X30: NA | Y30: wfo-0000910571 | Z30: 90111 | AA30: coffee; not roasted or decaffeinated | AD30: robusta coffee
A31: l5 | B31: Plant | C31: Plant | D31: Cash Crops | E31: CaCr | F31: Rubber | G31: Rubber | H31: Rub | I31: Sap | J31: Hevea brasiliensis | L31: No | M31: Yes | N31: a17.1 | O31: a17.2 | P31: a17 | Q31: Hevea brasiliensis | S31: 9.04 | T31: rubber | U31: NA | V31: NA | W31: NA | X31: NA | Y31: wfo-0000982080 | Z31: 4001 | AA31: natural rubber, balata, gutta-percha, guayule, chicle and similar gums; in primary forms or in plates, sheets or strip
A32: l13 | B32: Plant | C32: Plant | D32: Cash Crops | E32: CaCr | F32: Stevia | G32: Stevia | H32: Stev | I32: Leaf | J32: Stevia rebaudiana | L32: No | M32: Yes | N32: a17.1 | O32: a17.2 | P32: a17 | Q32: Stevia rebaudiana | S32: no match | T32: no match | U32: NA | V32: NA | W32: NA | X32: NA | Y32: wfo-0000003546 | Z32: no match
A33: l20 | B33: Plant | C33: Plant | D33: Cash Crops | E33: CaCr | F33: Sugar Beet | G33: Sugar Beet | H33: SuBe | I33: Unspecified | J33: Beta vulgaris vulgaris | L33: No | M33: No | N33: b27.2 | O33: b41.2 | P33: b40.2 | Q33: Beta vulgaris var. saccharifera | S33: 8.01 | T33: sugar beet | U33: NA | V33: NA | W33: NA | X33: NA | Y33: wfo-0001235049 | Z33: 121291 | AA33: sugar beet; fit for human consumption, fresh, chilled, frozen or dried, whether or not ground | AD33: sugarbeet
A34: l20.1 | B34: Plant | C34: Plant | D34: Cash Crops | E34: CaCr | F34: Sugar Beet (Root) | G34: Sugar Beet | H34: SuBe | I34: Tuber/Root/Bulb | J34: Beta vulgaris vulgaris | L34: No | M34: No | N34: b27.2 | O34: b41.2 | P34: b40.2 | Q34: Beta vulgaris var. saccharifera | S34: 8.01 | T34: sugar beet | U34: NA | V34: NA | W34: NA | X34: NA | Y34: wfo-0001235049 | Z34: 121291 | AA34: sugar beet; fit for human consumption, fresh, chilled, frozen or dried, whether or not ground | AD34: sugarbeet
A35: l20.2 | B35: Plant | C35: Plant | D35: Cash Crops | E35: CaCr | F35: Sugar Beet (Sugar) | G35: Sugar Beet | H35: SuBe | I35: Sugar | J35: Beta vulgaris vulgaris | L35: No | M35: No | N35: b27.2 | O35: b41.2 | P35: b40.2 | Q35: Beta vulgaris var. saccharifera | S35: 8.01 | T35: sugar beet | U35: NA | V35: NA | W35: NA | X35: NA | Y35: wfo-0001235049 | Z35: 170112 | AA35: sugars; beet sugar, raw, in solid form, not containing added flavouring or colouring matter | AD35: sugarbeet
A36: l9 | B36: Plant | C36: Plant | D36: Cash Crops | E36: CaCr | F36: Sugar Cane | G36: Sugar Cane | H36: SuCa | I36: Unspecified | J36: Saccharum sp | L36: No | M36: No | N36: b27.2 | O36: b41.2 | P36: b40.2 | Q36: Saccharum officinarum | R36: We consider Saccharum officinarum to be the most likely species if unspecified in a paper | S36: 8.02 | T36: sugar cane for sugar or alcohol | U36: NA | V36: NA | W36: NA | X36: NA | Y36: wfo-4000033729 | Z36: 121293 | AA36: sugar cane; fit for human consumption, fresh, chilled, frozen or dried, whether or not ground | AD36: sugarcane
A37: l9.1 | B37: Plant | C37: Plant | D37: Cash Crops | E37: CaCr | F37: Sugar Cane (Cane) | G37: Sugar Cane | H37: SuCa | I37: Stem/Stalks | J37: Saccharum sp | L37: No | M37: No | N37: b27.2 | O37: b41.2 | P37: b40.2 | Q37: Saccharum officinarum | R37: We consider Saccharum officinarum to be the most likely species if unspecified in a paper | S37: 8.02 | T37: sugar cane for sugar or alcohol | U37: NA | V37: NA | W37: NA | X37: NA | Y37: wfo-4000033729 | Z37: 121293 | AA37: sugar cane; fit for human consumption, fresh, chilled, frozen or dried, whether or not ground | AD37: sugarcane
A38: l9.2 | B38: Plant | C38: Plant | D38: Cash Crops | E38: CaCr | F38: Sugar Cane (Sugar) | G38: Sugar Cane | H38: SuCa | I38: Sugar | J38: Saccharum sp | L38: No | M38: No | N38: b27.2 | O38: b41.2 | P38: b40.2 | Q38: Saccharum officinarum | R38: We consider Saccharum officinarum to be the most likely species if unspecified in a paper | S38: 8.02 | T38: sugar cane for sugar or alcohol | U38: NA | V38: NA | W38: NA | X38: NA | Y38: wfo-4000033729 | Z38: 170113 | AA38: sugars; cane sugar, raw, in solid form, as specified in subheading note 2 to this chapter, not containing added flavouring or colouring matter | AD38: sugarcane
A39: l9.3 | B39: Plant | C39: Plant | D39: Cash Crops | E39: CaCr | F39: Sugar Cane (Cane) | G39: Sugar Cane | H39: SuCa | I39: Stem/Stalks | J39: Saccharum officinarum | L39: No | M39: No | N39: b27.2 | O39: b41.2 | P39: b40.2 | Q39: Saccharum officinarum | S39: 8.02 | T39: sugar cane for sugar or alcohol | U39: NA | V39: NA | W39: NA | X39: NA | Y39: wfo-0000896660 | Z39: 121293 | AA39: sugar cane; fit for human consumption, fresh, chilled, frozen or dried, whether or not ground | AD39: sugarcane
A40: l9.4 | B40: Plant | C40: Plant | D40: Cash Crops | E40: CaCr | F40: Sugar Cane (Sugar) | G40: Sugar Cane | H40: SuCa | I40: Sugar | J40: Saccharum officinarum | L40: No | M40: No | N40: b27.2 | O40: b41.2 | P40: b40.2 | Q40: Saccharum officinarum | S40: 8.02 | T40: sugar cane for sugar or alcohol | U40: NA | V40: NA | W40: NA | X40: NA | Y40: wfo-0000896660 | Z40: 170113 | AA40: sugars; cane sugar, raw, in solid form, as specified in subheading note 2 to this chapter, not containing added flavouring or colouring matter | AD40: sugarcane
A41: l9.5 | B41: Plant | C41: Plant | D41: Cash Crops | E41: CaCr | F41: Sweetcane (Cane) | G41: Sweetcane | H41: SwCa | I41: Stem/Stalks | J41: Saccharum arundinaceum | L41: No | M41: No | N41: b27.2 | O41: b41.2 | P41: b40.2 | Q41: Saccharum officinarum | R41: Substituting Saccharum officinarum as ecocrop match for this species | S41: no match | T41: no match | U41: NA | V41: NA | W41: NA | X41: NA | Y41: wfo-0000896536 | Z41: no match
A42: l9.6 | B42: Plant | C42: Plant | D42: Cash Crops | E42: CaCr | F42: Sweetcane (Sugar) | G42: Sweetcane | H42: SwCa | I42: Sugar | J42: Saccharum arundinaceum | L42: No | M42: No | N42: b27.2 | O42: b41.2 | P42: b40.2 | Q42: Saccharum officinarum | R42: Substituting Saccharum officinarum as ecocrop match for this species | S42: no match | T42: no match | U42: NA | V42: NA | W42: NA | X42: NA | Y42: wfo-0000896536 | Z42: no match
A43: l11 | B43: Plant | C43: Plant | D43: Cash Crops | E43: CaCr | F43: Tea | G43: Tea | H43: Tea | I43: Leaf | J43: Camellia sinensis | L43: No | M43: Yes | N43: a17.1 | O43: a17.2 | P43: a17 | Q43: Camellia sp. | R43: Camellia sinensis + Camellia sinensis var. assamica + Camellia sinensis var. sinensis + | S43: 6.01.02 | T43: tea | U43: NA | V43: NA | W43: NA | X43: NA | Y43: wfo-0000582676 | Z43: 902 | AA43: tea | AD43: tea
A44: l12 | B44: Plant | C44: Plant | D44: Cash Crops | E44: CaCr | F44: Tobacco | G44: Tobacco | H44: Tob | I44: Leaf | J44: Nicotiana sp | L44: No | M44: No | N44: b27.2 | O44: b41.2 | P44: b40.2 | Q44: Nicotiana sp. | S44: 9.06 | T44: tobacco | U44: NA | V44: NA | W44: NA | X44: NA | Y44: wfo-4000026097 | Z44: 240110 | AA44: tobacco, (not stemmed or stripped) | AD44: tobacco
A45: l23 | B45: Plant | C45: Plant | D45: Cash Crops | E45: CaCr | F45: Tree cassava | G45: Tree cassava | H45: TrCa | I45: Tuber/Root/Bulb | J45: Manihot glaziovii | L45: No | M45: Yes | N45: a17.1 | O45: a17.2 | P45: a17 | U45: NA | V45: NA | W45: NA | X45: NA | Y45: wfo-0000235456
A46: l7 | B46: Plant | C46: Plant | D46: Cash Crops | E46: CaCr | F46: Yerba Mate | G46: Yerba Mate | H46: Yer | I46: Leaf | J46: Ilex paraguariensis | L46: No | M46: Yes | N46: a17.1 | O46: a17.2 | P46: a17 | Q46: Ilex paraguariensis | S46: 6.01.03 | T46: yerba mate | U46: NA | V46: NA | W46: NA | X46: NA | Y46: wfo-0000729719 | Z46: 90300 | AA46: mate
A47: c2 | B47: Plant | C47: Plant | D47: Cereals | E47: Ce | F47: Amaranth (Grain) | G47: Amaranth | H47: Amar | I47: Seed | J47: Amaranthus sp | L47: No | M47: No | N47: b27.2 | O47: b41.2 | P47: b40.2 | Q47: Amaranthus sp. | S47: no match | T47: no match | U47: NA | V47: NA | W47: NA | X47: NA | Y47: wfo-4000001466 | Z47: no match
A48: c3 | B48: Plant | C48: Plant | D48: Cereals | E48: Ce | F48: Barley | G48: Barley | H48: Bar | I48: Seed | J48: Hordeum vulgare | L48: No | M48: No | N48: b27.2 | O48: b41.2 | P48: b40.2 | Q48: Hordeum vulgare | S48: 1.05 | T48: barley | U48: NA | V48: NA | W48: NA | X48: NA | Y48: wfo-0000875054 | Z48: 100310 | AA48: cereals; barley, seed | AD48: barley
A49: c20 | B49: Plant | C49: Plant | D49: Cereals | E49: Ce | F49: Black oats | G49: Black oats | H49: BlOa | I49: Seed | J49: Avena strigosa | L49: No | M49: No | N49: b27.2 | O49: b41.2 | P49: b40.2 | Q49: Avena strigosa | U49: NA | V49: NA | W49: NA | X49: NA | Y49: wfo-0000852368 | Z49: no match | AD49: NA
A50: c4 | B50: Plant | C50: Plant | D50: Cereals | E50: Ce | F50: Buckwheat | G50: Buckwheat | H50: Buc | I50: Seed | J50: Fagopyrum esculentum | L50: No | M50: No | N50: b27.2 | O50: b41.2 | P50: b40.2 | Q50: Fagopyrum esculentum | S50: 1.1 | T50: buckwheat | U50: NA | V50: NA | W50: NA | X50: NA | Y50: wfo-0000685460 | Z50: 100810 | AA50: cereals; buckwheat
A51: c18 | B51: Plant | C51: Plant | D51: Cereals | E51: Ce | F51: Durum Wheat | G51: Durum Wheat | H51: Dur | I51: Seed | J51: Triticum durum | L51: No | M51: No | N51: b27.2 | O51: b41.2 | P51: b40.2 | Q51: Triticum durum | S51: 1.01 | T51: durum wheat | U51: NA | V51: NA | W51: NA | X51: NA | Y51: wfo-0000905945 | Z51: 100111 | AA51: cereals; wheat and meslin, durum wheat, seed
A52: c16 | B52: Plant | C52: Plant | D52: Cereals | E52: Ce | F52: Finger Millet | G52: Finger Millet | H52: FiMi | I52: Seed | J52: Eleusine coracana | L52: No | M52: No | N52: b27.2 | O52: b41.2 | P52: b40.2 | Q52: Eleusine coracana ssp. coracana | S52: 1.08 | T52: millet, finger | U52: NA | V52: NA | W52: NA | X52: NA | Y52: wfo-0000865686 | Z52: no match
A53: c6 | B53: Plant | C53: Plant | D53: Cereals | E53: Ce | F53: Fonio | G53: Fonio | H53: Fon | I53: Seed | J53: Digitaria sp | L53: No | M53: No | N53: b27.2 | O53: b41.2 | P53: b40.2 | Q53: Digitaria sp. | S53: 1.11 | T53: fonio | U53: NA | V53: NA | W53: NA | X53: NA | Y53: wfo-4000011700 | Z53: 100840 | AA53: cereals; fonio (Digitaria spp.)
A54: c7 | B54: Plant | C54: Plant | D54: Cereals | E54: Ce | F54: Maize | G54: Maize | H54: Mai | I54: Seed | J54: Zea mays | L54: No | M54: No | N54: b27.2 | O54: b41.2 | P54: b40.2 | Q54: Zea mays ssp. mays | S54: 1.02 | T54: maize, ordinary | U54: NA | V54: NA | W54: NA | X54: NA | Y54: wfo-0000907754 | Z54: 100510 | AA54: cereals; maize (corn), seed | AD54: maize
A55: c9 | B55: Plant | C55: Plant | D55: Cereals | E55: Ce | F55: Oats | G55: Oats | H55: Oat | I55: Seed | J55: Avena sativa | L55: No | M55: No | N55: b27.2 | O55: b41.2 | P55: b40.2 | Q55: Avena sativa | S55: 1.07 | T55: oats, for grain | U55: NA | V55: NA | W55: NA | X55: NA | Y55: wfo-0000852231 | Z55: 100410 | AA55: cereals; oats, seeds
A56: c8 | B56: Plant | C56: Plant | D56: Cereals | E56: Ce | F56: Millet (Other) | G56: Other Millet | H56: OtMi | I56: Seed | J56: Echinochloa sp | L56: No | M56: No | N56: b27.2 | O56: b41.2 | P56: b40.2 | Q56: Echinochloa sp. | R56: cereal crops only (Echinochloa crus-galli + Echinochloa frumentacea) | S56: 1.08 | T56: millet, japanese | U56: NA | V56: NA | W56: NA | X56: NA | Y56: wfo-4000012916 | Z56: 100821 | AA56: cereals; millet, seed
A57: c17 | B57: Plant | C57: Plant | D57: Cereals | E57: Ce | F57: Pearl Millet | G57: Pearl Millet | H57: PeMi | I57: Seed | J57: Pennisetum glaucum | L57: No | M57: No | N57: b27.2 | O57: b41.2 | P57: b40.2 | Q57: Pennisetum glaucum | S57: 1.08 | T57: millet, pearl (bajra, bulrush) | U57: NA | V57: NA | W57: NA | X57: NA | Y57: wfo-0000888897 | Z57: no match | AD57: pearl millet
A58: c10 | B58: Plant | C58: Plant | D58: Cereals | E58: Ce | F58: Quinoa | G58: Quinoa | H58: Quin | I58: Seed | J58: Chenopodium quinoa | L58: No | M58: No | N58: b27.2 | O58: b41.2 | P58: b40.2 | Q58: Chenopodium quinoa | S58: 1.12 | T58: quinoa | U58: NA | V58: NA | W58: NA | X58: NA | Y58: wfo-0000601712 | Z58: 100850 | AA58: cereals; quinoa (Chenopodium quinoa)
A59: c11 | B59: Plant | C59: Plant | D59: Cereals | E59: Ce | F59: Rice | G59: Rice | H59: Rice | I59: Seed | J59: Oryza sativa | L59: No | M59: No | N59: b27.2 | O59: b41.2 | P59: b40.2 | Q59: Oryza sativa | R59: Oryza sativa + Oryza sativa ssp. Indica + Oryza sativa ssp. javanica | S59: 1.03 | T59: rice | U59: NA | V59: NA | W59: NA | X59: NA | Y59: wfo-0000882438 | Z59: 1006 | AA59: rice | AD59: rice
A60: c12 | B60: Plant | C60: Plant | D60: Cereals | E60: Ce | F60: Rye | G60: Rye | H60: Rye | I60: Seed | J60: Secale cereale | L60: No | M60: No | N60: b27.2 | O60: b41.2 | P60: b40.2 | Q60: Secale cereale | S60: 1.06 | T60: rye | U60: NA | V60: NA | W60: NA | X60: NA | Y60: wfo-0000898524 | Z60: 100210 | AA60: cereals; rye, seed
A61: c13 | B61: Plant | C61: Plant | D61: Cereals | E61: Ce | F61: Sorghum | G61: Sorghum | H61: Sor | I61: Seed | J61: Sorghum bicolor | L61: No | M61: No | N61: b27.2 | O61: b41.2 | P61: b40.2 | Q61: Sorghum bicolor | S61: 1.04 | T61: sorghum | U61: NA | V61: NA | W61: NA | X61: NA | Y61: wfo-0000900184 | Z61: 100710 | AA61: cereals; grain sorghum, seed | AD61: sorghum
A62: c15 | B62: Plant | C62: Plant | D62: Cereals | E62: Ce | F62: Teff | G62: Teff | H62: Tef | I62: Seed | J62: Eragrostis tef | L62: No | M62: No | N62: b27.2 | O62: b41.2 | P62: b40.2 | Q62: Eragrostis tef | S62: 1.9 | T62: tef | U62: NA | V62: NA | W62: NA | X62: NA | Y62: wfo-0000868504 | Z62: no match
A63: c19 | B63: Plant | C63: Plant | D63: Cereals | E63: Ce | F63: Triticale | G63: Triticale | H63: Trit | I63: Seed | J63: × Triticosecale | L63: No | M63: No | N63: b27.2 | O63: b41.2 | P63: b40.2 | Q63: NA | R63: NA | S63: 1.09 | T63: triticale | U63: NA | V63: NA | W63: NA | X63: NA | Y63: wfo-4000039396 | Z63: 100860 | AA63: cereals; triticale
A64: c14 | B64: Plant | C64: Plant | D64: Cereals | E64: Ce | F64: Wheat | G64: Wheat | H64: Whe | I64: Seed | J64: Triticum aestivum | L64: No | M64: No | N64: b27.2 | O64: b41.2 | P64: b40.2 | Q64: Triticum aestivum | R64: Triticum aestivum | S64: 1.01 | T64: wheat | U64: NA | V64: NA | W64: NA | X64: NA | Y64: wfo-0000905667 | Z64: 100191 | AA64: cereals; wheat and meslin, other than durum wheat, seed | AD64: wheat
A65: s33 | B65: Non-product | C65: Non-product | D65: Cover Crop | E65: CoCr | F65: Arachis pintoi | G65: Arachis pintoi | H65: ArPi | I65: Biomass | J65: Arachis pintoi | L65: Yes | M65: No | N65: b27.1 | O65: b41.1 | P65: b40.1 | U65: NA | V65: NA | W65: NA | X65: NA | Y65: wfo-0000193779
A66: s38 | B66: Non-product | C66: Non-product | D66: Cover Crop | E66: CoCr | F66: Jack Bean | G66: Jack Bean | H66: JaBe | I66: Biomass | J66: Canavalia ensiformis | L66: Yes | M66: No | N66: b27.1 | O66: b41.1 | P66: b40.1 | Q66: Canavalia ensiformis | S66: no match | T66: no match | U66: NA | V66: NA | W66: NA | X66: NA | Y66: wfo-0000189815 | Z66: no match
A67: s40 | B67: Non-product | C67: Non-product | D67: Cover Crop | E67: CoCr | F67: Calopogonium mucunoides | G67: Calopogonium mucunoides | H67: CaMu | I67: Biomass | J67: Calopogonium mucunoides | L67: Yes | M67: No | N67: b27.1 | O67: b41.1 | P67: b40.1 | U67: NA | V67: NA | W67: NA | X67: NA | Y67: wfo-0000179119
A68: s26 | B68: Non-product | C68: Non-product | D68: Cover Crop | E68: CoCr | F68: Centrosema pubescens | G68: Centrosema pubescens | H68: CePu | I68: Biomass | J68: Centrosema pubescens | L68: Yes | M68: No | N68: b27.1 | O68: b41.1 | P68: b40.1 | Q68: Centrosema pubescens | S68: no match | T68: no match | U68: NA | V68: NA | W68: NA | X68: NA | Y68: wfo-0000179155 | Z68: no match
A69: s18 | B69: Non-product | C69: Non-product | D69: Cover Crop | E69: CoCr | F69: Cleretum bellidiforme | G69: Cleretum bellidiforme | H69: ClBe | I69: Biomass | J69: Cleretum bellidiforme | L69: No | M69: No | N69: b27.2 | O69: b41.2 | P69: b40.2 | S69: no match | T69: no match | U69: NA | V69: NA | W69: NA | X69: NA | Y69: wfo-0000611732 | Z69: no match
A70: s25 | B70: Non-product | C70: Non-product | D70: Cover Crop | E70: CoCr | F70: Clitoria ternatea | G70: Clitoria ternatea | H70: ClTe | I70: Biomass | J70: Clitoria ternatea | L70: Yes | M70: No | N70: b27.1 | O70: b41.1 | P70: b40.1 | Q70: Clitoria ternatea | S70: no match | T70: no match | U70: NA | V70: NA | W70: NA | X70: NA | Y70: wfo-0000179216 | Z70: no match
A71: s39 | B71: Non-product | C71: Non-product | D71: Cover Crop | E71: CoCr | F71: Common Vetch | G71: Common Vetch | H71: CoVe | I71: Biomass | J71: Vicia sativa | L71: Yes | M71: No | N71: b27.1 | O71: b41.1 | P71: b40.1 | S71: no match | T71: no match | U71: NA | V71: NA | W71: NA | X71: NA | Y71: wfo-0000212779
A72: s37 | B72: Non-product | C72: Non-product | D72: Cover Crop | E72: CoCr | F72: Crotalaria juncea | G72: Crotalaria juncea | H72: CrJu | I72: Biomass | J72: Crotalaria juncea | L72: Yes | M72: No | N72: b27.1 | O72: b41.1 | P72: b40.1 | S72: no match | T72: no match | U72: NA | V72: NA | W72: NA | X72: NA | Y72: wfo-0000210925 | Z72: no match
A73: s36 | B73: Non-product | C73: Non-product | D73: Cover Crop | E73: CoCr | F73: Crotalaria ochroleuca | G73: Crotalaria ochroleuca | H73: CrOc | I73: Biomass | J73: Crotalaria ochroleuca | L73: Yes | M73: No | N73: b27.1 | O73: b41.1 | P73: b40.1 | Q73: Crotalaria averaged | S73: no match | T73: no match | U73: NA | V73: NA | W73: NA | X73: NA | Y73: wfo-0000209242 | Z73: no match
A74: s24 | B74: Non-product | C74: Non-product | D74: Cover Crop | E74: CoCr | F74: Crotalaria retusa | G74: Crotalaria retusa | H74: CrRe | I74: Biomass | J74: Crotalaria retusa | L74: Yes | M74: No | N74: b27.1 | O74: b41.1 | P74: b40.1 | Q74: Crotalaria averaged | S74: no match | T74: no match | U74: NA | V74: NA | W74: NA | X74: NA | Y74: wfo-0000210930 | Z74: no match
A75: s30 | B75: Non-product | C75: Non-product | D75: Cover Crop | E75: CoCr | F75: Crotalaria spectabilis | G75: Crotalaria spectabilis | H75: CrSp | I75: Biomass | J75: Crotalaria spectabilis | L75: Yes | M75: No | N75: b27.1 | O75: b41.1 | P75: b40.1 | Q75: Crotalaria spectabilis | S75: no match | T75: no match | U75: NA | V75: NA | W75: NA | X75: NA | Y75: wfo-0000210927 | Z75: no match
A76: s28 | B76: Non-product | C76: Non-product | D76: Cover Crop | E76: CoCr | F76: Desmodium intortum | G76: Desmodium intortum | H76: DeIn | I76: Biomass | J76: Desmodium intortum | L76: Yes | M76: Yes | N76: a16.1 | O76: a16.2 | P76: a16 | Q76: Desmodium intortum | S76: no match | T76: no match | U76: NA | V76: NA | W76: NA | X76: NA | Y76: wfo-0000177239 | Z76: no match
A77: s31 | B77: Non-product | C77: Non-product | D77: Cover Crop | E77: CoCr | F77: Desmodium uncinatum | G77: Desmodium uncinatum | H77: DeUn | I77: Biomass | J77: Desmodium uncinatum | L77: Yes | M77: No | N77: b27.1 | O77: b41.1 | P77: b40.1 | S77: no match | T77: no match | U77: NA | V77: NA | W77: NA | X77: NA | Y77: wfo-0000177239 | Z77: no match
A78: s6 | B78: Non-product | C78: Non-product | D78: Cover Crop | E78: CoCr | F78: Dimorphotheca pluvialis | G78: Dimorphotheca pluvialis | H78: DiPl | I78: Biomass | J78: Dimorphotheca pluvialis | L78: No | M78: No | N78: b27.2 | O78: b41.2 | P78: b40.2 | S78: no match | T78: no match | U78: NA | V78: NA | W78: NA | X78: NA | Y78: wfo-0000127997 | Z78: no match
A79: s22 | B79: Non-product | C79: Non-product | D79: Cover Crop | E79: CoCr | F79: Drosanthemum floribundum | G79: Drosanthemum floribundum | H79: DrFl | I79: Biomass | J79: Drosanthemum floribundum | L79: No | M79: No | N79: b27.2 | O79: b41.2 | P79: b40.2 | S79: no match | T79: no match | U79: NA | V79: NA | W79: NA | X79: NA | Y79: wfo-0000656906 | Z79: no match
A80: s21 | B80: Non-product | C80: Non-product | D80: Cover Crop | E80: CoCr | F80: Drosanthemum speciosum | G80: Drosanthemum speciosum | H80: DrSp | I80: Biomass | J80: Drosanthemum speciosum | L80: No | M80: No | N80: b27.2 | O80: b41.2 | P80: b40.2 | S80: no match | T80: no match | U80: NA | V80: NA | W80: NA | X80: NA | Y80: wfo-0000656980 | Z80: no match
A81: s20 | B81: Non-product | C81: Non-product | D81: Cover Crop | E81: CoCr | F81: Drosanthemum striatum | G81: Drosanthemum striatum | H81: DrSt | I81: Biomass | J81: Drosanthemum striatum | L81: No | M81: No | N81: b27.2 | O81: b41.2 | P81: b40.2 | S81: no match | T81: no match | U81: NA | V81: NA | W81: NA | X81: NA | Y81: wfo-0000656984 | Z81: no match
A82: s5 | B82: Non-product | C82: Non-product | D82: Cover Crop | E82: CoCr | F82: Felicia heterophylla | G82: Felicia heterophylla | H82: FeHe | I82: Biomass | J82: Felicia heterophylla | L82: No | M82: No | N82: b27.2 | O82: b41.2 | P82: b40.2 | S82: no match | T82: no match | U82: NA | V82: NA | W82: NA | X82: NA | Y82: wfo-0000088691 | Z82: no match
A83: s12 | B83: Non-product | C83: Non-product | D83: Cover Crop | E83: CoCr | F83: Gazania krebsiana | G83: Gazania krebsiana | H83: GaKr | I83: Biomass | J83: Gazania krebsiana | L83: No | M83: No | N83: b27.2 | O83: b41.2 | P83: b40.2 | S83: no match | T83: no match | U83: NA | V83: NA | W83: NA | X83: NA | Y83: wfo-0000040495 | Z83: no match
A84: s8 | B84: Non-product | C84: Non-product | D84: Cover Crop | E84: CoCr | F84: Geranium incanum | G84: Geranium incanum | H84: GeIn | I84: Biomass | J84: Geranium incanum | L84: No | M84: No | N84: b27.2 | O84: b41.2 | P84: b40.2 | S84: no match | T84: no match | U84: NA | V84: NA | W84: NA | X84: NA | Y84: wfo-0000700650 | Z84: no match
A85: s10 | B85: Non-product | C85: Non-product | D85: Cover Crop | E85: CoCr | F85: Helichrysum petiolare | G85: Helichrysum petiolare | H85: HePe | I85: Biomass | J85: Helichrysum petiolare | L85: No | M85: No | N85: b27.2 | O85: b41.2 | P85: b40.2 | S85: no match | T85: no match | U85: NA | V85: NA | W85: NA | X85: NA | Y85: wfo-0000024510 | Z85: no match
A86: s14 | B86: Non-product | C86: Non-product | D86: Cover Crop | E86: CoCr | F86: Heliophila coronopifolia | G86: Heliophyla coronopifolia | H86: HeCr | I86: Biomass | J86: Heliophyla coronopifolia | L86: No | M86: No | N86: b27.2 | O86: b41.2 | P86: b40.2 | S86: no match | T86: no match | U86: NA | V86: NA | W86: NA | X86: NA | Y86: no match | Z86: no match
A87: s9 | B87: Non-product | C87: Non-product | D87: Cover Crop | E87: CoCr | F87: Hermannia pinnata | G87: Hermannia pinnata | H87: HePi | I87: Biomass | J87: Hermannia pinnata | L87: No | M87: No | N87: b27.2 | O87: b41.2 | P87: b40.2 | S87: no match | T87: no match | U87: NA | V87: NA | W87: NA | X87: NA | Y87: wfo-0001141024 | Z87: no match
A88: s32 | B88: Non-product | C88: Non-product | D88: Cover Crop | E88: CoCr | F88: Hyptis spicigera | G88: Hyptis spicigera | H88: HySp | I88: Biomass | J88: Hyptis spicigera | L88: No | M88: No | N88: b27.2 | O88: b41.2 | P88: b40.2 | U88: NA | V88: NA | W88: NA | X88: NA | Y88: wfo-0000217082
A89: s19 | B89: Non-product | C89: Non-product | D89: Cover Crop | E89: CoCr | F89: Lampranthus multiradiatus | G89: Lampranthus multiradiatus | H89: LaMu | I89: Biomass | J89: Lampranthus multiradiatus | L89: No | M89: No | N89: b27.2 | O89: b41.2 | P89: b40.2 | S89: no match | T89: no match | U89: NA | V89: NA | W89: NA | X89: NA | Y89: wfo-0000361350 | Z89: no match
A90: s15 | B90: Non-product | C90: Non-product | D90: Cover Crop | E90: CoCr | F90: Lessertia frutescens | G90: Lessertia frutescens | H90: LeFr | I90: Biomass | J90: Lessertia frutescens | L90: Yes | M90: No | N90: b27.1 | O90: b41.1 | P90: b40.1 | S90: no match | T90: no match | U90: NA | V90: NA | W90: NA | X90: NA | Y90: wfo-0001274560 | Z90: no match
A91: s34 | B91: Non-product | C91: Non-product | D91: Cover Crop | E91: CoCr | F91: Medicago scutellata | G91: Medicago scutellata | H91: MeSc | I91: Biomass | J91: Medicago scutellata | L91: Yes | M91: No | N91: b27.1 | O91: b41.1 | P91: b40.1 | S91: no match | T91: no match | U91: NA | V91: NA | W91: NA | X91: NA | Y91: wfo-1200009388 | Z91: no match
A92: s4 | B92: Non-product | C92: Non-product | D92: Cover Crop | E92: CoCr | F92: Medicago truncatula | G92: Medicago truncatula | H92: MeTr | I92: Biomass | J92: Medicago truncatula | L92: Yes | M92: No | N92: b27.1 | O92: b41.1 | P92: b40.1 | Q92: Medicago truncatula | S92: no match | T92: no match | U92: NA | V92: NA | W92: NA | X92: NA | Y92: wfo-0000213477 | Z92: no match
A93: s27 | B93: Non-product | C93: Non-product | D93: Cover Crop | E93: CoCr | F93: Mimosa invisa | G93: Mimosa invisa | H93: MiIn | I93: Biomass | J93: Mimosa invisa | L93: Yes | M93: Yes | N93: a16.1 | O93: a16.2 | P93: a16 | Q93: NA | S93: no match | T93: no match | U93: NA | V93: NA | W93: NA | X93: NA | Y93: wfo-0000164675 | Z93: no match
A94: s17 | B94: Non-product | C94: Non-product | D94: Cover Crop | E94: CoCr | F94: Monopsis lutea | G94: Monopsis lutea | H94: MoLu | I94: Biomass | J94: Monopsis lutea | L94: No | M94: No | N94: b27.2 | O94: b41.2 | P94: b40.2 | S94: no match | T94: no match | U94: NA | V94: NA | W94: NA | X94: NA | Y94: wfo-0000816624 | Z94: no match
A95: s3 | B95: Non-product | C95: Non-product | D95: Cover Crop | E95: CoCr | F95: Ornithopus sativus | G95: Ornithopus sativus | H95: OrSa | I95: Biomass | J95: Ornithopus sativus | L95: No | M95: No | N95: b27.2 | O95: b41.2 | P95: b40.2 | Q95: Ornithopus sativus | S95: no match | T95: no match | U95: NA | V95: NA | W95: NA | X95: NA | Y95: wfo-0000205829 | Z95: no match
A96: s11 | B96: Non-product | C96: Non-product | D96: Cover Crop | E96: CoCr | F96: Pelargonium capitatum | G96: Pelargonium capitatum | H96: PeCa | I96: Biomass | J96: Pelargonium capitatum | L96: No | M96: No | N96: b27.2 | O96: b41.2 | P96: b40.2 | S96: no match | T96: no match | U96: NA | V96: NA | W96: NA | X96: NA | Y96: wfo-0001064058 | Z96: no match
A97: s16 | B97: Non-product | C97: Non-product | D97: Cover Crop | E97: CoCr | F97: Roella ciliata | G97: Roella ciliata | H97: RoCi | I97: Biomass | J97: Roella ciliata | L97: No | M97: No | N97: b27.2 | O97: b41.2 | P97: b40.2 | S97: no match | T97: no match | U97: NA | V97: NA | W97: NA | X97: NA | Y97: wfo-0000818110 | Z97: no match
A98: s7 | B98: Non-product | C98: Non-product | D98: Cover Crop | E98: CoCr | F98: Senecio elegans | G98: Senecio elegans | H98: SeEl | I98: Biomass | J98: Senecio elegans | L98: No | M98: No | N98: b27.2 | O98: b41.2 | P98: b40.2 | S98: no match | T98: no match | U98: NA | V98: NA | W98: NA | X98: NA | Y98: wfo-0000074874 | Z98: no match
A99: s13 | B99: Non-product | C99: Non-product | D99: Cover Crop | E99: CoCr | F99: Steirodiscus tagetes | G99: Steirodiscus tagetes | H99: StTa | I99: Biomass | J99: Steirodiscus tagetes | L99: No | M99: No | N99: b27.2 | O99: b41.2 | P99: b40.2 | S99: no match | T99: no match | U99: NA | V99: NA | W99: NA | X99: NA | Y99: wfo-0000063658 | Z99: no match
A100: s29 | B100: Non-product | C100: Non-product | D100: Cover Crop | E100: CoCr | F100: Tithonia diversifolia | G100: Tithonia diversifolia | H100: TiDe | I100: Biomass | J100: Tithonia diversifolia | L100: No | M100: Yes | N100: a17.1 | O100: a17.2 | P100: a17 | Q100: Tithonia diversifolia | S100: no match | T100: no match | U100: NA | V100: NA | W100: NA | X100: NA | Y100: wfo-0000018279 | Z100: no match
...

Sheet lookup_levels
A1: Table | B1: Field | C1: Values_Old | D1: Values_New | E1: Description | F1: GPT_Description_Checked | G1: Translation_Source | H1: Value_Spanish | I1: Description_Spanish | J1: Ref_Source | K1: Ref_Name | L1: Ref_Link | M1: Ref_Match | N1: Ref_Notes | O1: Ref2_DataScribe | P1: Ref2_Source | Q1: Ref2_Name | R1: Ref2_Link | S1: Ref2_Match | T1: Ref2_Notes | U1: Other_Links
A2: AF.Out | B2: AF.Unit | D2: % shade
A3: AF.Out | B3: AF.Unit | D3: trees/ha
A4: AF.Out | B4: AF.Unit | D4: trees/m2
A5: AF.Out | B5: AF.Unit | D5: trees/acre
A6: Chems.Out | B6: C.AI.Unit | C6: % | D6: % | E6: Percentage | F6: Yes
A7: Chems.Out | B7: C.AI.Unit | C7: g/kg | D7: g/kg | E7: Grams per kilogram. | F7: Yes
A8: Chems.Out | B8: C.AI.Unit | D8: g/100ml
A9: Chems.Out | B9: C.AI.Unit | C9: mg/kg | D9: mg/kg | E9: Miligrams per kilogram. | F9: Yes
A10: Chems.Out | B10: C.AI.Unit | D10: mg/ml
A11: Chems.Out | B11: C.AI.Unit | D11: g/l
A12: Chems.Out | B12: C.AI.Unit | C12: mg/l | D12: mg/l | E12: Miligrams per liter. | F12: Yes
A13: Chems.Out | B13: C.AI.Unit | C13: ml/l | D13: ml/l | E13: Mililiter per liter. | F13: Yes
A14: Chems.Out | B14: C.AI.Unit | D14: ppm
A15: Chems.Out | B15: C.AI.Unit | C15: EC | D15: EC | E15: Emulsifiable concentrate | F15: Yes
A16: Chems.Out | B16: C.AI.Unit | C16: WP | D16: WP | E16: Wettable powder | F16: Yes
A17: Chems.Out | B17: C.AI.Unit | C17: SL | D17: SL | E17: Soluble (liquid) concentrate | F17: Yes
A18: Chems.Out | B18: C.AI.Unit | C18: SP | D18: SP | E18: Soluble powder | F18: Yes
A19: Chems.Out | B19: C.AI.Unit | C19: SC | D19: SC | E19: Suspension concentrate | F19: Yes
A20: Chems.Out | B20: C.AI.Unit | C20: CS | D20: CS | E20: Capsule suspension | F20: Yes
A21: Chems.Out | B21: C.AI.Unit | C21: WG | D21: WG | E21: Water dispersible granule | F21: Yes
A22: Chems.Out | B22: C.AI.Unit | C22: GR | D22: GR | E22: Granules | F22: Yes
A23: Chems.Out | B23: C.App.Method | D23: Spraying | E23: Application of liquid agro-chemicals as fine droplets using various types of sprayers. | F23: No
A24: Chems.Out | B24: C.App.Method | D24: Dusting | E24: Dispensing dry agro-chemical particles in powder or dust form over the target area. | F24: No
A25: Chems.Out | B25: C.App.Method | D25: Fogging | E25: Creating a mist or fog of agro-chemical droplets using specialized fogging machines. | F25: No
A26: Chems.Out | B26: C.App.Method | D26: Aerial Application | E26: Application of agro-chemicals from aircraft, typically used for large agricultural fields. | F26: No
A27: Chems.Out | B27: C.App.Method | D27: Seed Treatment | E27: Coating seeds with agro-chemical formulations before planting to protect crops from pests. | F27: No
A28: Chems.Out | B28: C.App.Method | D28: Soil Incorporation | E28: Mixing agro-chemicals into the soil before planting or after crop emergence. | F28: No
A29: Chems.Out | B29: C.App.Method | D29: Baiting | E29: Placing agro-chemical-laced baits or traps in areas frequented by pests. | F29: No
A30: Chems.Out | B30: C.App.Method | D30: Trunk Injection | E30: Direct injection of agro-chemicals into tree trunks to combat tree pests or diseases. | F30: No
A31: Chems.Out | B31: C.App.Method | D31: Chemigation | E31: Application of agro-chemicals through irrigation systems for precise distribution. | F31: No
A32: Chems.Out | B32: C.App.Method | D32: Paint-On Application | E32: Applying agro-chemicals directly to plant surfaces or structures using brushes or rollers. | F32: No
A33: Chems.Out | B33: C.App.Method | D33: Drenching | E33: Pouring or soaking soil around plants with a agro-chemical solution to target root pests. | F33: No
A34: Chems.Out | B34: C.App.Method | D34: Dipping | E34: Application of chemicals to livestock by immersing the animal in a solution
A35: Chems.Out | B35: C.App.Method | D35: Spot Treatment | E35: Applying agro-chemicals to specific areas or individual plants, minimizing use. | F35: No
A36: Chems.Out | B36: C.App.Method | D36: Misting | E36: Creating a fine mist of agro-chemical droplets in enclosed spaces using misting equipment. | F36: No
A37: Chems.Out | B37: C.App.Method | D37: Injected | E37: Animals were injected with a medicine/vaccine | F37: No
A38: Chems.Out | B38: C.App.Method | D38: Oral | E38: Administering chemicals to livestock through the mouth
A39: Chems.Out | B39: C.App.Method | D39: Unspecified | E39: Method of agro-chemical application is unknown. | F39: No
A40: Chems.Out | B40: C.Unit | C40: % of Diet | D40: % Diet
A41: Chems.Out | B41: C.Unit | C41: kg/ha | D41: kg/ha | E41: Kilograms per hectare. | F41: Yes
A42: Chems.Out | B42: C.Unit | C42: l/ha | D42: l/ha | E42: Liters per hectare. | F42: Yes
A43: Chems.Out | B43: C.Unit | C43: g/ha | D43: g/ha | E43: Grams per hectare. | F43: Yes
A44: Chems.Out | B44: C.Unit | C44: ml/ha | D44: ml/ha | E44: Mililiter per hectare. | F44: Yes
A45: Chems.Out | B45: C.Unit | D45: ml/kg seed | E45: Mililiter per Kilogram seed | F45: Not GPT
A46: Chems.Out | B46: C.Unit | D46: ml/100 kg seed | E46: Mililiter per 100kg Seed | F46: Not GPT
A47: Chems.Out | B47: C.Unit | D47: ml/1000 kg seed | E47: Mililiter per 1000kg Seed | F47: Not GPT
A48: Chems.Out | B48: C.Unit | C48: mL | D48: ml
A49: Chems.Out | B49: C.Unit | D49: ml/individual
A50: Chems.Out | B50: C.Unit | C50: ml/10 kg BW;mL/10kg BW;ml/10 kg body weight;ml/10 kg LW;ml/10kg LW;mL/10 kg BW | D50: ml/10kg body weight
A51: Chems.Out | B51: C.Unit | C51: ml/50 kg BW;ml/50kg BW | D51: ml/50kg body weight
A52: Chems.Out | B52: C.Unit | C52: mL/L | D52: ml/l
A53: Chems.Out | B53: C.Unit | C53: ml/25 l water | D53: ml/25l
A54: Chems.Out | B54: C.Unit | C54: g/l water;g/L | D54: g/l | E54: Grams per liter. | F54: Yes
A55: Chems.Out | B55: C.Unit | C55: g/kg | D55: g/kg | E55: Grams per kilogram. | F55: Yes
A56: Chems.Out | B56: C.Unit | D56: g/100 kg seed | E56: Grams per 100kg Seed | F56: Not GPT
A57: Chems.Out | B57: C.Unit | D57: mg/individual
A58: Chems.Out | B58: C.Unit | C58: mg/kg live weight;mg/kg LW;mg/kg BW;mg/kg of BW | D58: mg/kg body weight
A59: Chems.Out | B59: C.Unit | D59: g/kg diet
A60: Chems.Out | B60: C.Unit | D60: mg/g diet
A61: Chems.Out | B61: C.Unit | D61: mg/kg diet
A62: Chems.Out | B62: C.Unit | C62: mg/kg | D62: mg/kg | E62: Miligrams per kilogram. | F62: Yes
A63: Chems.Out | B63: C.Unit | D63: mg/seed | E63: Miligrams per seed. | F63: Not GPT
A64: Chems.Out | B64: C.Unit | C64: mg/g | D64: mg/g | E64: Miligrams per gram. | F64: Yes
A65: Data.Out | B65: Error.Type | C65: SE (Standard Error) | D65: SE (Standard Error) | E65: This is a measure of the precision of the sample mean estimate. | F65: Yes
A66: Data.Out | B66: Error.Type | C66: SEM (Standard Error) | D66: SEM (Standard Error of Mean) | E66: This is the standard error of the mean.
A67: Data.Out | B67: Error.Type | C67: SD (Standard Deviation) | D67: SD (Standard Deviation) | E67: This is a measure of the amount of variation or dispersion in a set of data. | F67: Yes
A68: Data.Out | B68: Error.Type | C68: CV (Co-efficient of Variation) | D68: CV (Co-efficient of Variation) | E68: This is a measure of relative variability in the sample or population. | F68: Yes
A69: Data.Out | B69: Error.Type | D69: Grouped SE (Standard Error) | E69: This is the standard error computed from grouped data. | F69: Yes
A70: Data.Out | B70: Error.Type | D70: Grouped SEM (Standard Error of Mean) | E70: This is the standard error of the mean that is computed from grouped data. | F70: Yes
A71: Data.Out | B71: Error.Type | D71: Grouped SD (Standard Deviation) | E71: This is the standard deviation that is computed from grouped data. | F71: Yes
A72: Data.Out | B72: Error.Type | D72: Grouped SED (Standard Error of Difference Between Means) | E72: This is the standard error of the difference between means that is computed from grouped data. | F72: Yes
A73: Fert.Method | B73: F.Method | C73: Banding (Double) | D73: Banding (Double) | E73: A method of fertilizer application where two narrow bands are created on opposite sides of the plant row. | F73: Yes
A74: Fert.Method | B74: F.Method | D74: Added to Planting Hole | E74: Fertilizer is added to a planting hole, often associated with planting of tree crops. | F74: Not GPT
A75: Fert.Method | B75: F.Method | C75: Banding (Side) | D75: Banding (Side) | E75: A method of fertilizer application where fertilizer bands are placed on one side of the plant row. | F75: Yes
A76: Fert.Method | B76: F.Method | C76: Banding (Single) | D76: Banding (Single) | E76: A method of fertilizer application where a narrow band is created alongside the plant row. | F76: Yes
A77: Fert.Method | B77: F.Method | C77: Basal | D77: Basal | E77: A method of fertilizer application where fertilizer is applied at the bottom of the planting hole. | F77: Yes
A78: Fert.Method | B78: F.Method | C78: Base Dressing | D78: Base Dressing | E78: A method of fertilizer application where fertilizer is broadcast and incorporated into the soil prior to planting. | F78: Yes
A79: Fert.Method | B79: F.Method | C79: Broadcast | D79: Broadcast | E79: A method of uniformly spreading dry fertilizer over soil surface either by hand or mechanically, using a broadcaster. | F79: Yes
A80: Fert.Method | B80: F.Method | C80: Dollop | D80: Dollop | E80: A controlled amount of liquid or dry fertilizer manually placed around a plant's base. | F80: Yes
A81: Fert.Method | B81: F.Method | C81: Drill | D81: Drill | E81: A method of placing dry fertilizer below the soil surface, usually alongside the seed, with specialized equipment. | F81: Yes
A82: Fert.Method | B82: F.Method | C82: Fertigation (Irrigation Water) | D82: Fertigation (Irrigation Water) | E82: A technique of delivering liquid fertilizer through irrigation water. | F82: Yes
A83: Fert.Method | B83: F.Method | C83: Foliar | D83: Foliar | E83: A method of fertilizer application where nutrients are sprayed onto the leaves of plants. | F83: Yes
A84: Fert.Method | B84: F.Method | C84: Liquid Injection | D84: Liquid Injection | E84: The technique of injecting liquid fertilizer directly into the soil near the roots of plants. | F84: Yes
A85: Fert.Method | B85: F.Method | C85: Microdosing | D85: Microdosing | E85: The process of providing small, precise amounts of fertilizer to plants at specific intervals throughout the growing cycle. | F85: Yes
A86: Fert.Method | B86: F.Method | C86: Plough Furrow (Single Band Placement) | D86: Plough Furrow (Single Band Placement) | E86: A method of fertilizer application where a furrow is dug in the soil using a plough, and the fertilizer is placed only in that furrow in a band. | F86: Yes
... A91: Fert.Method | B91: F.Method | C91: Gaseous Injection | D91: Gaseous Injection | E91: Fertilizer is injected into the soil as a gas. | F91: Yes
A92: Fert.Method | B92: F.Method | D92: Top Dressing
A93: Fert.Method | B93: F.Method | D93: Surface Dressing
A94: Fert.Method | B94: F.Method | D94: Side Dressing
A95: Fert.Method | B95: F.Method | D95: Banding (Surface)
A96: Fert.Method | B96: F.Physical | C96: Briquette | D96: Briquette | E96: A slow-releasing fertilizer compressed into a solid block and placed below the soil surface. | F96: Yes
A97: Fert.Method | B97: F.Physical | C97: Pellet | D97: Pelleted | E97: Fertilizer is compressed and shaped into pellets that are scattered across the soil surface or placed beneath it. | F97: Yes
A98: Fert.Method | B98: F.Physical | D98: Prilled | E98: Prilled fertilizer is formed into small, round pellets. | F98: Yes
A99: Fert.Method | B99: F.Physical | D99: Supergranulated | E99: Supergranulated fertilizer is a type of fertilizer that has been processed to form large granules. These granules are typically 2-4 mm in diameter and are designed to release nutrients slowly over time. Supergranulated fertilizers can be made from a variety of different nutrient sources, including nitrogen, phosphorus, and potassium. | F99: Yes
A100: Fert.Method | B100: F.Physical | D100: Humic Acid Coated | E100: Humic acid coating is a process of applying a layer of humic acid to fertilizer granules. | F100: Yes
A101: Fert.Method | B101: F.Physical | D101: Polymer Coated | E101: Polymer-coated fertilizers are designed to control the release of nutrients, such as nitrogen, over an extended period. This type of coating can serve multiple purposes, one of which is to minimize nutrient losses and emissions, particularly in the form of ammonia, which can occur when certain fertilizers, like urea, are applied to soil | F101: Yes
A102: Fert.Method | B102: M.Source | C102: In-field | D102: In-field | E102: From inside the experimental field. | F102: Not GPT
A103: Fert.Method | B103: M.Source | C103: Off-farm (collected) | D103: Off-farm (collected) | E103: Collected from outside the experimental field,farm or landholding, did not require purchasing. | F103: Not GPT
A104: Fert.Method | B104: M.Source | C104: Off-farm (purchased) | D104: Off-farm (purchased) | E104: Collected from outside the experimental field,farm or landholding, required purchasing. | F104: Not GPT
...

Sheet prod_comp
A1: Component | B1: Comp.Level1 | C1: Comp.Level2 | D1: Comp.Level3
A2: Baby corn | B2: Baby corn | C2: Baby corn
A3: Bark | B3: Bark | C3: Bark
A4: Biomass/Fodder | B4: Biomass | C4: Biomass/Fodder
A5: Biomass/Fodder - Above + Below Ground | B5: Biomass | C5: Biomass/Fodder | D5: Above+Below Ground
A6: Biomass/Fodder - Above Ground | B6: Biomass | C6: Biomass/Fodder | D6: Above Ground
A7: Biomass/Fodder - Below Ground | B7: Biomass | C7: Biomass/Fodder | D7: Below Ground
A8: Biomass/Fodder - Branches | B8: Biomass | C8: Biomass/Fodder | D8: Branches
A9: Biomass/Fodder - Leaf Litter | B9: Biomass | C9: Biomass/Fodder | D9: Leaf Litter
A10: Biomass/Fodder - Leaves | B10: Biomass | C10: Biomass/Fodder | D10: Leaves
A11: Biomass/Fodder - Leaves + Stalks/Branches | B11: Biomass | C11: Biomass/Fodder | D11: Leaves+Stalks/Branches
A12: Biomass/Fodder - Stalks | B12: Biomass | C12: Biomass/Fodder | D12: Stalks
A13: Biomass/Fodder - Stalks/Branches | B13: Biomass | C13: Biomass/Fodder | D13: Stalks/Branches
A14: Biomass/Fodder - Stover | B14: Biomass | C14: Biomass/Fodder | D14: Stover
A15: Biomass/Fodder - Straw | B15: Biomass | C15: Biomass/Fodder | D15: Straw
A16: Bulb | B16: Tuber/Root/Bulb | C16: Bulb
A17: Bulb (Marketable Yield) | B17: Tuber/Root/Bulb | C17: Bulb | D17: Marketable Yield
A18: Bulb (Non-Marketable Yield) | B18: Tuber/Root/Bulb | C18: Bulb | D18: Non-Marketable Yield
A19: Bulb (Total Yield) | B19: Tuber/Root/Bulb | C19: Bulb | D19: Total Yield
A20: Bulb (Unspecified) | B20: Tuber/Root/Bulb | C20: Bulb | D20: Unspecified
A21: Cane | B21: Stem | C21: Stem
A22: Charcoal | B22: Charcoal | C22: Charcoal
A23: Corm (Marketable Yield) | B23: Tuber/Root/Bulb | C23: Corm | D23: Marketable Yield
A24: Corm (Non-Marketable Yield) | B24: Tuber/Root/Bulb | C24: Corm | D24: Non-Marketable Yield
A25: Corm (Total Yield) | B25: Tuber/Root/Bulb | C25: Corm | D25: Total Yield
A26: Corm (Unspecified) | B26: Tuber/Root/Bulb | C26: Corm | D26: Unspecified
A27: Cormel (Marketable Yield) | B27: Tuber/Root/Bulb | C27: Cormel | D27: Marketable Yield
A28: Cormel (Non-Marketable Yield) | B28: Tuber/Root/Bulb | C28: Cormel | D28: Non-Marketable Yield
A29: Cormel (Total Yield) | B29: Tuber/Root/Bulb | C29: Cormel | D29: Total Yield
A30: Cormel (Unspecified) | B30: Tuber/Root/Bulb | C30: Cormel | D30: Unspecified
A31: Eggs | B31: Eggs | C31: Eggs
A32: Fibre/Lint | B32: Fibre | C32: Fibre/Lint
A33: Flowers | B33: Flower | C33: Flowers
A34: Fruit (Marketable Yield) | B34: Fruit | C34: Fruit | D34: Marketable Yield
A35: Fruit (Non-Marketable Yield) | B35: Fruit | C35: Fruit | D35: Non-Marketable Yield
A36: Fruit (Total Yield) | B36: Fruit | C36: Fruit | D36: Total Yield
A37: Fruit (Unspecified) | B37: Fruit | C37: Fruit | D37: Unspecified
A38: Grain/Seed | B38: Seed | C38: Grain/Seed
A39: Gum/Sap | B39: Sap | C39: Gum/Sap
A40: Haulm | B40: Biomass | C40: Biomass/Fodder | D40: Stalks/Branches
A41: Hide | B41: Hide | C41: Hide
A42: Honey | B42: Honey | C42: Honey
A43: Juice | B43: Juice | C43: Juice
A44: Leaves | B44: Leaf | C44: Leaves
A45: Meal/Flour | B45: Flour | C45: Meal/Flour
A46: Meat | B46: Meat | C46: Meat
A47: Meat - Carcass | B47: Meat | C47: Meat | D47: Carcass
A48: Meat - Carcass Defeathered | B48: Meat | C48: Meat | D48: Carcass Defeathered
A49: Meat - Cold Carcass | B49: Meat | C49: Meat | D49: Cold Carcass
A50: Meat - Dressed | B50: Meat | C50: Meat | D50: Dressed
A51: Meat - Empty Carcass | B51: Meat | C51: Meat | D51: Empty Carcass
A52: Meat - Eviscerated | B52: Meat | C52: Meat | D52: Eviscerated
A53: Meat - Final Body Weight | B53: Meat | C53: Meat | D53: Final Body Weight
A54: Meat - Hot Carcass | B54: Meat | C54: Meat | D54: Hot Carcass
A55: Meat - Internal Fat | B55: Meat | C55: Meat | D55: Internal Fat
A56: Meat - Non-carcass | B56: Meat | C56: Meat | D56: Non-carcass
A57: Meat - Slaughter Body | B57: Meat | C57: Meat | D57: Slaughter Body
A58: Meat - Subcutaneous Fat | B58: Meat | C58: Meat | D58: Subcutaneous Fat
A59: Milk | B59: Milk | C59: Milk
A60: Mushroom | B60: Mushroom | C60: Mushroom
A61: Nuts | B61: Seed | C61: Nuts
A62: Nuts+Shells | B62: Seed | C62: Nuts+Shells
A63: Offspring | B63: Offspring | C63: Offspring
A64: Oil | B64: Oil | C64: Oil
A65: Pods | B65: Pods | C65: Pods
A66: Rhizome | B66: Tuber/Root/Bulb
A67: Shells | B67: Seed | C67: Shells
A68: Stem/Stalks | B68: Stem/Stalks
A69: Stem | B69: Stem/Stalks | C69: Stem
A70: Stalks | B70: Stem/Stalks | C70: Stalks
A71: Stalks+Leaves | B71: Stem/Stalks | C71: Stalks+Leaves
A72: Sugar | B72: Sugar | C72: Sugar
A73: Tuber/Root | B73: Tuber/Root/Bulb | C73: Tuber/Root
A74: Tuber/Root (Marketable Yield) | B74: Tuber/Root/Bulb | C74: Tuber/Root | D74: Marketable Yield
A75: Tuber/Root (Non-Marketable Yield) | B75: Tuber/Root/Bulb | C75: Tuber/Root | D75: Non-Marketable Yield
A76: Tuber/Root (Tops) | B76: Tuber/Root/Bulb | C76: Tuber/Root | D76: Tops
A77: Tuber/Root (Total Yield) | B77: Tuber/Root/Bulb | C77: Tuber/Root | D77: Total Yield
A78: Tuber/Root (Unspecified) | B78: Tuber/Root/Bulb | C78: Tuber/Root | D78: Unspecified
A79: Whole Plant | B79: Biomass | C79: Whole Plant
A80: Wood - Firewood | B80: Wood | C80: Wood | D80: Firewood
A81: Wood - Timber | B81: Wood | C81: Wood | D81: Timber
A82: Wool | B82: Wool | C82: Wool

Sheet out
A1: Code | B1: Pillar | C1: Pillar.Code | D1: Subpillar | E1: Subpillar.Code | F1: Indicator | G1: Indicator.Code | H1: Subindicator | I1: Subindicator.Short | J1: Subindicator.Code | K1: Definition | L1: Notes | M1: Example units | N1: Original.Outcome | O1: Negative Values | P1: Sign | Q1: TC.Ratio | R1: Not.Perc | S1: Depreciated | T1: Previous.Names
A2: 101 | B2: Productivity | C2: Productivity | D2: Yield | E2: Yi | F2: Product Yield | G2: PY | H2: Crop Yield | I2: Crop Yield | J2: CrY | K2: Amount of crop plant product produced (e.g., grain or fruit yield) per unit area land. | L2: When product and non-product components are not separated, for example measures of total, above-ground or below-ground crop biomass, the outcome sould be recorded using the Biomass Yield Outcome. Non-product component outcomes (e.g. maize stover or wheat stalks) should be recorded using the Crop Residue Yield outcome. | M2: t/ha;kg/ha | O2: N | P2: p | Q2: N | R2: Y | S2: FALSE
A3: 101.1 | B3: Productivity | C3: Productivity | D3: Yield | E3: Yi | F3: Product Yield | G3: PY | H3: Biomass Yield | I3: Biomass Yield | J3: BiY | K3: Plant biomass yield. This can be used to describe pasture biomass yields or when total, above ground, or below ground biomass yields are given for crops that are usually split into product and non-product parts on harvest. | M3: t/ha;kg/ha | O3: N | P3: p | Q3: N | R3: Y | S3: FALSE
A4: 101.2 | B4: Productivity | C4: Productivity | D4: Yield | E4: Yi | F4: Product Yield | G4: PY | H4: Extraction Yield | I4: Extraction Yield | J4: ExY | K4: Extraction yield of oil from oil seeds or similar. For example 300kg oil extracted from 1000kg oil seeds = 0.3 or 30% oil yield per kg oil seeds. | L4: This outcome should be a percentage or ratio. | M4: Unitless ratio; % | O4: N | P4: p | Q4: N | R4: N | S4: FALSE
A5: 103 | B5: Productivity | C5: Productivity | D5: Yield | E5: Yi | F5: Product Yield | G5: PY | H5: Land Equivalent Ratio | I5: LER | J5: LER | K5: The land equivalent ratio describes the relative land area required under sole cropping (monoculture) to produce the same yield as under intercropping (polyculture). | L5: We do not accept LER for practice A vs practice B (e.g. mulch vs no-mulch as this yield A/yield B, which we calculated as the response ratio). | M5: Unitless ratio | O5: N | P5: p | Q5: Y | R5: Y | S5: FALSE
A6: 104 | B6: Productivity | C6: Productivity | D6: Yield | E6: Yi | F6: Product Yield | G6: PY | H6: Area Time Equivalent Ratio | I6: ATER | J6: ATER | K6: The Area Time Equivalent Ratio (ATER) is a measure of the productivity of an intercropping system. It is calculated by dividing the total yield of the intercrop by the yield of a sole crop grown for the same duration. The ATER is calculated as follows: ATER = (Total yield of intercrop) / (Yield of sole crop grown for the same duration). The ATER is particularly useful in intercropping systems where the crops have different growth durations. For example, if a farmer intercrops a fast-growing crop with a slow-growing crop, the faster-growing crop will produce a yield before the slower-growing crop. The ATER will take into account the different growth durations of the crops and will give a more accurate measure of the overall productivity of the intercropping system. | O6: N | P6: p | Q6: Y | R6: Y | S6: FALSE
A7: 118 | B7: Productivity | C7: Productivity | D7: Yield | E7: Yi | F7: Product Yield | G7: PY | H7: Weight Gain | I7: Weight Gain | J7: WG | K7: Change in animal weight relative to a baseline (usually weight at the start of an experiment) over a specified time period. | L7: Please try to standardise to g per animal per day (g/individual/day). Default unit is unit/individual (e.g kg/cow) unless otherwise stated. Values for this outcome can be negative (the animal loses weight) or positive. | M7: g/individual/day SGR (Specific Growth Rate) | O7: Y | P7: p | Q7: N | R7: Not Sure | S7: FALSE
A8: 119.1 | B8: Productivity | C8: Productivity | D8: Yield | E8: Yi | F8: Product Yield | G8: PY | H8: Meat Yield | I8: Meat Yield | J8: MeY | K8: The total weight of the animal or meat parts of it. | L8: This should not be an increase from a baseline weight (this is recorded under the Weight Gain outcome). Please try and standardise units kg/individual, you may specify the type of meat or weight measurement though (e.g. carcass weight kg/individual).' Specify if carcass is hot or cold, take both if given;Default unit is unit/individual (e.g kg/cow) unless otherwise statement | M8: kg/individual | O8: N | P8: p | Q8: N | R8: Y | S8: FALSE
A9: 119.2 | B9: Productivity | C9: Productivity | D9: Yield | E9: Yi | F9: Product Yield | G9: PY | H9: Milk Yield | I9: Milk Yield | J9: MiY | K9: Milk yields. Please specify absolute values and not change in yield relative to a base value. | L9: Please try and standardise to litres per animal per day (l/individual/day). | M9: l/individual/day | O9: N | P9: p | Q9: N | R9: Y | S9: FALSE
A10: 119.3 | B10: Productivity | C10: Productivity | D10: Yield | E10: Yi | F10: Product Yield | G10: PY | H10: Egg Yield | I10: Egg Yield | J10: EgY | K10: Egg yields, such as number of eggs per hen(s) per day(s). | L10: Please try and standardise units to eggs per one individual per day. (eggs/individual/day). | M10: eggs/hen/day | O10: N | P10: p | Q10: N | R10: Y | S10: FALSE
A11: 119.4 | B11: Productivity | C11: Productivity | D11: Yield | E11: Yi | F11: Product Yield | G11: PY | H11: Other Animal Product Yield | I11: Animal Yield (Other) | J11: OAY | K11: Animal products that are not meat, egg, milk or offsping, for example wool, hides and honey. | M11: See any units for other animal outcomes. | O11: N | P11: p | Q11: N | R11: Y | S11: FALSE
A12: 119.5 | B12: Productivity | C12: Productivity | D12: Yield | E12: Yi | F12: Product Yield | G12: PY | H12: Reproductive Yield | I12: Repro Yield | J12: RepY | K12: Number of offpsring produced. This also includes % calving rate or similar. | M12: #; % | O12: N | P12: p | Q12: N | R12: Y | S12: FALSE
A13: 400 | B13: Other | C13: Other | D13: Livestock Diet | E13: Li | F13: Feed Intake | G13: FI | H13: Feed Intake | I13: Feed Intake | J13: FeI | K13: The amount of a diet consumed per unit time. | O13: N | P13: n | Q13: N | R13: Y | S13: FALSE
A14: 102 | B14: Productivity | C14: Productivity | D14: Yield | E14: Yi | F14: Non-Product Yield | G14: NPY | H14: Crop Residue Yield | I14: Residue Yield | J14: ResY | K14: Crop residue yield is the amount of crop biomass left over once the crop products has been harvested. For example maize grain is a crop product, the stover and cobs leftover after harvesting the maize grain are crop residues. | L14: Entire plant biomass can also be recorded under this outcome if product or biomass yields are not available ( make sure the unit reflects this). | M14: t/ha;kg/ha | O14: N | P14: p | Q14: N | R14: Y | S14: FALSE
A15: 120 | B15: Productivity | C15: Productivity | D15: Economics | E15: Ec | F15: Income | G15: In | H15: Gross Return | I15: Gross Return | J15: GR | K15: Total income, revenue or returns without consideration of costs. | L15: Please standardize area denominators to ha where possible. Convert currences to USD (present $ in units) if exchange rates are presented in the paper. Record values in non-USD currency using the ISO 4217 country currency code in the units. | M15: USD; USD/ha; USD/yr | O15: N | P15: p | Q15: N | R15: Y | S15: FALSE
A16: 124 | B16: Productivity | C16: Productivity | D16: Economics | E16: Ec | F16: Income | G16: In | H16: Net Return | I16: Net Return | J16: NR | K16: Net returns = income - total costs. Values for this outcome can be negative or positive. | L16: Please standardize area denominators to ha where possible. Convert currences to USD (present $ in units) if exchange rates are presented in the paper. Record values in non-USD currency using the ISO 4217 country currency code in the units. | M16: USD; USD/ha; USD/yr | O16: Y | P16: p | Q16: N | R16: Y | S16: FALSE
A17: 124.1 | B17: Productivity | C17: Productivity | D17: Economics | E17: Ec | F17: Income | G17: In | H17: Gross Margin | I17: Gross Margin | J17: GM | K17: Gross margin = revenue - variable costs. Values for this outcome can be negative or positive. | L17: Please standardize area denominators to ha where possible. Convert local currences to USD (present $ in units) if exchange rates are presented in the paper. Record values in non-USD currency using the ISO 4217 country currency code in the units. | M17: USD; USD/ha; USD/yr | O17: Y | P17: p | Q17: N | R17: Y | S17: FALSE
